Workbook
Name BinDivisor: 'Overall Metrics'!$X$2
Name DynamicFilterColumnName: 'Overall Metrics'!#REF!
Name DynamicFilterForceCalculationRange: HistogramBins[[Dynamic Filter Bin]:[Dynamic Filter Frequency]]
Name DynamicFilterSourceColumnRange: 'Overall Metrics'!$X$4
Name DynamicFilterTableName: 'Overall Metrics'!#REF!
Name NoMetricMessage: 'Overall Metrics'!$X$3
Name NotAvailable: 'Overall Metrics'!$X$2
Name ValidBooleansDefaultFalse: Misc!$G$2:$G$5
Name ValidEdgeStyles: Misc!$B$2:$B$11
Name ValidEdgeVisibilities: Misc!$A$2:$A$7
Name ValidGroupShapes: Misc!$E$2:$E$19
Name ValidGroupVisibilities: Misc!$F$2:$F$7
Name ValidVertexLabelPositions: Misc!$H$2:$H$21
Name ValidVertexShapes: Misc!$D$2:$D$23
Name ValidVertexVisibilities: Misc!$C$2:$C$9

Sheet Edges
C1: Visual Properties | H1: Labels | K1: Graph Metrics | L1: Do Not Edit | N1: Other Columns
A2: Vertex 1 | B2: Vertex 2 | C2: Color | D2: Width | E2: Style | F2: Opacity | G2: Visibility | H2: Label | I2: Label Text Color | J2: Label Font Size | K2: Reciprocated? | L2: ID | M2: Dynamic Filter | N2: Add Your Own Columns Here | O2: Relationship | P2: Relationship Date (UTC) | Q2: Tweet | R2: URLs in Tweet | S2: Domains in Tweet | T2: Hashtags in Tweet | U2: Tweet Date (UTC) | V2: Twitter Page for Tweet | W2: Latitude | X2: Longitude | Y2: Imported ID | Z2: In-Reply-To Tweet ID
A3: maxsmithtweet | B3: tesco | K3: No | L3: 3 | M3: =IF(AND(OR(NOT(ISNUMBER(Edges[Relationship Date (UTC)])), Edges[Relationship Date (UTC)] >= Misc!$O$2), OR(NOT(ISNUMBER(Edges[Relationship Date (UTC)])), Edges[Relationship Date (UTC)] <= Misc!$P$2),OR(NOT(ISNUMBER(Edges[Tweet Date (UTC)])), Edges[Tweet Date (UTC)] >= Misc!$O$3), OR(NOT(ISNUMBER(Edges[Tweet Date (UTC)])), Edges[Tweet Date (UTC)] <= Misc!$P$3),TRUE), TRUE, FALSE) -> TRUE | O3: Mentions | P3: 43045.409 | Q3: RT @Tesco: The definitive WWII campaign at an unbeatable price. Get #CODWWII for £44 at Tesco now, in-store and online. https://t.co/yEgyxR… | T3: codwwii | U3: 43045.409 | V3: https://twitter.com/#!/maxsmithtweet/status/927472778378399744 | Y3: 927472778378399744
A4: xpoze_aqua | B4: codww2intel | K4: No | L4: 4 | M4: =IF(AND(OR(NOT(ISNUMBER(Edges[Relationship Date (UTC)])), Edges[Relationship Date (UTC)] >= Misc!$O$2), OR(NOT(ISNUMBER(Edges[Relationship Date (UTC)])), Edges[Relationship Date (UTC)] <= Misc!$P$2),OR(NOT(ISNUMBER(Edges[Tweet Date (UTC)])), Edges[Tweet Date (UTC)] >= Misc!$O$3), OR(NOT(ISNUMBER(Edges[Tweet Date (UTC)])), Edges[Tweet Date (UTC)] <= Misc!$P$3),TRUE), TRUE, FALSE) -> TRUE | O4: Mentions | P4: 43045.409 | Q4: RT @CoDWW2Intel: Here's all of the 10 Prestige + Prestige Master Icons in CoD WWII! #CoDWW2 #CoDWWII Credit: Reddit (LackingAGoodName) htt… | T4: codww2 codwwii | U4: 43045.409 | V4: https://twitter.com/#!/xpoze_aqua/status/927472791607226369 | Y4: 927472791607226369
A5: infused_vanq | B5: astrogaminguk | K5: No | L5: 5 | M5: =IF(AND(OR(NOT(ISNUMBER(Edges[Relationship Date (UTC)])), Edges[Relationship Date (UTC)] >= Misc!$O$2), OR(NOT(ISNUMBER(Edges[Relationship Date (UTC)])), Edges[Relationship Date (UTC)] <= Misc!$P$2),OR(NOT(ISNUMBER(Edges[Tweet Date (UTC)])), Edges[Tweet Date (UTC)] >= Misc!$O$3), OR(NOT(ISNUMBER(Edges[Tweet Date (UTC)])), Edges[Tweet Date (UTC)] <= Misc!$P$3),TRUE), TRUE, FALSE) -> TRUE | O5: Mentions | P5: 43045.409 | Q5: RT @ASTROGamingUK: The first Monday after #CODWWII and the workforce is on the move! #ASTROfamily https://t.co/FTfIdTpNRF | T5: codwwii astrofamily | U5: 43045.409 | V5: https://twitter.com/#!/infused_vanq/status/927472805347823616 | Y5: 927472805347823616
A6: loperosal | B6: thegrefgyt | K6: No | L6: 6 | M6: =IF(AND(OR(NOT(ISNUMBER(Edges[Relationship Date (UTC)])), Edges[Relationship Date (UTC)] >= Misc!$O$2), OR(NOT(ISNUMBER(Edges[Relationship Date (UTC)])), Edges[Relationship Date (UTC)] <= Misc!$P$2),OR(NOT(ISNUMBER(Edges[Tweet Date (UTC)])), Edges[Tweet Date (UTC)] >= Misc!$O$3), OR(NOT(ISNUMBER(Edges[Tweet Date (UTC)])), Edges[Tweet Date (UTC)] <= Misc!$P$3),TRUE), TRUE, FALSE) -> TRUE | O6: Mentions | P6: 43045.409 | Q6: RT @TheGrefgYT: ¡NUEVO VÍDEO! 😡😠 #CODWWII ME BANEA 😠😡 RT Chicos!! 🙌🏻🔥▶️ https://t.co/78KdJQv8Ij https://t.co/heBObzc6N5 | R6: https://www.youtube.com/watch?v=-W5I1VoVWiI&feature=youtu.be | S6: youtube.com | T6: codwwii | U6: 43045.409 | V6: https://twitter.com/#!/loperosal/status/927472817385365504 | Y6: 927472817385365504
A7: onany_yarou | B7: onany_yarou | K7: No | L7: 7 | M7: =IF(AND(OR(NOT(ISNUMBER(Edges[Relationship Date (UTC)])), Edges[Relationship Date (UTC)] >= Misc!$O$2), OR(NOT(ISNUMBER(Edges[Relationship Date (UTC)])), Edges[Relationship Date (UTC)] <= Misc!$P$2),OR(NOT(ISNUMBER(Edges[Tweet Date (UTC)])), Edges[Tweet Date (UTC)] >= Misc!$O$3), OR(NOT(ISNUMBER(Edges[Tweet Date (UTC)])), Edges[Tweet Date (UTC)] <= Misc!$P$3),TRUE), TRUE, FALSE) -> TRUE | O7: Tweet | P7: 43045.409 | Q7: codwwⅡを買いました笑 | U7: 43045.409 | V7: https://twitter.com/#!/onany_yarou/status/927472822477135874 | Y7: 927472822477135874
A8: tweetmeista | B8: tweetmeista | K8: No | L8: 8 | M8: =IF(AND(OR(NOT(ISNUMBER(Edges[Relationship Date (UTC)])), Edges[Relationship Date (UTC)] >= Misc!$O$2), OR(NOT(ISNUMBER(Edges[Relationship Date (UTC)])), Edges[Relationship Date (UTC)] <= Misc!$P$2),OR(NOT(ISNUMBER(Edges[Tweet Date (UTC)])), Edges[Tweet Date (UTC)] >= Misc!$O$3), OR(NOT(ISNUMBER(Edges[Tweet Date (UTC)])), Edges[Tweet Date (UTC)] <= Misc!$P$3),TRUE), TRUE, FALSE) -> TRUE | O8: Tweet | P8: 43045.409 | Q8: #activision #CODWWII How can I actually log a support case?All your website does is offer solutions that don’t apply.Why is it so difficult? | T8: activision codwwii | U8: 43045.409 | V8: https://twitter.com/#!/tweetmeista/status/927472825014849537 | Y8: 927472825014849537
A9: gooya_58p | B9: decksplash | K9: No | L9: 9 | M9: =IF(AND(OR(NOT(ISNUMBER(Edges[Relationship Date (UTC)])), Edges[Relationship Date (UTC)] >= Misc!$O$2), OR(NOT(ISNUMBER(Edges[Relationship Date (UTC)])), Edges[Relationship Date (UTC)] <= Misc!$P$2),OR(NOT(ISNUMBER(Edges[Tweet Date (UTC)])), Edges[Tweet Date (UTC)] >= Misc!$O$3), OR(NOT(ISNUMBER(Edges[Tweet Date (UTC)])), Edges[Tweet Date (UTC)] <= Misc!$P$3),TRUE), TRUE, FALSE) -> TRUE | O9: Mentions | P9: 43045.409 | Q9: RT @Decksplash: Ask your mom for money to play COD... ORRRR play Decksplash RIGHT NOW for FREE! #CODWWII #Decksplash https://t.co/PUmMqBTPc… | T9: codwwii decksplash | U9: 43045.409 | V9: https://twitter.com/#!/gooya_58p/status/927472863119945728 | Y9: 927472863119945728
A10: 5xe49shsufp8w4i | B10: arabiagtx | K10: No | L10: 10 | M10: =IF(AND(OR(NOT(ISNUMBER(Edges[Relationship Date (UTC)])), Edges[Relationship Date (UTC)] >= Misc!$O$2), OR(NOT(ISNUMBER(Edges[Relationship Date (UTC)])), Edges[Relationship Date (UTC)] <= Misc!$P$2),OR(NOT(ISNUMBER(Edges[Tweet Date (UTC)])), Edges[Tweet Date (UTC)] >= Misc!$O$3), OR(NOT(ISNUMBER(Edges[Tweet Date (UTC)])), Edges[Tweet Date (UTC)] <= Misc!$P$3),TRUE), TRUE, FALSE) -> TRUE | O10: Mentions | P10: 43045.409 | Q10: RT @ArabiaGtx: هدية للمتابعين نسخة Duluxe من #CODWWII لـXB1 أو PS4 او 100 دولار ستور: الشروط: - متابع الحساب - رتويت للتغريدة - منشن أصدقا… | T10: codwwii | U10: 43045.409 | V10: https://twitter.com/#!/5xe49shsufp8w4i/status/927472863241744384 | Y10: 927472863241744384
A11: bwdgalaxy3000 | B11: eaa_tw | K11: No | L11: 11 | M11: =IF(AND(OR(NOT(ISNUMBER(Edges[Relationship Date (UTC)])), Edges[Relationship Date (UTC)] >= Misc!$O$2), OR(NOT(ISNUMBER(Edges[Relationship Date (UTC)])), Edges[Relationship Date (UTC)] <= Misc!$P$2),OR(NOT(ISNUMBER(Edges[Tweet Date (UTC)])), Edges[Tweet Date (UTC)] >= Misc!$O$3), OR(NOT(ISNUMBER(Edges[Tweet Date (UTC)])), Edges[Tweet Date (UTC)] <= Misc!$P$3),TRUE), TRUE, FALSE) -> TRUE | O11: Mentions | P11: 43045.409 | Q11: RT @EAA_tw: CoD:WWII：サーバーの接続問題や巻き戻し現象を修正！ 原因は予想以上の人気によるアクセス集中 #CoDWWII https://t.co/iMtnw5W2Tl https://t.co/VQkd1m6D3S | R11: http://fpsjp.net/archives/294374 | S11: fpsjp.net | T11: codwwii | U11: 43045.409 | V11: https://twitter.com/#!/bwdgalaxy3000/status/927472877040943105 | Y11: 927472877040943105
A12: sakana3385 | B12: sakana3385 | K12: No | L12: 12 | M12: =IF(AND(OR(NOT(ISNUMBER(Edges[Relationship Date (UTC)])), Edges[Relationship Date (UTC)] >= Misc!$O$2), OR(NOT(ISNUMBER(Edges[Relationship Date (UTC)])), Edges[Relationship Date (UTC)] <= Misc!$P$2),OR(NOT(ISNUMBER(Edges[Tweet Date (UTC)])), Edges[Tweet Date (UTC)] >= Misc!$O$3), OR(NOT(ISNUMBER(Edges[Tweet Date (UTC)])), Edges[Tweet Date (UTC)] <= Misc!$P$3),TRUE), TRUE, FALSE) -> TRUE | O12: Tweet | P12: 43045.409 | Q12: https://t.co/dC9A3bfFAe うぐっ | R12: https://www.jp.playstation.com/blog/detail/5914/20171030-codwwii.html | S12: playstation.com | U12: 43045.409 | V12: https://twitter.com/#!/sakana3385/status/927472920967856128 | Y12: 927472920967856128 | Z12: 927384214609080320
A13: tonytony_555 | B13: eaa_tw | K13: No | L13: 13 | M13: =IF(AND(OR(NOT(ISNUMBER(Edges[Relationship Date (UTC)])), Edges[Relationship Date (UTC)] >= Misc!$O$2), OR(NOT(ISNUMBER(Edges[Relationship Date (UTC)])), Edges[Relationship Date (UTC)] <= Misc!$P$2),OR(NOT(ISNUMBER(Edges[Tweet Date (UTC)])), Edges[Tweet Date (UTC)] >= Misc!$O$3), OR(NOT(ISNUMBER(Edges[Tweet Date (UTC)])), Edges[Tweet Date (UTC)] <= Misc!$P$3),TRUE), TRUE, FALSE) -> TRUE | O13: Mentions | P13: 43045.409 | Q13: RT @EAA_tw: CoD:WWII： プレステージアイコン全10種と、プレステージマスターアイコンが判明 #CoDWWII https://t.co/PSkNgKtZ3K https://t.co/41SmfDFFhy | R13: http://fpsjp.net/archives/294392 | S13: fpsjp.net | T13: codwwii | U13: 43045.409 | V13: https://twitter.com/#!/tonytony_555/status/927472949321281537 | Y13: 927472949321281537
A14: tanakan_1st | B14: eaa_tw | K14: No | L14: 14 | M14: =IF(AND(OR(NOT(ISNUMBER(Edges[Relationship Date (UTC)])), Edges[Relationship Date (UTC)] >= Misc!$O$2), OR(NOT(ISNUMBER(Edges[Relationship Date (UTC)])), Edges[Relationship Date (UTC)] <= Misc!$P$2),OR(NOT(ISNUMBER(Edges[Tweet Date (UTC)])), Edges[Tweet Date (UTC)] >= Misc!$O$3), OR(NOT(ISNUMBER(Edges[Tweet Date (UTC)])), Edges[Tweet Date (UTC)] <= Misc!$P$3),TRUE), TRUE, FALSE) -> TRUE | O14: Mentions | P14: 43045.409 | Q14: RT @EAA_tw: CoD:WWII：サーバーの接続問題や巻き戻し現象を修正！ 原因は予想以上の人気によるアクセス集中 #CoDWWII https://t.co/iMtnw5W2Tl https://t.co/VQkd1m6D3S | R14: http://fpsjp.net/archives/294374 | S14: fpsjp.net | T14: codwwii | U14: 43045.409 | V14: https://twitter.com/#!/tanakan_1st/status/927472959702286337 | Y14: 927472959702286337
A15: munchkinletty | B15: munchkinletty | K15: No | L15: 15 | M15: =IF(AND(OR(NOT(ISNUMBER(Edges[Relationship Date (UTC)])), Edges[Relationship Date (UTC)] >= Misc!$O$2), OR(NOT(ISNUMBER(Edges[Relationship Date (UTC)])), Edges[Relationship Date (UTC)] <= Misc!$P$2),OR(NOT(ISNUMBER(Edges[Tweet Date (UTC)])), Edges[Tweet Date (UTC)] >= Misc!$O$3), OR(NOT(ISNUMBER(Edges[Tweet Date (UTC)])), Edges[Tweet Date (UTC)] <= Misc!$P$3),TRUE), TRUE, FALSE) -> TRUE | O15: Tweet | P15: 43045.409 | Q15: Me to myself: "Ima go to sleep after this match" Also me: *starts another match* 😴 #CODWWII #gaming | T15: codwwii gaming | U15: 43045.409 | V15: https://twitter.com/#!/munchkinletty/status/927472759420022784 | Y15: 927472759420022784
A16: johnstezer | B16: munchkinletty | K16: No | L16: 16 | M16: =IF(AND(OR(NOT(ISNUMBER(Edges[Relationship Date (UTC)])), Edges[Relationship Date (UTC)] >= Misc!$O$2), OR(NOT(ISNUMBER(Edges[Relationship Date (UTC)])), Edges[Relationship Date (UTC)] <= Misc!$P$2),OR(NOT(ISNUMBER(Edges[Tweet Date (UTC)])), Edges[Tweet Date (UTC)] >= Misc!$O$3), OR(NOT(ISNUMBER(Edges[Tweet Date (UTC)])), Edges[Tweet Date (UTC)] <= Misc!$P$3),TRUE), TRUE, FALSE) -> TRUE | O16: Mentions | P16: 43045.409 | Q16: RT @MunchkinLetty: Me to myself: "Ima go to sleep after this match" Also me: *starts another match* 😴 #CODWWII #gaming | T16: codwwii gaming | U16: 43045.409 | V16: https://twitter.com/#!/johnstezer/status/927472960973295617 | Y16: 927472960973295617
A17: quent48911092 | B17: game_collection | K17: No | L17: 17 | M17: =IF(AND(OR(NOT(ISNUMBER(Edges[Relationship Date (UTC)])), Edges[Relationship Date (UTC)] >= Misc!$O$2), OR(NOT(ISNUMBER(Edges[Relationship Date (UTC)])), Edges[Relationship Date (UTC)] <= Misc!$P$2),OR(NOT(ISNUMBER(Edges[Tweet Date (UTC)])), Edges[Tweet Date (UTC)] >= Misc!$O$3), OR(NOT(ISNUMBER(Edges[Tweet Date (UTC)])), Edges[Tweet Date (UTC)] <= Misc!$P$3),TRUE), TRUE, FALSE) -> TRUE | O17: Mentions | P17: 43045.409 | Q17: Win #CODWWII on #PS4 or #XboxOne! RT + Follow @postabargain &amp; @game_collection and enter here: https://t.co/euTqBOogfK | R17: https://gleam.io/oyimv-nqfxU4?l=http%3A%2F%2Fwww.postabargain.co.uk%2Fpages%2Fcompetition%2F2017%2Fcall-of-duty-wwii-giveaway | S17: gleam.io | T17: codwwii ps4 xboxone | U17: 43045.409 | V17: https://twitter.com/#!/quent48911092/status/927472920607186944 | Y17: 927472920607186944
A18: quent48911092 | B18: postabargain | K18: No | L18: 18 | M18: =IF(AND(OR(NOT(ISNUMBER(Edges[Relationship Date (UTC)])), Edges[Relationship Date (UTC)] >= Misc!$O$2), OR(NOT(ISNUMBER(Edges[Relationship Date (UTC)])), Edges[Relationship Date (UTC)] <= Misc!$P$2),OR(NOT(ISNUMBER(Edges[Tweet Date (UTC)])), Edges[Tweet Date (UTC)] >= Misc!$O$3), OR(NOT(ISNUMBER(Edges[Tweet Date (UTC)])), Edges[Tweet Date (UTC)] <= Misc!$P$3),TRUE), TRUE, FALSE) -> TRUE | O18: Mentions | P18: 43045.409 | Q18: Win #CODWWII on #PS4 or #XboxOne! RT + Follow @postabargain &amp; @game_collection and enter here: https://t.co/euTqBOogfK | R18: https://gleam.io/oyimv-nqfxU4?l=http%3A%2F%2Fwww.postabargain.co.uk%2Fpages%2Fcompetition%2F2017%2Fcall-of-duty-wwii-giveaway | S18: gleam.io | T18: codwwii ps4 xboxone | U18: 43045.409 | V18: https://twitter.com/#!/quent48911092/status/927472920607186944 | Y18: 927472920607186944
A19: quent48911092 | B19: game_collection | K19: No | L19: 19 | M19: =IF(AND(OR(NOT(ISNUMBER(Edges[Relationship Date (UTC)])), Edges[Relationship Date (UTC)] >= Misc!$O$2), OR(NOT(ISNUMBER(Edges[Relationship Date (UTC)])), Edges[Relationship Date (UTC)] <= Misc!$P$2),OR(NOT(ISNUMBER(Edges[Tweet Date (UTC)])), Edges[Tweet Date (UTC)] >= Misc!$O$3), OR(NOT(ISNUMBER(Edges[Tweet Date (UTC)])), Edges[Tweet Date (UTC)] <= Misc!$P$3),TRUE), TRUE, FALSE) -> TRUE | O19: Mentions | P19: 43045.409 | Q19: Enter &amp; help me win this Call of Duty WWII competition by @postabargain &amp; @game_collection #CODWWII https://t.co/euTqBOFREk | R19: https://gleam.io/oyimv-nqfxU4?l=http%3A%2F%2Fwww.postabargain.co.uk%2Fpages%2Fcompetition%2F2017%2Fcall-of-duty-wwii-giveaway | S19: gleam.io | T19: codwwii | U19: 43045.409 | V19: https://twitter.com/#!/quent48911092/status/927472982364246016 | Y19: 927472982364246016
A20: quent48911092 | B20: postabargain | K20: No | L20: 20 | M20: =IF(AND(OR(NOT(ISNUMBER(Edges[Relationship Date (UTC)])), Edges[Relationship Date (UTC)] >= Misc!$O$2), OR(NOT(ISNUMBER(Edges[Relationship Date (UTC)])), Edges[Relationship Date (UTC)] <= Misc!$P$2),OR(NOT(ISNUMBER(Edges[Tweet Date (UTC)])), Edges[Tweet Date (UTC)] >= Misc!$O$3), OR(NOT(ISNUMBER(Edges[Tweet Date (UTC)])), Edges[Tweet Date (UTC)] <= Misc!$P$3),TRUE), TRUE, FALSE) -> TRUE | O20: Mentions | P20: 43045.409 | Q20: Enter &amp; help me win this Call of Duty WWII competition by @postabargain &amp; @game_collection #CODWWII https://t.co/euTqBOFREk | R20: https://gleam.io/oyimv-nqfxU4?l=http%3A%2F%2Fwww.postabargain.co.uk%2Fpages%2Fcompetition%2F2017%2Fcall-of-duty-wwii-giveaway | S20: gleam.io | T20: codwwii | U20: 43045.409 | V20: https://twitter.com/#!/quent48911092/status/927472982364246016 | Y20: 927472982364246016
A21: 10veax | B21: apex_clan1 | K21: No | L21: 21 | M21: =IF(AND(OR(NOT(ISNUMBER(Edges[Relationship Date (UTC)])), Edges[Relationship Date (UTC)] >= Misc!$O$2), OR(NOT(ISNUMBER(Edges[Relationship Date (UTC)])), Edges[Relationship Date (UTC)] <= Misc!$P$2),OR(NOT(ISNUMBER(Edges[Tweet Date (UTC)])), Edges[Tweet Date (UTC)] >= Misc!$O$3), OR(NOT(ISNUMBER(Edges[Tweet Date (UTC)])), Edges[Tweet Date (UTC)] <= Misc!$P$3),TRUE), TRUE, FALSE) -> TRUE | O21: Mentions | P21: 43045.409 | Q21: RT @ApeX_Clan1: Une des maps trouvés dans les fichiers de #CODWWII pour le DLC 1... #RT si tu l'as reconnu 👀 https://t.co/Q3BJmgQAOZ | T21: codwwii rt | U21: 43045.409 | V21: https://twitter.com/#!/10veax/status/927473028040183808 | Y21: 927473028040183808
A22: regen2206 | B22: decksplash | K22: No | L22: 22 | M22: =IF(AND(OR(NOT(ISNUMBER(Edges[Relationship Date (UTC)])), Edges[Relationship Date (UTC)] >= Misc!$O$2), OR(NOT(ISNUMBER(Edges[Relationship Date (UTC)])), Edges[Relationship Date (UTC)] <= Misc!$P$2),OR(NOT(ISNUMBER(Edges[Tweet Date (UTC)])), Edges[Tweet Date (UTC)] >= Misc!$O$3), OR(NOT(ISNUMBER(Edges[Tweet Date (UTC)])), Edges[Tweet Date (UTC)] <= Misc!$P$3),TRUE), TRUE, FALSE) -> TRUE | O22: Mentions | P22: 43045.409 | Q22: RT @Decksplash: Ask your mom for money to play COD... ORRRR play Decksplash RIGHT NOW for FREE! #CODWWII #Decksplash https://t.co/PUmMqBTPc… | T22: codwwii decksplash | U22: 43045.409 | V22: https://twitter.com/#!/regen2206/status/927473029256396800 | Y22: 927473029256396800
A23: gibelloscar | B23: jinhix | K23: No | L23: 23 | M23: =IF(AND(OR(NOT(ISNUMBER(Edges[Relationship Date (UTC)])), Edges[Relationship Date (UTC)] >= Misc!$O$2), OR(NOT(ISNUMBER(Edges[Relationship Date (UTC)])), Edges[Relationship Date (UTC)] <= Misc!$P$2),OR(NOT(ISNUMBER(Edges[Tweet Date (UTC)])), Edges[Tweet Date (UTC)] >= Misc!$O$3), OR(NOT(ISNUMBER(Edges[Tweet Date (UTC)])), Edges[Tweet Date (UTC)] <= Misc!$P$3),TRUE), TRUE, FALSE) -> TRUE | O23: Mentions | P23: 43045.409 | Q23: RT @jinhix: Mañana libro chic@s, si veo mucho apoyo en este tweet hoy me compro el #CODWWII y entre hoy y mañana me hago unos directos con… | T23: codwwii | U23: 43045.409 | V23: https://twitter.com/#!/gibelloscar/status/927473036172955649 | Y23: 927473036172955649
A24: joeypescione | B24: codww2intel | K24: No | L24: 24 | M24: =IF(AND(OR(NOT(ISNUMBER(Edges[Relationship Date (UTC)])), Edges[Relationship Date (UTC)] >= Misc!$O$2), OR(NOT(ISNUMBER(Edges[Relationship Date (UTC)])), Edges[Relationship Date (UTC)] <= Misc!$P$2),OR(NOT(ISNUMBER(Edges[Tweet Date (UTC)])), Edges[Tweet Date (UTC)] >= Misc!$O$3), OR(NOT(ISNUMBER(Edges[Tweet Date (UTC)])), Edges[Tweet Date (UTC)] <= Misc!$P$3),TRUE), TRUE, FALSE) -> TRUE | O24: Mentions | P24: 43045.41 | Q24: RT @CoDWW2Intel: RT if you agree the Snipers and BAR need nerfing in #CoDWWII What else do you feel needs changing? | T24: codwwii | U24: 43045.41 | V24: https://twitter.com/#!/joeypescione/status/927473076312399872 | Y24: 927473076312399872
A25: usmaan_ali | B25: michaelcondrey | K25: No | L25: 25 | M25: =IF(AND(OR(NOT(ISNUMBER(Edges[Relationship Date (UTC)])), Edges[Relationship Date (UTC)] >= Misc!$O$2), OR(NOT(ISNUMBER(Edges[Relationship Date (UTC)])), Edges[Relationship Date (UTC)] <= Misc!$P$2),OR(NOT(ISNUMBER(Edges[Tweet Date (UTC)])), Edges[Tweet Date (UTC)] >= Misc!$O$3), OR(NOT(ISNUMBER(Edges[Tweet Date (UTC)])), Edges[Tweet Date (UTC)] <= Misc!$P$3),TRUE), TRUE, FALSE) -> TRUE | O25: Mentions | P25: 43045.41 | Q25: RT @FaZeJev: @MichaelCondrey Hey is there a Dark Matter/Exclusion Zone equivalent in CODWWII? I need to know if contemplating throwing myse… | U25: 43045.41 | V25: https://twitter.com/#!/usmaan_ali/status/927473186287112192 | Y25: 927473186287112192
A26: usmaan_ali | B26: fazejev | K26: No | L26: 26 | M26: =IF(AND(OR(NOT(ISNUMBER(Edges[Relationship Date (UTC)])), Edges[Relationship Date (UTC)] >= Misc!$O$2), OR(NOT(ISNUMBER(Edges[Relationship Date (UTC)])), Edges[Relationship Date (UTC)] <= Misc!$P$2),OR(NOT(ISNUMBER(Edges[Tweet Date (UTC)])), Edges[Tweet Date (UTC)] >= Misc!$O$3), OR(NOT(ISNUMBER(Edges[Tweet Date (UTC)])), Edges[Tweet Date (UTC)] <= Misc!$P$3),TRUE), TRUE, FALSE) -> TRUE | O26: Mentions | P26: 43045.41 | Q26: RT @FaZeJev: @MichaelCondrey Hey is there a Dark Matter/Exclusion Zone equivalent in CODWWII? I need to know if contemplating throwing myse… | U26: 43045.41 | V26: https://twitter.com/#!/usmaan_ali/status/927473186287112192 | Y26: 927473186287112192
A27: acesxmet | B27: vweazzy | K27: No | L27: 27 | M27: =IF(AND(OR(NOT(ISNUMBER(Edges[Relationship Date (UTC)])), Edges[Relationship Date (UTC)] >= Misc!$O$2), OR(NOT(ISNUMBER(Edges[Relationship Date (UTC)])), Edges[Relationship Date (UTC)] <= Misc!$P$2),OR(NOT(ISNUMBER(Edges[Tweet Date (UTC)])), Edges[Tweet Date (UTC)] >= Misc!$O$3), OR(NOT(ISNUMBER(Edges[Tweet Date (UTC)])), Edges[Tweet Date (UTC)] <= Misc!$P$3),TRUE), TRUE, FALSE) -> TRUE | O27: Mentions | P27: 43045.41 | Q27: RT @VWeazzy: Jemand hier der richtig sicke Embleme ingame macht #CODWWII? wenns sick ist, lass ich was springen👌🏻😝 | T27: codwwii | U27: 43045.41 | V27: https://twitter.com/#!/acesxmet/status/927473273125957633 | Y27: 927473273125957633
A28: kuromamonism | B28: rushgamingjp | K28: No | L28: 28 | M28: =IF(AND(OR(NOT(ISNUMBER(Edges[Relationship Date (UTC)])), Edges[Relationship Date (UTC)] >= Misc!$O$2), OR(NOT(ISNUMBER(Edges[Relationship Date (UTC)])), Edges[Relationship Date (UTC)] <= Misc!$P$2),OR(NOT(ISNUMBER(Edges[Tweet Date (UTC)])), Edges[Tweet Date (UTC)] >= Misc!$O$3), OR(NOT(ISNUMBER(Edges[Tweet Date (UTC)])), Edges[Tweet Date (UTC)] <= Misc!$P$3),TRUE), TRUE, FALSE) -> TRUE | O28: Mentions | P28: 43045.41 | Q28: RT @RushGamingJP: 【Rush Gaming発足記念キャンペーン！】 @RushGamingJPをフォロー＆このツイートをRTで、プロチームご用達公式コントローラー、「Scuf Impact 」を抽選で1名様にプレゼント! 応募期限：11/30 23:59 #r… | U28: 43045.41 | V28: https://twitter.com/#!/kuromamonism/status/927473311411453952 | Y28: 927473311411453952
A29: frankiethetell | B29: vatoisloco | K29: No | L29: 29 | M29: =IF(AND(OR(NOT(ISNUMBER(Edges[Relationship Date (UTC)])), Edges[Relationship Date (UTC)] >= Misc!$O$2), OR(NOT(ISNUMBER(Edges[Relationship Date (UTC)])), Edges[Relationship Date (UTC)] <= Misc!$P$2),OR(NOT(ISNUMBER(Edges[Tweet Date (UTC)])), Edges[Tweet Date (UTC)] >= Misc!$O$3), OR(NOT(ISNUMBER(Edges[Tweet Date (UTC)])), Edges[Tweet Date (UTC)] <= Misc!$P$3),TRUE), TRUE, FALSE) -> TRUE | O29: Mentions | P29: 43045.41 | Q29: RT @VatoIsLoco: How Does My #Mexican #Flag #CODWWII Emblem Look Took About 1hr But I'm Liking It #PS4 https://t.co/Fb9HMNZJVa | T29: mexican flag codwwii ps4 | U29: 43045.41 | V29: https://twitter.com/#!/frankiethetell/status/927473381154234368 | Y29: 927473381154234368
A30: gouki21451224 | B30: playstation_jp | K30: No | L30: 30 | M30: =IF(AND(OR(NOT(ISNUMBER(Edges[Relationship Date (UTC)])), Edges[Relationship Date (UTC)] >= Misc!$O$2), OR(NOT(ISNUMBER(Edges[Relationship Date (UTC)])), Edges[Relationship Date (UTC)] <= Misc!$P$2),OR(NOT(ISNUMBER(Edges[Tweet Date (UTC)])), Edges[Tweet Date (UTC)] >= Misc!$O$3), OR(NOT(ISNUMBER(Edges[Tweet Date (UTC)])), Edges[Tweet Date (UTC)] <= Misc!$P$3),TRUE), TRUE, FALSE) -> TRUE | O30: Mentions | P30: 43045.41 | Q30: RT @PlayStation_jp: 【PGW 2017】『コール オブ デューティ ワールドウォーII』ブースの対戦試遊をレポート！ 立体的で死角多数、マルチプレイヤー用追加マップ｢Carentan｣のスリリングな市街戦を体験！ https://t.co/RvyvhlLfi… | U30: 43045.41 | V30: https://twitter.com/#!/gouki21451224/status/927473392684429313 | Y30: 927473392684429313
A31: t_mogura42 | B31: eaa_tw | K31: No | L31: 31 | M31: =IF(AND(OR(NOT(ISNUMBER(Edges[Relationship Date (UTC)])), Edges[Relationship Date (UTC)] >= Misc!$O$2), OR(NOT(ISNUMBER(Edges[Relationship Date (UTC)])), Edges[Relationship Date (UTC)] <= Misc!$P$2),OR(NOT(ISNUMBER(Edges[Tweet Date (UTC)])), Edges[Tweet Date (UTC)] >= Misc!$O$3), OR(NOT(ISNUMBER(Edges[Tweet Date (UTC)])), Edges[Tweet Date (UTC)] <= Misc!$P$3),TRUE), TRUE, FALSE) -> TRUE | O31: Mentions | P31: 43045.41 | Q31: RT @EAA_tw: CoD:WWII： プレステージアイコン全10種と、プレステージマスターアイコンが判明 #CoDWWII https://t.co/PSkNgKtZ3K https://t.co/41SmfDFFhy | R31: http://fpsjp.net/archives/294392 | S31: fpsjp.net | T31: codwwii | U31: 43045.41 | V31: https://twitter.com/#!/t_mogura42/status/927473395230371840 | Y31: 927473395230371840
A32: introndepot | B32: game_collection | K32: No | L32: 32 | M32: =IF(AND(OR(NOT(ISNUMBER(Edges[Relationship Date (UTC)])), Edges[Relationship Date (UTC)] >= Misc!$O$2), OR(NOT(ISNUMBER(Edges[Relationship Date (UTC)])), Edges[Relationship Date (UTC)] <= Misc!$P$2),OR(NOT(ISNUMBER(Edges[Tweet Date (UTC)])), Edges[Tweet Date (UTC)] >= Misc!$O$3), OR(NOT(ISNUMBER(Edges[Tweet Date (UTC)])), Edges[Tweet Date (UTC)] <= Misc!$P$3),TRUE), TRUE, FALSE) -> TRUE | O32: Mentions | P32: 43045.411 | Q32: Win #CODWWII on #PS4 or #XboxOne! RT + Follow @postabargain &amp; @game_collection and enter here: https://t.co/x0IEyqkLVQ | R32: https://gleam.io/oyimv-f03kOk?l=http%3A%2F%2Fwww.postabargain.co.uk%2Fpages%2Fcompetition%2F2017%2Fcall-of-duty-wwii-giveaway | S32: gleam.io | T32: codwwii ps4 xboxone | U32: 43045.411 | V32: https://twitter.com/#!/introndepot/status/927473444689649665 | Y32: 927473444689649665
A33: introndepot | B33: postabargain | K33: No | L33: 33 | M33: =IF(AND(OR(NOT(ISNUMBER(Edges[Relationship Date (UTC)])), Edges[Relationship Date (UTC)] >= Misc!$O$2), OR(NOT(ISNUMBER(Edges[Relationship Date (UTC)])), Edges[Relationship Date (UTC)] <= Misc!$P$2),OR(NOT(ISNUMBER(Edges[Tweet Date (UTC)])), Edges[Tweet Date (UTC)] >= Misc!$O$3), OR(NOT(ISNUMBER(Edges[Tweet Date (UTC)])), Edges[Tweet Date (UTC)] <= Misc!$P$3),TRUE), TRUE, FALSE) -> TRUE | O33: Mentions | P33: 43045.411 | Q33: Win #CODWWII on #PS4 or #XboxOne! RT + Follow @postabargain &amp; @game_collection and enter here: https://t.co/x0IEyqkLVQ | R33: https://gleam.io/oyimv-f03kOk?l=http%3A%2F%2Fwww.postabargain.co.uk%2Fpages%2Fcompetition%2F2017%2Fcall-of-duty-wwii-giveaway | S33: gleam.io | T33: codwwii ps4 xboxone | U33: 43045.411 | V33: https://twitter.com/#!/introndepot/status/927473444689649665 | Y33: 927473444689649665
A34: shinobifist | B34: shinobifist | K34: No | L34: 34 | M34: =IF(AND(OR(NOT(ISNUMBER(Edges[Relationship Date (UTC)])), Edges[Relationship Date (UTC)] >= Misc!$O$2), OR(NOT(ISNUMBER(Edges[Relationship Date (UTC)])), Edges[Relationship Date (UTC)] <= Misc!$P$2),OR(NOT(ISNUMBER(Edges[Tweet Date (UTC)])), Edges[Tweet Date (UTC)] >= Misc!$O$3), OR(NOT(ISNUMBER(Edges[Tweet Date (UTC)])), Edges[Tweet Date (UTC)] <= Misc!$P$3),TRUE), TRUE, FALSE) -> TRUE | O34: Tweet | P34: 43045.411 | Q34: The BAR is so good in #CODWWII https://t.co/GcO7gtCJ2D | T34: codwwii | U34: 43045.411 | V34: https://twitter.com/#!/shinobifist/status/927473452008837121 | Y34: 927473452008837121
A35: vazquez151821 | B35: thegrefgyt | K35: No | L35: 35 | M35: =IF(AND(OR(NOT(ISNUMBER(Edges[Relationship Date (UTC)])), Edges[Relationship Date (UTC)] >= Misc!$O$2), OR(NOT(ISNUMBER(Edges[Relationship Date (UTC)])), Edges[Relationship Date (UTC)] <= Misc!$P$2),OR(NOT(ISNUMBER(Edges[Tweet Date (UTC)])), Edges[Tweet Date (UTC)] >= Misc!$O$3), OR(NOT(ISNUMBER(Edges[Tweet Date (UTC)])), Edges[Tweet Date (UTC)] <= Misc!$P$3),TRUE), TRUE, FALSE) -> TRUE | O35: Mentions | P35: 43045.411 | Q35: RT @TheGrefgYT: ¡NUEVO VÍDEO! 😡😠 #CODWWII ME BANEA 😠😡 RT Chicos!! 🙌🏻🔥▶️ https://t.co/78KdJQv8Ij https://t.co/heBObzc6N5 | R35: https://www.youtube.com/watch?v=-W5I1VoVWiI&feature=youtu.be | S35: youtube.com | T35: codwwii | U35: 43045.411 | V35: https://twitter.com/#!/vazquez151821/status/927473472837582848 | Y35: 927473472837582848
A36: eagle1928 | B36: eaa_tw | K36: No | L36: 36 | M36: =IF(AND(OR(NOT(ISNUMBER(Edges[Relationship Date (UTC)])), Edges[Relationship Date (UTC)] >= Misc!$O$2), OR(NOT(ISNUMBER(Edges[Relationship Date (UTC)])), Edges[Relationship Date (UTC)] <= Misc!$P$2),OR(NOT(ISNUMBER(Edges[Tweet Date (UTC)])), Edges[Tweet Date (UTC)] >= Misc!$O$3), OR(NOT(ISNUMBER(Edges[Tweet Date (UTC)])), Edges[Tweet Date (UTC)] <= Misc!$P$3),TRUE), TRUE, FALSE) -> TRUE | O36: Mentions | P36: 43045.411 | Q36: RT @EAA_tw: CoD:WWII：サーバーの接続問題や巻き戻し現象を修正！ 原因は予想以上の人気によるアクセス集中 #CoDWWII https://t.co/iMtnw5W2Tl https://t.co/VQkd1m6D3S | R36: http://fpsjp.net/archives/294374 | S36: fpsjp.net | T36: codwwii | U36: 43045.411 | V36: https://twitter.com/#!/eagle1928/status/927473494933327872 | Y36: 927473494933327872
A37: copper_kabell | B37: xboxodesperadoo | K37: No | L37: 37 | M37: =IF(AND(OR(NOT(ISNUMBER(Edges[Relationship Date (UTC)])), Edges[Relationship Date (UTC)] >= Misc!$O$2), OR(NOT(ISNUMBER(Edges[Relationship Date (UTC)])), Edges[Relationship Date (UTC)] <= Misc!$P$2),OR(NOT(ISNUMBER(Edges[Tweet Date (UTC)])), Edges[Tweet Date (UTC)] >= Misc!$O$3), OR(NOT(ISNUMBER(Edges[Tweet Date (UTC)])), Edges[Tweet Date (UTC)] <= Misc!$P$3),TRUE), TRUE, FALSE) -> TRUE | O37: Mentions | P37: 43045.411 | Q37: RT @WorldBestGaming: .@XBOXoDESPERADOo When someone tells you get to cover... you get to cover! 😂#CODWWII #WBGUP 👊 https://t.co/680eIBln6o | T37: codwwii wbgup | U37: 43045.411 | V37: https://twitter.com/#!/copper_kabell/status/927473503154163712 | Y37: 927473503154163712
A38: copper_kabell | B38: worldbestgaming | K38: No | L38: 38 | M38: =IF(AND(OR(NOT(ISNUMBER(Edges[Relationship Date (UTC)])), Edges[Relationship Date (UTC)] >= Misc!$O$2), OR(NOT(ISNUMBER(Edges[Relationship Date (UTC)])), Edges[Relationship Date (UTC)] <= Misc!$P$2),OR(NOT(ISNUMBER(Edges[Tweet Date (UTC)])), Edges[Tweet Date (UTC)] >= Misc!$O$3), OR(NOT(ISNUMBER(Edges[Tweet Date (UTC)])), Edges[Tweet Date (UTC)] <= Misc!$P$3),TRUE), TRUE, FALSE) -> TRUE | O38: Mentions | P38: 43045.411 | Q38: RT @WorldBestGaming: .@XBOXoDESPERADOo When someone tells you get to cover... you get to cover! 😂#CODWWII #WBGUP 👊 https://t.co/680eIBln6o | T38: codwwii wbgup | U38: 43045.411 | V38: https://twitter.com/#!/copper_kabell/status/927473503154163712 | Y38: 927473503154163712
A39: staceywwfc | B39: game_collection | K39: No | L39: 39 | M39: =IF(AND(OR(NOT(ISNUMBER(Edges[Relationship Date (UTC)])), Edges[Relationship Date (UTC)] >= Misc!$O$2), OR(NOT(ISNUMBER(Edges[Relationship Date (UTC)])), Edges[Relationship Date (UTC)] <= Misc!$P$2),OR(NOT(ISNUMBER(Edges[Tweet Date (UTC)])), Edges[Tweet Date (UTC)] >= Misc!$O$3), OR(NOT(ISNUMBER(Edges[Tweet Date (UTC)])), Edges[Tweet Date (UTC)] <= Misc!$P$3),TRUE), TRUE, FALSE) -> TRUE | O39: Mentions | P39: 43045.411 | Q39: Win #CODWWII on #PS4 or #XboxOne! RT + Follow @postabargain &amp; @game_collection and enter here: https://t.co/akDN6DztgC | R39: https://gleam.io/oyimv-0Xa1NB?l=http%3A%2F%2Fwww.postabargain.co.uk%2Fpages%2Fcompetition%2F2017%2Fcall-of-duty-wwii-giveaway | S39: gleam.io | T39: codwwii ps4 xboxone | U39: 43045.411 | V39: https://twitter.com/#!/staceywwfc/status/927473486695514112 | Y39: 927473486695514112
A40: staceywwfc | B40: postabargain | K40: No | L40: 40 | M40: =IF(AND(OR(NOT(ISNUMBER(Edges[Relationship Date (UTC)])), Edges[Relationship Date (UTC)] >= Misc!$O$2), OR(NOT(ISNUMBER(Edges[Relationship Date (UTC)])), Edges[Relationship Date (UTC)] <= Misc!$P$2),OR(NOT(ISNUMBER(Edges[Tweet Date (UTC)])), Edges[Tweet Date (UTC)] >= Misc!$O$3), OR(NOT(ISNUMBER(Edges[Tweet Date (UTC)])), Edges[Tweet Date (UTC)] <= Misc!$P$3),TRUE), TRUE, FALSE) -> TRUE | O40: Mentions | P40: 43045.411 | Q40: Win #CODWWII on #PS4 or #XboxOne! RT + Follow @postabargain &amp; @game_collection and enter here: https://t.co/akDN6DztgC | R40: https://gleam.io/oyimv-0Xa1NB?l=http%3A%2F%2Fwww.postabargain.co.uk%2Fpages%2Fcompetition%2F2017%2Fcall-of-duty-wwii-giveaway | S40: gleam.io | T40: codwwii ps4 xboxone | U40: 43045.411 | V40: https://twitter.com/#!/staceywwfc/status/927473486695514112 | Y40: 927473486695514112
A41: staceywwfc | B41: game_collection | K41: No | L41: 41 | M41: =IF(AND(OR(NOT(ISNUMBER(Edges[Relationship Date (UTC)])), Edges[Relationship Date (UTC)] >= Misc!$O$2), OR(NOT(ISNUMBER(Edges[Relationship Date (UTC)])), Edges[Relationship Date (UTC)] <= Misc!$P$2),OR(NOT(ISNUMBER(Edges[Tweet Date (UTC)])), Edges[Tweet Date (UTC)] >= Misc!$O$3), OR(NOT(ISNUMBER(Edges[Tweet Date (UTC)])), Edges[Tweet Date (UTC)] <= Misc!$P$3),TRUE), TRUE, FALSE) -> TRUE | O41: Mentions | P41: 43045.411 | Q41: Enter &amp; help me win this Call of Duty WWII competition by @postabargain &amp; @game_collection #CODWWII https://t.co/akDN6DhSp4 | R41: https://gleam.io/oyimv-0Xa1NB?l=http%3A%2F%2Fwww.postabargain.co.uk%2Fpages%2Fcompetition%2F2017%2Fcall-of-duty-wwii-giveaway | S41: gleam.io | T41: codwwii | U41: 43045.411 | V41: https://twitter.com/#!/staceywwfc/status/927473517532196864 | Y41: 927473517532196864
A42: staceywwfc | B42: postabargain | K42: No | L42: 42 | M42: =IF(AND(OR(NOT(ISNUMBER(Edges[Relationship Date (UTC)])), Edges[Relationship Date (UTC)] >= Misc!$O$2), OR(NOT(ISNUMBER(Edges[Relationship Date (UTC)])), Edges[Relationship Date (UTC)] <= Misc!$P$2),OR(NOT(ISNUMBER(Edges[Tweet Date (UTC)])), Edges[Tweet Date (UTC)] >= Misc!$O$3), OR(NOT(ISNUMBER(Edges[Tweet Date (UTC)])), Edges[Tweet Date (UTC)] <= Misc!$P$3),TRUE), TRUE, FALSE) -> TRUE | O42: Mentions | P42: 43045.411 | Q42: Enter &amp; help me win this Call of Duty WWII competition by @postabargain &amp; @game_collection #CODWWII https://t.co/akDN6DhSp4 | R42: https://gleam.io/oyimv-0Xa1NB?l=http%3A%2F%2Fwww.postabargain.co.uk%2Fpages%2Fcompetition%2F2017%2Fcall-of-duty-wwii-giveaway | S42: gleam.io | T42: codwwii | U42: 43045.411 | V42: https://twitter.com/#!/staceywwfc/status/927473517532196864 | Y42: 927473517532196864
A43: ayaneko0429 | B43: eaa_tw | K43: No | L43: 43 | M43: =IF(AND(OR(NOT(ISNUMBER(Edges[Relationship Date (UTC)])), Edges[Relationship Date (UTC)] >= Misc!$O$2), OR(NOT(ISNUMBER(Edges[Relationship Date (UTC)])), Edges[Relationship Date (UTC)] <= Misc!$P$2),OR(NOT(ISNUMBER(Edges[Tweet Date (UTC)])), Edges[Tweet Date (UTC)] >= Misc!$O$3), OR(NOT(ISNUMBER(Edges[Tweet Date (UTC)])), Edges[Tweet Date (UTC)] <= Misc!$P$3),TRUE), TRUE, FALSE) -> TRUE | O43: Mentions | P43: 43045.411 | Q43: RT @EAA_tw: CoD:WWII：サーバーの接続問題や巻き戻し現象を修正！ 原因は予想以上の人気によるアクセス集中 #CoDWWII https://t.co/iMtnw5W2Tl https://t.co/VQkd1m6D3S | R43: http://fpsjp.net/archives/294374 | S43: fpsjp.net | T43: codwwii | U43: 43045.411 | V43: https://twitter.com/#!/ayaneko0429/status/927473550713176064 | Y43: 927473550713176064
A44: mrrickmatthews | B44: pgsports | K44: No | L44: 44 | M44: =IF(AND(OR(NOT(ISNUMBER(Edges[Relationship Date (UTC)])), Edges[Relationship Date (UTC)] >= Misc!$O$2), OR(NOT(ISNUMBER(Edges[Relationship Date (UTC)])), Edges[Relationship Date (UTC)] <= Misc!$P$2),OR(NOT(ISNUMBER(Edges[Tweet Date (UTC)])), Edges[Tweet Date (UTC)] >= Misc!$O$3), OR(NOT(ISNUMBER(Edges[Tweet Date (UTC)])), Edges[Tweet Date (UTC)] <= Misc!$P$3),TRUE), TRUE, FALSE) -> TRUE | O44: Mentions | P44: 43045.411 | Q44: RT @PGSports: RT and follow to win a copy of #CODWWII winner chooses XB1 or PS4. Ends 11/7 https://t.co/keCA34QUP3 | T44: codwwii | U44: 43045.411 | V44: https://twitter.com/#!/mrrickmatthews/status/927473579217825793 | Y44: 927473579217825793
A45: dagashiexsp | B45: shinji_freedom | K45: No | L45: 45 | M45: =IF(AND(OR(NOT(ISNUMBER(Edges[Relationship Date (UTC)])), Edges[Relationship Date (UTC)] >= Misc!$O$2), OR(NOT(ISNUMBER(Edges[Relationship Date (UTC)])), Edges[Relationship Date (UTC)] <= Misc!$P$2),OR(NOT(ISNUMBER(Edges[Tweet Date (UTC)])), Edges[Tweet Date (UTC)] >= Misc!$O$3), OR(NOT(ISNUMBER(Edges[Tweet Date (UTC)])), Edges[Tweet Date (UTC)] <= Misc!$P$3),TRUE), TRUE, FALSE) -> TRUE | O45: Mentions | P45: 43045.411 | Q45: RT @SHINJI_FREEDOM: CoDの広告、秋元康プロデュースの劇団とのコラボレーションで、プレ公演初日と被せたタイアップらしいが、この広告が裏目ってるのなんというかゲーマー不在という感じが強い。 https://t.co/iWwL6D5yJj | R45: https://www.jp.playstation.com/blog/detail/5914/20171030-codwwii.html | S45: playstation.com | U45: 43045.411 | V45: https://twitter.com/#!/dagashiexsp/status/927473588092801025 | Y45: 927473588092801025
A46: d1_prix | B46: rchanfps | K46: No | L46: 46 | M46: =IF(AND(OR(NOT(ISNUMBER(Edges[Relationship Date (UTC)])), Edges[Relationship Date (UTC)] >= Misc!$O$2), OR(NOT(ISNUMBER(Edges[Relationship Date (UTC)])), Edges[Relationship Date (UTC)] <= Misc!$P$2),OR(NOT(ISNUMBER(Edges[Tweet Date (UTC)])), Edges[Tweet Date (UTC)] >= Misc!$O$3), OR(NOT(ISNUMBER(Edges[Tweet Date (UTC)])), Edges[Tweet Date (UTC)] <= Misc!$P$3),TRUE), TRUE, FALSE) -> TRUE | O46: Mentions | P46: 43045.411 | Q46: RT @RchanFPS: PC版codwwⅡをやっている方歓迎致します🔫 PC版COD仲間作りましょ！ ↓↓ディスコードチャンネル↓ https://t.co/fXMu5n8wYL 無期限 #CODWW2 #CODWWII #コールオブデューティー #PC版 #… | R46: https://discord.gg/evBYESg | S46: discord.gg | T46: codww2 codwwii コールオブデューティー pc版 | U46: 43045.411 | V46: https://twitter.com/#!/d1_prix/status/927473603292962819 | Y46: 927473603292962819
A47: davidarusta33 | B47: thegrefgyt | K47: No | L47: 47 | M47: =IF(AND(OR(NOT(ISNUMBER(Edges[Relationship Date (UTC)])), Edges[Relationship Date (UTC)] >= Misc!$O$2), OR(NOT(ISNUMBER(Edges[Relationship Date (UTC)])), Edges[Relationship Date (UTC)] <= Misc!$P$2),OR(NOT(ISNUMBER(Edges[Tweet Date (UTC)])), Edges[Tweet Date (UTC)] >= Misc!$O$3), OR(NOT(ISNUMBER(Edges[Tweet Date (UTC)])), Edges[Tweet Date (UTC)] <= Misc!$P$3),TRUE), TRUE, FALSE) -> TRUE | O47: Mentions | P47: 43045.411 | Q47: RT @TheGrefgYT: ¡NUEVO VÍDEO! 😡😠 #CODWWII ME BANEA 😠😡 RT Chicos!! 🙌🏻🔥▶️ https://t.co/78KdJQv8Ij https://t.co/heBObzc6N5 | R47: https://www.youtube.com/watch?v=-W5I1VoVWiI&feature=youtu.be | S47: youtube.com | T47: codwwii | U47: 43045.411 | V47: https://twitter.com/#!/davidarusta33/status/927473608452014081 | Y47: 927473608452014081
A48: reido1314 | B48: game_collection | K48: No | L48: 48 | M48: =IF(AND(OR(NOT(ISNUMBER(Edges[Relationship Date (UTC)])), Edges[Relationship Date (UTC)] >= Misc!$O$2), OR(NOT(ISNUMBER(Edges[Relationship Date (UTC)])), Edges[Relationship Date (UTC)] <= Misc!$P$2),OR(NOT(ISNUMBER(Edges[Tweet Date (UTC)])), Edges[Tweet Date (UTC)] >= Misc!$O$3), OR(NOT(ISNUMBER(Edges[Tweet Date (UTC)])), Edges[Tweet Date (UTC)] <= Misc!$P$3),TRUE), TRUE, FALSE) -> TRUE | O48: Mentions | P48: 43045.411 | Q48: Win #CODWWII on #PS4 or #XboxOne! RT + Follow @postabargain &amp; @game_collection and enter here: https://t.co/imdRqLflaC | R48: https://gleam.io/oyimv-kXuz5S?l=http%3A%2F%2Fwww.postabargain.co.uk%2Fpages%2Fcompetition%2F2017%2Fcall-of-duty-wwii-giveaway | S48: gleam.io | T48: codwwii ps4 xboxone | U48: 43045.411 | V48: https://twitter.com/#!/reido1314/status/927473611593543685 | Y48: 927473611593543685
A49: reido1314 | B49: postabargain | K49: No | L49: 49 | M49: =IF(AND(OR(NOT(ISNUMBER(Edges[Relationship Date (UTC)])), Edges[Relationship Date (UTC)] >= Misc!$O$2), OR(NOT(ISNUMBER(Edges[Relationship Date (UTC)])), Edges[Relationship Date (UTC)] <= Misc!$P$2),OR(NOT(ISNUMBER(Edges[Tweet Date (UTC)])), Edges[Tweet Date (UTC)] >= Misc!$O$3), OR(NOT(ISNUMBER(Edges[Tweet Date (UTC)])), Edges[Tweet Date (UTC)] <= Misc!$P$3),TRUE), TRUE, FALSE) -> TRUE | O49: Mentions | P49: 43045.411 | Q49: Win #CODWWII on #PS4 or #XboxOne! RT + Follow @postabargain &amp; @game_collection and enter here: https://t.co/imdRqLflaC | R49: https://gleam.io/oyimv-kXuz5S?l=http%3A%2F%2Fwww.postabargain.co.uk%2Fpages%2Fcompetition%2F2017%2Fcall-of-duty-wwii-giveaway | S49: gleam.io | T49: codwwii ps4 xboxone | U49: 43045.411 | V49: https://twitter.com/#!/reido1314/status/927473611593543685 | Y49: 927473611593543685
A50: bubber | B50: siefe | K50: No | L50: 50 | M50: =IF(AND(OR(NOT(ISNUMBER(Edges[Relationship Date (UTC)])), Edges[Relationship Date (UTC)] >= Misc!$O$2), OR(NOT(ISNUMBER(Edges[Relationship Date (UTC)])), Edges[Relationship Date (UTC)] <= Misc!$P$2),OR(NOT(ISNUMBER(Edges[Tweet Date (UTC)])), Edges[Tweet Date (UTC)] >= Misc!$O$3), OR(NOT(ISNUMBER(Edges[Tweet Date (UTC)])), Edges[Tweet Date (UTC)] <= Misc!$P$3),TRUE), TRUE, FALSE) -> TRUE | O50: Mentions | P50: 43045.411 | Q50: RT @Siefe: 🔴GIVEAWAY! RT &amp; FOLLOW for a chance to win a copy of #CODWWII ! #AD https://t.co/LMlUYaq1OM | T50: codwwii ad | U50: 43045.411 | V50: https://twitter.com/#!/bubber/status/927473616064860160 | Y50: 927473616064860160
A51: netdecoco | B51: eaa_tw | K51: No | L51: 51 | M51: =IF(AND(OR(NOT(ISNUMBER(Edges[Relationship Date (UTC)])), Edges[Relationship Date (UTC)] >= Misc!$O$2), OR(NOT(ISNUMBER(Edges[Relationship Date (UTC)])), Edges[Relationship Date (UTC)] <= Misc!$P$2),OR(NOT(ISNUMBER(Edges[Tweet Date (UTC)])), Edges[Tweet Date (UTC)] >= Misc!$O$3), OR(NOT(ISNUMBER(Edges[Tweet Date (UTC)])), Edges[Tweet Date (UTC)] <= Misc!$P$3),TRUE), TRUE, FALSE) -> TRUE | O51: Mentions | P51: 43045.411 | Q51: RT @EAA_tw: CoD:WWII：サーバーの接続問題や巻き戻し現象を修正！ 原因は予想以上の人気によるアクセス集中 #CoDWWII https://t.co/iMtnw5W2Tl https://t.co/VQkd1m6D3S | R51: http://fpsjp.net/archives/294374 | S51: fpsjp.net | T51: codwwii | U51: 43045.411 | V51: https://twitter.com/#!/netdecoco/status/927473691180523521 | Y51: 927473691180523521
A52: 29man_jp | B52: 29man_jp | K52: No | L52: 52 | M52: =IF(AND(OR(NOT(ISNUMBER(Edges[Relationship Date (UTC)])), Edges[Relationship Date (UTC)] >= Misc!$O$2), OR(NOT(ISNUMBER(Edges[Relationship Date (UTC)])), Edges[Relationship Date (UTC)] <= Misc!$P$2),OR(NOT(ISNUMBER(Edges[Tweet Date (UTC)])), Edges[Tweet Date (UTC)] >= Misc!$O$3), OR(NOT(ISNUMBER(Edges[Tweet Date (UTC)])), Edges[Tweet Date (UTC)] <= Misc!$P$3),TRUE), TRUE, FALSE) -> TRUE | O52: Tweet | P52: 43045.411 | Q52: やっと立ち回りに慣れてきて、キル数の方が上回るようになってきた😳 #CodWWII | T52: codwwii | U52: 43045.411 | V52: https://twitter.com/#!/29man_jp/status/927473724244111360 | Y52: 927473724244111360
A53: dembiscuitzz | B53: turtlebeach | K53: No | L53: 53 | M53: =IF(AND(OR(NOT(ISNUMBER(Edges[Relationship Date (UTC)])), Edges[Relationship Date (UTC)] >= Misc!$O$2), OR(NOT(ISNUMBER(Edges[Relationship Date (UTC)])), Edges[Relationship Date (UTC)] <= Misc!$P$2),OR(NOT(ISNUMBER(Edges[Tweet Date (UTC)])), Edges[Tweet Date (UTC)] >= Misc!$O$3), OR(NOT(ISNUMBER(Edges[Tweet Date (UTC)])), Edges[Tweet Date (UTC)] <= Misc!$P$3),TRUE), TRUE, FALSE) -> TRUE | O53: Mentions | P53: 43045.411 | Q53: I entered the @TurtleBeach Recon Camo #CODWWII #GIVEAWAY. Squad up with me and enter too! https://t.co/uSfFoN5RvD | R53: https://gleam.io/5UehP/turtle-beach-cod-wwii-giveaway | S53: gleam.io | T53: codwwii giveaway | U53: 43045.411 | V53: https://twitter.com/#!/dembiscuitzz/status/927473741684183040 | Y53: 927473741684183040
A54: vishalgiri13111 | B54: chigztechreview | K54: No | L54: 54 | M54: =IF(AND(OR(NOT(ISNUMBER(Edges[Relationship Date (UTC)])), Edges[Relationship Date (UTC)] >= Misc!$O$2), OR(NOT(ISNUMBER(Edges[Relationship Date (UTC)])), Edges[Relationship Date (UTC)] <= Misc!$P$2),OR(NOT(ISNUMBER(Edges[Tweet Date (UTC)])), Edges[Tweet Date (UTC)] >= Misc!$O$3), OR(NOT(ISNUMBER(Edges[Tweet Date (UTC)])), Edges[Tweet Date (UTC)] <= Misc!$P$3),TRUE), TRUE, FALSE) -> TRUE | O54: Mentions | P54: 43045.411 | Q54: RT @ChigzTechReview: Finally, I have it in my hands. 😎👍 #CODWWII https://t.co/WpW4MvJBZx | T54: codwwii | U54: 43045.411 | V54: https://twitter.com/#!/vishalgiri13111/status/927473743516987393 | Y54: 927473743516987393
A55: estheryjhan524 | B55: igotchusuckaa | K55: No | L55: 55 | M55: =IF(AND(OR(NOT(ISNUMBER(Edges[Relationship Date (UTC)])), Edges[Relationship Date (UTC)] >= Misc!$O$2), OR(NOT(ISNUMBER(Edges[Relationship Date (UTC)])), Edges[Relationship Date (UTC)] <= Misc!$P$2),OR(NOT(ISNUMBER(Edges[Tweet Date (UTC)])), Edges[Tweet Date (UTC)] >= Misc!$O$3), OR(NOT(ISNUMBER(Edges[Tweet Date (UTC)])), Edges[Tweet Date (UTC)] <= Misc!$P$3),TRUE), TRUE, FALSE) -> TRUE | O55: Mentions | P55: 43045.411 | Q55: RT @IGotChuSuckaa: Stats are painfully average lol #CODWWII https://t.co/hRWsVoVlJT | T55: codwwii | U55: 43045.411 | V55: https://twitter.com/#!/estheryjhan524/status/927473752513892357 | Y55: 927473752513892357
A56: reciomolina | B56: thegrefgyt | K56: No | L56: 56 | M56: =IF(AND(OR(NOT(ISNUMBER(Edges[Relationship Date (UTC)])), Edges[Relationship Date (UTC)] >= Misc!$O$2), OR(NOT(ISNUMBER(Edges[Relationship Date (UTC)])), Edges[Relationship Date (UTC)] <= Misc!$P$2),OR(NOT(ISNUMBER(Edges[Tweet Date (UTC)])), Edges[Tweet Date (UTC)] >= Misc!$O$3), OR(NOT(ISNUMBER(Edges[Tweet Date (UTC)])), Edges[Tweet Date (UTC)] <= Misc!$P$3),TRUE), TRUE, FALSE) -> TRUE | O56: Mentions | P56: 43045.411 | Q56: RT @TheGrefgYT: ¡NUEVO VÍDEO! 😡😠 #CODWWII ME BANEA 😠😡 RT Chicos!! 🙌🏻🔥▶️ https://t.co/78KdJQv8Ij https://t.co/heBObzc6N5 | R56: https://www.youtube.com/watch?v=-W5I1VoVWiI&feature=youtu.be | S56: youtube.com | T56: codwwii | U56: 43045.411 | V56: https://twitter.com/#!/reciomolina/status/927473755827269632 | Y56: 927473755827269632
A57: peekuhchew | B57: legitmeow | K57: No | L57: 57 | M57: =IF(AND(OR(NOT(ISNUMBER(Edges[Relationship Date (UTC)])), Edges[Relationship Date (UTC)] >= Misc!$O$2), OR(NOT(ISNUMBER(Edges[Relationship Date (UTC)])), Edges[Relationship Date (UTC)] <= Misc!$P$2),OR(NOT(ISNUMBER(Edges[Tweet Date (UTC)])), Edges[Tweet Date (UTC)] >= Misc!$O$3), OR(NOT(ISNUMBER(Edges[Tweet Date (UTC)])), Edges[Tweet Date (UTC)] <= Misc!$P$3),TRUE), TRUE, FALSE) -> TRUE | O57: Mentions | P57: 43045.412 | Q57: RT @legitmeow: the #codwwii experience https://t.co/zJks51knSf | T57: codwwii | U57: 43045.412 | V57: https://twitter.com/#!/peekuhchew/status/927473786294800384 | Y57: 927473786294800384
A58: tonusstonus | B58: game_collection | K58: No | L58: 58 | M58: =IF(AND(OR(NOT(ISNUMBER(Edges[Relationship Date (UTC)])), Edges[Relationship Date (UTC)] >= Misc!$O$2), OR(NOT(ISNUMBER(Edges[Relationship Date (UTC)])), Edges[Relationship Date (UTC)] <= Misc!$P$2),OR(NOT(ISNUMBER(Edges[Tweet Date (UTC)])), Edges[Tweet Date (UTC)] >= Misc!$O$3), OR(NOT(ISNUMBER(Edges[Tweet Date (UTC)])), Edges[Tweet Date (UTC)] <= Misc!$P$3),TRUE), TRUE, FALSE) -> TRUE | O58: Mentions | P58: 43045.41 | Q58: Win #CODWWII on #PS4 or #XboxOne! RT + Follow @postabargain &amp; @game_collection and enter here: https://t.co/mjjTjUOBYB | R58: http://www.postabargain.co.uk/pages/competition/2017/call-of-duty-wwii-giveaway | S58: co.uk | T58: codwwii ps4 xboxone | U58: 43045.41 | V58: https://twitter.com/#!/tonusstonus/status/927473340490698752 | Y58: 927473340490698752
A59: tonusstonus | B59: postabargain | K59: No | L59: 59 | M59: =IF(AND(OR(NOT(ISNUMBER(Edges[Relationship Date (UTC)])), Edges[Relationship Date (UTC)] >= Misc!$O$2), OR(NOT(ISNUMBER(Edges[Relationship Date (UTC)])), Edges[Relationship Date (UTC)] <= Misc!$P$2),OR(NOT(ISNUMBER(Edges[Tweet Date (UTC)])), Edges[Tweet Date (UTC)] >= Misc!$O$3), OR(NOT(ISNUMBER(Edges[Tweet Date (UTC)])), Edges[Tweet Date (UTC)] <= Misc!$P$3),TRUE), TRUE, FALSE) -> TRUE | O59: Mentions | P59: 43045.41 | Q59: Win #CODWWII on #PS4 or #XboxOne! RT + Follow @postabargain &amp; @game_collection and enter here: https://t.co/mjjTjUOBYB | R59: http://www.postabargain.co.uk/pages/competition/2017/call-of-duty-wwii-giveaway | S59: co.uk | T59: codwwii ps4 xboxone | U59: 43045.41 | V59: https://twitter.com/#!/tonusstonus/status/927473340490698752 | Y59: 927473340490698752
A60: tonusstonus | B60: game_collection | K60: No | L60: 60 | M60: =IF(AND(OR(NOT(ISNUMBER(Edges[Relationship Date (UTC)])), Edges[Relationship Date (UTC)] >= Misc!$O$2), OR(NOT(ISNUMBER(Edges[Relationship Date (UTC)])), Edges[Relationship Date (UTC)] <= Misc!$P$2),OR(NOT(ISNUMBER(Edges[Tweet Date (UTC)])), Edges[Tweet Date (UTC)] >= Misc!$O$3), OR(NOT(ISNUMBER(Edges[Tweet Date (UTC)])), Edges[Tweet Date (UTC)] <= Misc!$P$3),TRUE), TRUE, FALSE) -> TRUE | O60: Mentions | P60: 43045.412 | Q60: Enter &amp; help me win this Call of Duty WWII competition by @postabargain &amp; @game_collection #CODWWII https://t.co/eH4FHslgoy | R60: https://gleam.io/oyimv-ylBmJe?l=http%3A%2F%2Fwww.postabargain.co.uk%2Fpages%2Fcompetition%2F2017%2Fcall-of-duty-wwii-giveaway | S60: gleam.io | T60: codwwii | U60: 43045.412 | V60: https://twitter.com/#!/tonusstonus/status/927473899197038592 | Y60: 927473899197038592
A61: tonusstonus | B61: postabargain | K61: No | L61: 61 | M61: =IF(AND(OR(NOT(ISNUMBER(Edges[Relationship Date (UTC)])), Edges[Relationship Date (UTC)] >= Misc!$O$2), OR(NOT(ISNUMBER(Edges[Relationship Date (UTC)])), Edges[Relationship Date (UTC)] <= Misc!$P$2),OR(NOT(ISNUMBER(Edges[Tweet Date (UTC)])), Edges[Tweet Date (UTC)] >= Misc!$O$3), OR(NOT(ISNUMBER(Edges[Tweet Date (UTC)])), Edges[Tweet Date (UTC)] <= Misc!$P$3),TRUE), TRUE, FALSE) -> TRUE | O61: Mentions | P61: 43045.412 | Q61: Enter &amp; help me win this Call of Duty WWII competition by @postabargain &amp; @game_collection #CODWWII https://t.co/eH4FHslgoy | R61: https://gleam.io/oyimv-ylBmJe?l=http%3A%2F%2Fwww.postabargain.co.uk%2Fpages%2Fcompetition%2F2017%2Fcall-of-duty-wwii-giveaway | S61: gleam.io | T61: codwwii | U61: 43045.412 | V61: https://twitter.com/#!/tonusstonus/status/927473899197038592 | Y61: 927473899197038592
A62: maximecollin35 | B62: codfrcommunity | K62: No | L62: 62 | M62: =IF(AND(OR(NOT(ISNUMBER(Edges[Relationship Date (UTC)])), Edges[Relationship Date (UTC)] >= Misc!$O$2), OR(NOT(ISNUMBER(Edges[Relationship Date (UTC)])), Edges[Relationship Date (UTC)] <= Misc!$P$2),OR(NOT(ISNUMBER(Edges[Tweet Date (UTC)])), Edges[Tweet Date (UTC)] >= Misc!$O$3), OR(NOT(ISNUMBER(Edges[Tweet Date (UTC)])), Edges[Tweet Date (UTC)] <= Misc!$P$3),TRUE), TRUE, FALSE) -> TRUE | O62: Mentions | P62: 43045.412 | Q62: RT @CODFRCommunity: ✅ Campagne ✅ Multijoueur au sol ✅ Nazi Zombies ✅ Quartier Général ✅ Divisions ✅ Mode Guerre ✅ #CWL2018 #CODWWII est di… | T62: cwl2018 codwwii | U62: 43045.412 | V62: https://twitter.com/#!/maximecollin35/status/927473914028216321 | Y62: 927473914028216321
A63: youre0903 | B63: k_carius | K63: No | L63: 63 | M63: =IF(AND(OR(NOT(ISNUMBER(Edges[Relationship Date (UTC)])), Edges[Relationship Date (UTC)] >= Misc!$O$2), OR(NOT(ISNUMBER(Edges[Relationship Date (UTC)])), Edges[Relationship Date (UTC)] <= Misc!$P$2),OR(NOT(ISNUMBER(Edges[Tweet Date (UTC)])), Edges[Tweet Date (UTC)] >= Misc!$O$3), OR(NOT(ISNUMBER(Edges[Tweet Date (UTC)])), Edges[Tweet Date (UTC)] <= Misc!$P$3),TRUE), TRUE, FALSE) -> TRUE | O63: Mentions | P63: 43045.412 | Q63: RT @k_carius: CoDWWⅡの例のあれ https://t.co/D6GIygertV | U63: 43045.412 | V63: https://twitter.com/#!/youre0903/status/927473968713424896 | Y63: 927473968713424896
A64: dinksteruk | B64: game_collection | K64: No | L64: 64 | M64: =IF(AND(OR(NOT(ISNUMBER(Edges[Relationship Date (UTC)])), Edges[Relationship Date (UTC)] >= Misc!$O$2), OR(NOT(ISNUMBER(Edges[Relationship Date (UTC)])), Edges[Relationship Date (UTC)] <= Misc!$P$2),OR(NOT(ISNUMBER(Edges[Tweet Date (UTC)])), Edges[Tweet Date (UTC)] >= Misc!$O$3), OR(NOT(ISNUMBER(Edges[Tweet Date (UTC)])), Edges[Tweet Date (UTC)] <= Misc!$P$3),TRUE), TRUE, FALSE) -> TRUE | O64: Mentions | P64: 43045.412 | Q64: Win #CODWWII on #PS4 or #XboxOne! RT + Follow @postabargain &amp; @game_collection and enter here: https://t.co/jKdpKrb9oz | R64: https://gleam.io/oyimv-jTak4e?l=http%3A%2F%2Fwww.postabargain.co.uk%2Fpages%2Fcompetition%2F2017%2Fcall-of-duty-wwii-giveaway | S64: gleam.io | T64: codwwii ps4 xboxone | U64: 43045.412 | V64: https://twitter.com/#!/dinksteruk/status/927474019363733504 | Y64: 927474019363733504
A65: dinksteruk | B65: postabargain | K65: No | L65: 65 | M65: =IF(AND(OR(NOT(ISNUMBER(Edges[Relationship Date (UTC)])), Edges[Relationship Date (UTC)] >= Misc!$O$2), OR(NOT(ISNUMBER(Edges[Relationship Date (UTC)])), Edges[Relationship Date (UTC)] <= Misc!$P$2),OR(NOT(ISNUMBER(Edges[Tweet Date (UTC)])), Edges[Tweet Date (UTC)] >= Misc!$O$3), OR(NOT(ISNUMBER(Edges[Tweet Date (UTC)])), Edges[Tweet Date (UTC)] <= Misc!$P$3),TRUE), TRUE, FALSE) -> TRUE | O65: Mentions | P65: 43045.412 | Q65: Win #CODWWII on #PS4 or #XboxOne! RT + Follow @postabargain &amp; @game_collection and enter here: https://t.co/jKdpKrb9oz | R65: https://gleam.io/oyimv-jTak4e?l=http%3A%2F%2Fwww.postabargain.co.uk%2Fpages%2Fcompetition%2F2017%2Fcall-of-duty-wwii-giveaway | S65: gleam.io | T65: codwwii ps4 xboxone | U65: 43045.412 | V65: https://twitter.com/#!/dinksteruk/status/927474019363733504 | Y65: 927474019363733504
A66: elblaugrana10 | B66: postabargain | K66: No | L66: 66 | M66: =IF(AND(OR(NOT(ISNUMBER(Edges[Relationship Date (UTC)])), Edges[Relationship Date (UTC)] >= Misc!$O$2), OR(NOT(ISNUMBER(Edges[Relationship Date (UTC)])), Edges[Relationship Date (UTC)] <= Misc!$P$2),OR(NOT(ISNUMBER(Edges[Tweet Date (UTC)])), Edges[Tweet Date (UTC)] >= Misc!$O$3), OR(NOT(ISNUMBER(Edges[Tweet Date (UTC)])), Edges[Tweet Date (UTC)] <= Misc!$P$3),TRUE), TRUE, FALSE) -> TRUE | O66: Mentions | P66: 43045.412 | Q66: RT @postabargain: #CODWWII arrives and takes over the number 1 spot in this week's chart. #ACOrigins falls to 2. #SuperMarioOdyssey to 4. h… | T66: codwwii acorigins supermarioodyssey | U66: 43045.412 | V66: https://twitter.com/#!/elblaugrana10/status/927474032034885632 | Y66: 927474032034885632
A67: reinhardt__ | B67: toshmcgruder | K67: No | L67: 67 | M67: =IF(AND(OR(NOT(ISNUMBER(Edges[Relationship Date (UTC)])), Edges[Relationship Date (UTC)] >= Misc!$O$2), OR(NOT(ISNUMBER(Edges[Relationship Date (UTC)])), Edges[Relationship Date (UTC)] <= Misc!$P$2),OR(NOT(ISNUMBER(Edges[Tweet Date (UTC)])), Edges[Tweet Date (UTC)] >= Misc!$O$3), OR(NOT(ISNUMBER(Edges[Tweet Date (UTC)])), Edges[Tweet Date (UTC)] <= Misc!$P$3),TRUE), TRUE, FALSE) -> TRUE | O67: Mentions | P67: 43045.412 | Q67: RT @StayPureGG: Happy to announce our entry into eSports. Introducing our official #CODWWII roster. @Sharp_tK @Neslo @Whea7s @ToshMcgruder… | T67: codwwii | U67: 43045.412 | V67: https://twitter.com/#!/reinhardt__/status/927474077001957376 | Y67: 927474077001957376
A68: reinhardt__ | B68: whea7s | K68: No | L68: 68 | M68: =IF(AND(OR(NOT(ISNUMBER(Edges[Relationship Date (UTC)])), Edges[Relationship Date (UTC)] >= Misc!$O$2), OR(NOT(ISNUMBER(Edges[Relationship Date (UTC)])), Edges[Relationship Date (UTC)] <= Misc!$P$2),OR(NOT(ISNUMBER(Edges[Tweet Date (UTC)])), Edges[Tweet Date (UTC)] >= Misc!$O$3), OR(NOT(ISNUMBER(Edges[Tweet Date (UTC)])), Edges[Tweet Date (UTC)] <= Misc!$P$3),TRUE), TRUE, FALSE) -> TRUE | O68: Mentions | P68: 43045.412 | Q68: RT @StayPureGG: Happy to announce our entry into eSports. Introducing our official #CODWWII roster. @Sharp_tK @Neslo @Whea7s @ToshMcgruder… | T68: codwwii | U68: 43045.412 | V68: https://twitter.com/#!/reinhardt__/status/927474077001957376 | Y68: 927474077001957376
A69: reinhardt__ | B69: neslo | K69: No | L69: 69 | M69: =IF(AND(OR(NOT(ISNUMBER(Edges[Relationship Date (UTC)])), Edges[Relationship Date (UTC)] >= Misc!$O$2), OR(NOT(ISNUMBER(Edges[Relationship Date (UTC)])), Edges[Relationship Date (UTC)] <= Misc!$P$2),OR(NOT(ISNUMBER(Edges[Tweet Date (UTC)])), Edges[Tweet Date (UTC)] >= Misc!$O$3), OR(NOT(ISNUMBER(Edges[Tweet Date (UTC)])), Edges[Tweet Date (UTC)] <= Misc!$P$3),TRUE), TRUE, FALSE) -> TRUE | O69: Mentions | P69: 43045.412 | Q69: RT @StayPureGG: Happy to announce our entry into eSports. Introducing our official #CODWWII roster. @Sharp_tK @Neslo @Whea7s @ToshMcgruder… | T69: codwwii | U69: 43045.412 | V69: https://twitter.com/#!/reinhardt__/status/927474077001957376 | Y69: 927474077001957376
A70: reinhardt__ | B70: sharp_tk | K70: No | L70: 70 | M70: =IF(AND(OR(NOT(ISNUMBER(Edges[Relationship Date (UTC)])), Edges[Relationship Date (UTC)] >= Misc!$O$2), OR(NOT(ISNUMBER(Edges[Relationship Date (UTC)])), Edges[Relationship Date (UTC)] <= Misc!$P$2),OR(NOT(ISNUMBER(Edges[Tweet Date (UTC)])), Edges[Tweet Date (UTC)] >= Misc!$O$3), OR(NOT(ISNUMBER(Edges[Tweet Date (UTC)])), Edges[Tweet Date (UTC)] <= Misc!$P$3),TRUE), TRUE, FALSE) -> TRUE | O70: Mentions | P70: 43045.412 | Q70: RT @StayPureGG: Happy to announce our entry into eSports. Introducing our official #CODWWII roster. @Sharp_tK @Neslo @Whea7s @ToshMcgruder… | T70: codwwii | U70: 43045.412 | V70: https://twitter.com/#!/reinhardt__/status/927474077001957376 | Y70: 927474077001957376
A71: reinhardt__ | B71: staypuregg | K71: No | L71: 71 | M71: =IF(AND(OR(NOT(ISNUMBER(Edges[Relationship Date (UTC)])), Edges[Relationship Date (UTC)] >= Misc!$O$2), OR(NOT(ISNUMBER(Edges[Relationship Date (UTC)])), Edges[Relationship Date (UTC)] <= Misc!$P$2),OR(NOT(ISNUMBER(Edges[Tweet Date (UTC)])), Edges[Tweet Date (UTC)] >= Misc!$O$3), OR(NOT(ISNUMBER(Edges[Tweet Date (UTC)])), Edges[Tweet Date (UTC)] <= Misc!$P$3),TRUE), TRUE, FALSE) -> TRUE | O71: Mentions | P71: 43045.412 | Q71: RT @StayPureGG: Happy to announce our entry into eSports. Introducing our official #CODWWII roster. @Sharp_tK @Neslo @Whea7s @ToshMcgruder… | T71: codwwii | U71: 43045.412 | V71: https://twitter.com/#!/reinhardt__/status/927474077001957376 | Y71: 927474077001957376
A72: danger_bear | B72: danger_bear | K72: No | L72: 72 | M72: =IF(AND(OR(NOT(ISNUMBER(Edges[Relationship Date (UTC)])), Edges[Relationship Date (UTC)] >= Misc!$O$2), OR(NOT(ISNUMBER(Edges[Relationship Date (UTC)])), Edges[Relationship Date (UTC)] <= Misc!$P$2),OR(NOT(ISNUMBER(Edges[Tweet Date (UTC)])), Edges[Tweet Date (UTC)] >= Misc!$O$3), OR(NOT(ISNUMBER(Edges[Tweet Date (UTC)])), Edges[Tweet Date (UTC)] <= Misc!$P$3),TRUE), TRUE, FALSE) -> TRUE | O72: Tweet | P72: 43045.412 | Q72: CODWWⅡ買いに行ったら 無かったのでモンハンワールド 予約して帰宅 | U72: 43045.412 | V72: https://twitter.com/#!/danger_bear/status/927474078428028930 | Y72: 927474078428028930
A73: omegamario17 | B73: omegamario17 | K73: No | L73: 73 | M73: =IF(AND(OR(NOT(ISNUMBER(Edges[Relationship Date (UTC)])), Edges[Relationship Date (UTC)] >= Misc!$O$2), OR(NOT(ISNUMBER(Edges[Relationship Date (UTC)])), Edges[Relationship Date (UTC)] <= Misc!$P$2),OR(NOT(ISNUMBER(Edges[Tweet Date (UTC)])), Edges[Tweet Date (UTC)] >= Misc!$O$3), OR(NOT(ISNUMBER(Edges[Tweet Date (UTC)])), Edges[Tweet Date (UTC)] <= Misc!$P$3),TRUE), TRUE, FALSE) -> TRUE | O73: Tweet | P73: 43045.412 | Q73: Watch JordanKgames with me on Twitch! As he is fighting the boss on #CODWWII Zombies https://t.co/ED6OysrBhs | R73: https://go.twitch.tv/jordankgames?sr=a | S73: twitch.tv | T73: codwwii | U73: 43045.412 | V73: https://twitter.com/#!/omegamario17/status/927474094702022656 | Y73: 927474094702022656
A74: cb4rockchad | B74: igotchusuckaa | K74: No | L74: 74 | M74: =IF(AND(OR(NOT(ISNUMBER(Edges[Relationship Date (UTC)])), Edges[Relationship Date (UTC)] >= Misc!$O$2), OR(NOT(ISNUMBER(Edges[Relationship Date (UTC)])), Edges[Relationship Date (UTC)] <= Misc!$P$2),OR(NOT(ISNUMBER(Edges[Tweet Date (UTC)])), Edges[Tweet Date (UTC)] >= Misc!$O$3), OR(NOT(ISNUMBER(Edges[Tweet Date (UTC)])), Edges[Tweet Date (UTC)] <= Misc!$P$3),TRUE), TRUE, FALSE) -> TRUE | O74: Mentions | P74: 43045.412 | Q74: RT @IGotChuSuckaa: Stats are painfully average lol #CODWWII https://t.co/hRWsVoVlJT | T74: codwwii | U74: 43045.412 | V74: https://twitter.com/#!/cb4rockchad/status/927474109977575425 | Y74: 927474109977575425
A75: mizanur199 | B75: andyhdxgaming | K75: No | L75: 75 | M75: =IF(AND(OR(NOT(ISNUMBER(Edges[Relationship Date (UTC)])), Edges[Relationship Date (UTC)] >= Misc!$O$2), OR(NOT(ISNUMBER(Edges[Relationship Date (UTC)])), Edges[Relationship Date (UTC)] <= Misc!$P$2),OR(NOT(ISNUMBER(Edges[Tweet Date (UTC)])), Edges[Tweet Date (UTC)] >= Misc!$O$3), OR(NOT(ISNUMBER(Edges[Tweet Date (UTC)])), Edges[Tweet Date (UTC)] <= Misc!$P$3),TRUE), TRUE, FALSE) -> TRUE | O75: Mentions | P75: 43045.412 | Q75: RT @AndyHDxGaming: Giving away a free copy of #CODWWII - like, follow @AndyHDxGaming and I’ll DM you with the hook up 👊🏼 https://t.co/TizWw… | T75: codwwii | U75: 43045.412 | V75: https://twitter.com/#!/mizanur199/status/927474111626006528 | Y75: 927474111626006528
A76: diaz__z | B76: cdiscount | K76: No | L76: 76 | M76: =IF(AND(OR(NOT(ISNUMBER(Edges[Relationship Date (UTC)])), Edges[Relationship Date (UTC)] >= Misc!$O$2), OR(NOT(ISNUMBER(Edges[Relationship Date (UTC)])), Edges[Relationship Date (UTC)] <= Misc!$P$2),OR(NOT(ISNUMBER(Edges[Tweet Date (UTC)])), Edges[Tweet Date (UTC)] >= Misc!$O$3), OR(NOT(ISNUMBER(Edges[Tweet Date (UTC)])), Edges[Tweet Date (UTC)] <= Misc!$P$3),TRUE), TRUE, FALSE) -> TRUE | O76: Mentions | P76: 43045.412 | Q76: RT @Cdiscount: 🎁 #Concours 🎮 #PS4 + #CODWWII à gagner &gt; https://t.co/9QvQzp85fe ⭐️ Pour participer : RT + Follow @Cdiscount 📢 TAS 09/… | R76: https://www.cdiscount.com/jeux-pc-video-console/consoles/nouvelle-ps4-slim-1-to-call-of-duty-world-war/f-1033916-711719941767.html?cm_mmc=inf-_-tw-_-31117-_-Jcod-_-&cid=inf | S76: cdiscount.com | T76: concours ps4 codwwii | U76: 43045.412 | V76: https://twitter.com/#!/diaz__z/status/927473949268676608 | Y76: 927473949268676608
A77: diaz__z | B77: fnac | K77: No | L77: 77 | M77: =IF(AND(OR(NOT(ISNUMBER(Edges[Relationship Date (UTC)])), Edges[Relationship Date (UTC)] >= Misc!$O$2), OR(NOT(ISNUMBER(Edges[Relationship Date (UTC)])), Edges[Relationship Date (UTC)] <= Misc!$P$2),OR(NOT(ISNUMBER(Edges[Tweet Date (UTC)])), Edges[Tweet Date (UTC)] >= Misc!$O$3), OR(NOT(ISNUMBER(Edges[Tweet Date (UTC)])), Edges[Tweet Date (UTC)] <= Misc!$P$3),TRUE), TRUE, FALSE) -> TRUE | O77: Mentions | P77: 43045.412 | Q77: RT @Fnac: JEU CONCOURS: À l'occasion de la sortie de #CODWWII, tente de gagner ces lots ! Pour participer : RT + Follow @Fnac 😄https://t.co… | T77: codwwii | U77: 43045.412 | V77: https://twitter.com/#!/diaz__z/status/927474113689587712 | Y77: 927474113689587712
A78: fpscafe_au_lait | B78: eaa_tw | K78: No | L78: 78 | M78: =IF(AND(OR(NOT(ISNUMBER(Edges[Relationship Date (UTC)])), Edges[Relationship Date (UTC)] >= Misc!$O$2), OR(NOT(ISNUMBER(Edges[Relationship Date (UTC)])), Edges[Relationship Date (UTC)] <= Misc!$P$2),OR(NOT(ISNUMBER(Edges[Tweet Date (UTC)])), Edges[Tweet Date (UTC)] >= Misc!$O$3), OR(NOT(ISNUMBER(Edges[Tweet Date (UTC)])), Edges[Tweet Date (UTC)] <= Misc!$P$3),TRUE), TRUE, FALSE) -> TRUE | O78: Mentions | P78: 43045.412 | Q78: RT @EAA_tw: CoD:WWII：サーバーの接続問題や巻き戻し現象を修正！ 原因は予想以上の人気によるアクセス集中 #CoDWWII https://t.co/iMtnw5W2Tl https://t.co/VQkd1m6D3S | R78: http://fpsjp.net/archives/294374 | S78: fpsjp.net | T78: codwwii | U78: 43045.412 | V78: https://twitter.com/#!/fpscafe_au_lait/status/927474123067990016 | Y78: 927474123067990016
A79: philippebhanna | B79: cdiscount | K79: No | L79: 79 | M79: =IF(AND(OR(NOT(ISNUMBER(Edges[Relationship Date (UTC)])), Edges[Relationship Date (UTC)] >= Misc!$O$2), OR(NOT(ISNUMBER(Edges[Relationship Date (UTC)])), Edges[Relationship Date (UTC)] <= Misc!$P$2),OR(NOT(ISNUMBER(Edges[Tweet Date (UTC)])), Edges[Tweet Date (UTC)] >= Misc!$O$3), OR(NOT(ISNUMBER(Edges[Tweet Date (UTC)])), Edges[Tweet Date (UTC)] <= Misc!$P$3),TRUE), TRUE, FALSE) -> TRUE | O79: Mentions | P79: 43045.412 | Q79: RT @Cdiscount: 🎁 #Concours 🎮 #PS4 + #CODWWII à gagner &gt; https://t.co/9QvQzp85fe ⭐️ Pour participer : RT + Follow @Cdiscount 📢 TAS 09/… | R79: https://www.cdiscount.com/jeux-pc-video-console/consoles/nouvelle-ps4-slim-1-to-call-of-duty-world-war/f-1033916-711719941767.html?cm_mmc=inf-_-tw-_-31117-_-Jcod-_-&cid=inf | S79: cdiscount.com | T79: concours ps4 codwwii | U79: 43045.412 | V79: https://twitter.com/#!/philippebhanna/status/927474108052451329 | Y79: 927474108052451329
A80: philippebhanna | B80: fnac | K80: No | L80: 80 | M80: =IF(AND(OR(NOT(ISNUMBER(Edges[Relationship Date (UTC)])), Edges[Relationship Date (UTC)] >= Misc!$O$2), OR(NOT(ISNUMBER(Edges[Relationship Date (UTC)])), Edges[Relationship Date (UTC)] <= Misc!$P$2),OR(NOT(ISNUMBER(Edges[Tweet Date (UTC)])), Edges[Tweet Date (UTC)] >= Misc!$O$3), OR(NOT(ISNUMBER(Edges[Tweet Date (UTC)])), Edges[Tweet Date (UTC)] <= Misc!$P$3),TRUE), TRUE, FALSE) -> TRUE | O80: Mentions | P80: 43045.412 | Q80: RT @Fnac: JEU CONCOURS: À l'occasion de la sortie de #CODWWII, tente de gagner ces lots ! Pour participer : RT + Follow @Fnac 😄https://t.co… | T80: codwwii | U80: 43045.412 | V80: https://twitter.com/#!/philippebhanna/status/927474127291723776 | Y80: 927474127291723776
A81: xyuna21 | B81: codww2intel | K81: No | L81: 81 | M81: =IF(AND(OR(NOT(ISNUMBER(Edges[Relationship Date (UTC)])), Edges[Relationship Date (UTC)] >= Misc!$O$2), OR(NOT(ISNUMBER(Edges[Relationship Date (UTC)])), Edges[Relationship Date (UTC)] <= Misc!$P$2),OR(NOT(ISNUMBER(Edges[Tweet Date (UTC)])), Edges[Tweet Date (UTC)] >= Misc!$O$3), OR(NOT(ISNUMBER(Edges[Tweet Date (UTC)])), Edges[Tweet Date (UTC)] <= Misc!$P$3),TRUE), TRUE, FALSE) -> TRUE | O81: Mentions | P81: 43045.413 | Q81: RT @CoDWW2Intel: Here's all of the 10 Prestige + Prestige Master Icons in CoD WWII! #CoDWW2 #CoDWWII Credit: Reddit (LackingAGoodName) htt… | T81: codww2 codwwii | U81: 43045.413 | V81: https://twitter.com/#!/xyuna21/status/927474148196024321 | Y81: 927474148196024321
A82: impeccablellama | B82: noahj456 | K82: No | L82: 82 | M82: =IF(AND(OR(NOT(ISNUMBER(Edges[Relationship Date (UTC)])), Edges[Relationship Date (UTC)] >= Misc!$O$2), OR(NOT(ISNUMBER(Edges[Relationship Date (UTC)])), Edges[Relationship Date (UTC)] <= Misc!$P$2),OR(NOT(ISNUMBER(Edges[Tweet Date (UTC)])), Edges[Tweet Date (UTC)] >= Misc!$O$3), OR(NOT(ISNUMBER(Edges[Tweet Date (UTC)])), Edges[Tweet Date (UTC)] <= Misc!$P$3),TRUE), TRUE, FALSE) -> TRUE | O82: Mentions | P82: 43045.413 | Q82: RT @NoahJ456: The coolest scene of all time in #CODWWII https://t.co/ZGuydUCcDB | T82: codwwii | U82: 43045.413 | V82: https://twitter.com/#!/impeccablellama/status/927474213736329217 | Y82: 927474213736329217
A83: hugosolanarf | B83: thegrefgyt | K83: No | L83: 83 | M83: =IF(AND(OR(NOT(ISNUMBER(Edges[Relationship Date (UTC)])), Edges[Relationship Date (UTC)] >= Misc!$O$2), OR(NOT(ISNUMBER(Edges[Relationship Date (UTC)])), Edges[Relationship Date (UTC)] <= Misc!$P$2),OR(NOT(ISNUMBER(Edges[Tweet Date (UTC)])), Edges[Tweet Date (UTC)] >= Misc!$O$3), OR(NOT(ISNUMBER(Edges[Tweet Date (UTC)])), Edges[Tweet Date (UTC)] <= Misc!$P$3),TRUE), TRUE, FALSE) -> TRUE | O83: Mentions | P83: 43045.413 | Q83: RT @TheGrefgYT: ¡NUEVO VÍDEO! 😡😠 #CODWWII ME BANEA 😠😡 RT Chicos!! 🙌🏻🔥▶️ https://t.co/78KdJQv8Ij https://t.co/heBObzc6N5 | R83: https://www.youtube.com/watch?v=-W5I1VoVWiI&feature=youtu.be | S83: youtube.com | T83: codwwii | U83: 43045.413 | V83: https://twitter.com/#!/hugosolanarf/status/927474227128573952 | Y83: 927474227128573952
A84: game_shiranami | B84: eaa_tw | K84: No | L84: 84 | M84: =IF(AND(OR(NOT(ISNUMBER(Edges[Relationship Date (UTC)])), Edges[Relationship Date (UTC)] >= Misc!$O$2), OR(NOT(ISNUMBER(Edges[Relationship Date (UTC)])), Edges[Relationship Date (UTC)] <= Misc!$P$2),OR(NOT(ISNUMBER(Edges[Tweet Date (UTC)])), Edges[Tweet Date (UTC)] >= Misc!$O$3), OR(NOT(ISNUMBER(Edges[Tweet Date (UTC)])), Edges[Tweet Date (UTC)] <= Misc!$P$3),TRUE), TRUE, FALSE) -> TRUE | O84: Mentions | P84: 43045.413 | Q84: RT @EAA_tw: CoD:WWII：サーバーの接続問題や巻き戻し現象を修正！ 原因は予想以上の人気によるアクセス集中 #CoDWWII https://t.co/iMtnw5W2Tl https://t.co/VQkd1m6D3S | R84: http://fpsjp.net/archives/294374 | S84: fpsjp.net | T84: codwwii | U84: 43045.413 | V84: https://twitter.com/#!/game_shiranami/status/927474307831275521 | Y84: 927474307831275521
A85: screally | B85: game_collection | K85: No | L85: 85 | M85: =IF(AND(OR(NOT(ISNUMBER(Edges[Relationship Date (UTC)])), Edges[Relationship Date (UTC)] >= Misc!$O$2), OR(NOT(ISNUMBER(Edges[Relationship Date (UTC)])), Edges[Relationship Date (UTC)] <= Misc!$P$2),OR(NOT(ISNUMBER(Edges[Tweet Date (UTC)])), Edges[Tweet Date (UTC)] >= Misc!$O$3), OR(NOT(ISNUMBER(Edges[Tweet Date (UTC)])), Edges[Tweet Date (UTC)] <= Misc!$P$3),TRUE), TRUE, FALSE) -> TRUE | O85: Mentions | P85: 43045.413 | Q85: Win #CODWWII on #PS4 or #XboxOne! RT + Follow @postabargain &amp; @game_collection and enter here: https://t.co/I4Gv8c4TpK | R85: https://gleam.io/oyimv-mw5r6S?l=http%3A%2F%2Fwww.postabargain.co.uk%2Fpages%2Fcompetition%2F2017%2Fcall-of-duty-wwii-giveaway | S85: gleam.io | T85: codwwii ps4 xboxone | U85: 43045.413 | V85: https://twitter.com/#!/screally/status/927474278257197056 | Y85: 927474278257197056
A86: screally | B86: postabargain | K86: No | L86: 86 | M86: =IF(AND(OR(NOT(ISNUMBER(Edges[Relationship Date (UTC)])), Edges[Relationship Date (UTC)] >= Misc!$O$2), OR(NOT(ISNUMBER(Edges[Relationship Date (UTC)])), Edges[Relationship Date (UTC)] <= Misc!$P$2),OR(NOT(ISNUMBER(Edges[Tweet Date (UTC)])), Edges[Tweet Date (UTC)] >= Misc!$O$3), OR(NOT(ISNUMBER(Edges[Tweet Date (UTC)])), Edges[Tweet Date (UTC)] <= Misc!$P$3),TRUE), TRUE, FALSE) -> TRUE | O86: Mentions | P86: 43045.413 | Q86: Win #CODWWII on #PS4 or #XboxOne! RT + Follow @postabargain &amp; @game_collection and enter here: https://t.co/I4Gv8c4TpK | R86: https://gleam.io/oyimv-mw5r6S?l=http%3A%2F%2Fwww.postabargain.co.uk%2Fpages%2Fcompetition%2F2017%2Fcall-of-duty-wwii-giveaway | S86: gleam.io | T86: codwwii ps4 xboxone | U86: 43045.413 | V86: https://twitter.com/#!/screally/status/927474278257197056 | Y86: 927474278257197056
A87: screally | B87: game_collection | K87: No | L87: 87 | M87: =IF(AND(OR(NOT(ISNUMBER(Edges[Relationship Date (UTC)])), Edges[Relationship Date (UTC)] >= Misc!$O$2), OR(NOT(ISNUMBER(Edges[Relationship Date (UTC)])), Edges[Relationship Date (UTC)] <= Misc!$P$2),OR(NOT(ISNUMBER(Edges[Tweet Date (UTC)])), Edges[Tweet Date (UTC)] >= Misc!$O$3), OR(NOT(ISNUMBER(Edges[Tweet Date (UTC)])), Edges[Tweet Date (UTC)] <= Misc!$P$3),TRUE), TRUE, FALSE) -> TRUE | O87: Mentions | P87: 43045.414 | Q87: Enter &amp; help me win this Call of Duty WWII competition by @postabargain &amp; @game_collection #CODWWII https://t.co/I4Gv8cmuOk | R87: https://gleam.io/oyimv-mw5r6S?l=http%3A%2F%2Fwww.postabargain.co.uk%2Fpages%2Fcompetition%2F2017%2Fcall-of-duty-wwii-giveaway | S87: gleam.io | T87: codwwii | U87: 43045.414 | V87: https://twitter.com/#!/screally/status/927474505039208449 | Y87: 927474505039208449
A88: screally | B88: postabargain | K88: No | L88: 88 | M88: =IF(AND(OR(NOT(ISNUMBER(Edges[Relationship Date (UTC)])), Edges[Relationship Date (UTC)] >= Misc!$O$2), OR(NOT(ISNUMBER(Edges[Relationship Date (UTC)])), Edges[Relationship Date (UTC)] <= Misc!$P$2),OR(NOT(ISNUMBER(Edges[Tweet Date (UTC)])), Edges[Tweet Date (UTC)] >= Misc!$O$3), OR(NOT(ISNUMBER(Edges[Tweet Date (UTC)])), Edges[Tweet Date (UTC)] <= Misc!$P$3),TRUE), TRUE, FALSE) -> TRUE | O88: Mentions | P88: 43045.414 | Q88: Enter &amp; help me win this Call of Duty WWII competition by @postabargain &amp; @game_collection #CODWWII https://t.co/I4Gv8cmuOk | R88: https://gleam.io/oyimv-mw5r6S?l=http%3A%2F%2Fwww.postabargain.co.uk%2Fpages%2Fcompetition%2F2017%2Fcall-of-duty-wwii-giveaway | S88: gleam.io | T88: codwwii | U88: 43045.414 | V88: https://twitter.com/#!/screally/status/927474505039208449 | Y88: 927474505039208449
A89: sazmiti | B89: cdiscount | K89: No | L89: 89 | M89: =IF(AND(OR(NOT(ISNUMBER(Edges[Relationship Date (UTC)])), Edges[Relationship Date (UTC)] >= Misc!$O$2), OR(NOT(ISNUMBER(Edges[Relationship Date (UTC)])), Edges[Relationship Date (UTC)] <= Misc!$P$2),OR(NOT(ISNUMBER(Edges[Tweet Date (UTC)])), Edges[Tweet Date (UTC)] >= Misc!$O$3), OR(NOT(ISNUMBER(Edges[Tweet Date (UTC)])), Edges[Tweet Date (UTC)] <= Misc!$P$3),TRUE), TRUE, FALSE) -> TRUE | O89: Mentions | P89: 43045.414 | Q89: RT @Cdiscount: 🎁 #Concours 🎮 #PS4 + #CODWWII à gagner &gt; https://t.co/9QvQzp85fe ⭐️ Pour participer : RT + Follow @Cdiscount 📢 TAS 09/… | R89: https://www.cdiscount.com/jeux-pc-video-console/consoles/nouvelle-ps4-slim-1-to-call-of-duty-world-war/f-1033916-711719941767.html?cm_mmc=inf-_-tw-_-31117-_-Jcod-_-&cid=inf | S89: cdiscount.com | T89: concours ps4 codwwii | U89: 43045.414 | V89: https://twitter.com/#!/sazmiti/status/927474527973584896 | Y89: 927474527973584896
A90: _origin_story_ | B90: jordanenthy | K90: No | L90: 90 | M90: =IF(AND(OR(NOT(ISNUMBER(Edges[Relationship Date (UTC)])), Edges[Relationship Date (UTC)] >= Misc!$O$2), OR(NOT(ISNUMBER(Edges[Relationship Date (UTC)])), Edges[Relationship Date (UTC)] <= Misc!$P$2),OR(NOT(ISNUMBER(Edges[Tweet Date (UTC)])), Edges[Tweet Date (UTC)] >= Misc!$O$3), OR(NOT(ISNUMBER(Edges[Tweet Date (UTC)])), Edges[Tweet Date (UTC)] <= Misc!$P$3),TRUE), TRUE, FALSE) -> TRUE | O90: Mentions | P90: 43045.414 | Q90: RT @JordanEnthy: Who’s hyped for #CoDWWII 👀 | T90: codwwii | U90: 43045.414 | V90: https://twitter.com/#!/_origin_story_/status/927474544188719106 | Y90: 927474544188719106
A91: shin03161412 | B91: eaa_tw | K91: No | L91: 91 | M91: =IF(AND(OR(NOT(ISNUMBER(Edges[Relationship Date (UTC)])), Edges[Relationship Date (UTC)] >= Misc!$O$2), OR(NOT(ISNUMBER(Edges[Relationship Date (UTC)])), Edges[Relationship Date (UTC)] <= Misc!$P$2),OR(NOT(ISNUMBER(Edges[Tweet Date (UTC)])), Edges[Tweet Date (UTC)] >= Misc!$O$3), OR(NOT(ISNUMBER(Edges[Tweet Date (UTC)])), Edges[Tweet Date (UTC)] <= Misc!$P$3),TRUE), TRUE, FALSE) -> TRUE | O91: Mentions | P91: 43045.414 | Q91: RT @EAA_tw: CoD:WWII： プレステージアイコン全10種と、プレステージマスターアイコンが判明 #CoDWWII https://t.co/PSkNgKtZ3K https://t.co/41SmfDFFhy | R91: http://fpsjp.net/archives/294392 | S91: fpsjp.net | T91: codwwii | U91: 43045.414 | V91: https://twitter.com/#!/shin03161412/status/927474563520200704 | Y91: 927474563520200704
A92: ninjarefinery | B92: game_collection | K92: No | L92: 92 | M92: =IF(AND(OR(NOT(ISNUMBER(Edges[Relationship Date (UTC)])), Edges[Relationship Date (UTC)] >= Misc!$O$2), OR(NOT(ISNUMBER(Edges[Relationship Date (UTC)])), Edges[Relationship Date (UTC)] <= Misc!$P$2),OR(NOT(ISNUMBER(Edges[Tweet Date (UTC)])), Edges[Tweet Date (UTC)] >= Misc!$O$3), OR(NOT(ISNUMBER(Edges[Tweet Date (UTC)])), Edges[Tweet Date (UTC)] <= Misc!$P$3),TRUE), TRUE, FALSE) -> TRUE | O92: Mentions | P92: 43045.414 | Q92: Win #CODWWII on #PS4 or #XboxOne! RT + Follow @postabargain &amp; @game_collection and enter here: https://t.co/Z6t8KjN7ax | R92: https://gleam.io/oyimv-zqiHcl?l=http%3A%2F%2Fwww.postabargain.co.uk%2Fpages%2Fcompetition%2F2017%2Fcall-of-duty-wwii-giveaway | S92: gleam.io | T92: codwwii ps4 xboxone | U92: 43045.414 | V92: https://twitter.com/#!/ninjarefinery/status/927474566217089025 | Y92: 927474566217089025
A93: ninjarefinery | B93: postabargain | K93: No | L93: 93 | M93: =IF(AND(OR(NOT(ISNUMBER(Edges[Relationship Date (UTC)])), Edges[Relationship Date (UTC)] >= Misc!$O$2), OR(NOT(ISNUMBER(Edges[Relationship Date (UTC)])), Edges[Relationship Date (UTC)] <= Misc!$P$2),OR(NOT(ISNUMBER(Edges[Tweet Date (UTC)])), Edges[Tweet Date (UTC)] >= Misc!$O$3), OR(NOT(ISNUMBER(Edges[Tweet Date (UTC)])), Edges[Tweet Date (UTC)] <= Misc!$P$3),TRUE), TRUE, FALSE) -> TRUE | O93: Mentions | P93: 43045.414 | Q93: Win #CODWWII on #PS4 or #XboxOne! RT + Follow @postabargain &amp; @game_collection and enter here: https://t.co/Z6t8KjN7ax | R93: https://gleam.io/oyimv-zqiHcl?l=http%3A%2F%2Fwww.postabargain.co.uk%2Fpages%2Fcompetition%2F2017%2Fcall-of-duty-wwii-giveaway | S93: gleam.io | T93: codwwii ps4 xboxone | U93: 43045.414 | V93: https://twitter.com/#!/ninjarefinery/status/927474566217089025 | Y93: 927474566217089025
A94: lanevox__ | B94: eaa_tw | K94: No | L94: 94 | M94: =IF(AND(OR(NOT(ISNUMBER(Edges[Relationship Date (UTC)])), Edges[Relationship Date (UTC)] >= Misc!$O$2), OR(NOT(ISNUMBER(Edges[Relationship Date (UTC)])), Edges[Relationship Date (UTC)] <= Misc!$P$2),OR(NOT(ISNUMBER(Edges[Tweet Date (UTC)])), Edges[Tweet Date (UTC)] >= Misc!$O$3), OR(NOT(ISNUMBER(Edges[Tweet Date (UTC)])), Edges[Tweet Date (UTC)] <= Misc!$P$3),TRUE), TRUE, FALSE) -> TRUE | O94: Mentions | P94: 43045.414 | Q94: RT @EAA_tw: CoD:WWII： プレステージアイコン全10種と、プレステージマスターアイコンが判明 #CoDWWII https://t.co/PSkNgKtZ3K https://t.co/41SmfDFFhy | R94: http://fpsjp.net/archives/294392 | S94: fpsjp.net | T94: codwwii | U94: 43045.414 | V94: https://twitter.com/#!/lanevox__/status/927474566330335232 | Y94: 927474566330335232
A95: king9507 | B95: turtlebeach | K95: No | L95: 95 | M95: =IF(AND(OR(NOT(ISNUMBER(Edges[Relationship Date (UTC)])), Edges[Relationship Date (UTC)] >= Misc!$O$2), OR(NOT(ISNUMBER(Edges[Relationship Date (UTC)])), Edges[Relationship Date (UTC)] <= Misc!$P$2),OR(NOT(ISNUMBER(Edges[Tweet Date (UTC)])), Edges[Tweet Date (UTC)] >= Misc!$O$3), OR(NOT(ISNUMBER(Edges[Tweet Date (UTC)])), Edges[Tweet Date (UTC)] <= Misc!$P$3),TRUE), TRUE, FALSE) -> TRUE | O95: Mentions | P95: 43045.414 | Q95: RT @turtlebeach: #TGIF We are giving away a WWII limited edition PS4 and Recon Camo to two lucky winners! RT and Enter here: https://t.co/s… | T95: tgif | U95: 43045.414 | V95: https://twitter.com/#!/king9507/status/927474569899896832 | Y95: 927474569899896832
A96: espeviruzz19 | B96: videojuegosgame | K96: No | L96: 96 | M96: =IF(AND(OR(NOT(ISNUMBER(Edges[Relationship Date (UTC)])), Edges[Relationship Date (UTC)] >= Misc!$O$2), OR(NOT(ISNUMBER(Edges[Relationship Date (UTC)])), Edges[Relationship Date (UTC)] <= Misc!$P$2),OR(NOT(ISNUMBER(Edges[Tweet Date (UTC)])), Edges[Tweet Date (UTC)] >= Misc!$O$3), OR(NOT(ISNUMBER(Edges[Tweet Date (UTC)])), Edges[Tweet Date (UTC)] <= Misc!$P$3),TRUE), TRUE, FALSE) -> TRUE | O96: Mentions | P96: 43045.414 | Q96: RT @VideojuegosGAME: ¿Conoces al SOLDADO CAGANER? 🙄 Es el NOOB de GAME, y la estrella de los belenes, ¡consigue el tuyo con el Pase de Temp… | U96: 43045.414 | V96: https://twitter.com/#!/espeviruzz19/status/927474597410287616 | Y96: 927474597410287616
A97: smasha1337 | B97: mattks | K97: No | L97: 97 | M97: =IF(AND(OR(NOT(ISNUMBER(Edges[Relationship Date (UTC)])), Edges[Relationship Date (UTC)] >= Misc!$O$2), OR(NOT(ISNUMBER(Edges[Relationship Date (UTC)])), Edges[Relationship Date (UTC)] <= Misc!$P$2),OR(NOT(ISNUMBER(Edges[Tweet Date (UTC)])), Edges[Tweet Date (UTC)] >= Misc!$O$3), OR(NOT(ISNUMBER(Edges[Tweet Date (UTC)])), Edges[Tweet Date (UTC)] <= Misc!$P$3),TRUE), TRUE, FALSE) -> TRUE | O97: Mentions | P97: 43045.414 | Q97: RT @MaTtKs: Five Guys. 🍔 #CODWWII https://t.co/YfKvKZD3Pa | T97: codwwii | U97: 43045.414 | V97: https://twitter.com/#!/smasha1337/status/927474628339085312 | Y97: 927474628339085312
A98: 2r96 | B98: napoan | K98: No | L98: 98 | M98: =IF(AND(OR(NOT(ISNUMBER(Edges[Relationship Date (UTC)])), Edges[Relationship Date (UTC)] >= Misc!$O$2), OR(NOT(ISNUMBER(Edges[Relationship Date (UTC)])), Edges[Relationship Date (UTC)] <= Misc!$P$2),OR(NOT(ISNUMBER(Edges[Tweet Date (UTC)])), Edges[Tweet Date (UTC)] >= Misc!$O$3), OR(NOT(ISNUMBER(Edges[Tweet Date (UTC)])), Edges[Tweet Date (UTC)] <= Misc!$P$3),TRUE), TRUE, FALSE) -> TRUE | O98: Mentions | P98: 43045.414 | Q98: RT @napoan: フ ォ ン ト の せ い で だ い な し #CODWWII https://t.co/h9XusCgIgQ | T98: codwwii | U98: 43045.414 | V98: https://twitter.com/#!/2r96/status/927474686912479232 | Y98: 927474686912479232
A99: bqliz_ | B99: codww2intel | K99: No | L99: 99 | M99: =IF(AND(OR(NOT(ISNUMBER(Edges[Relationship Date (UTC)])), Edges[Relationship Date (UTC)] >= Misc!$O$2), OR(NOT(ISNUMBER(Edges[Relationship Date (UTC)])), Edges[Relationship Date (UTC)] <= Misc!$P$2),OR(NOT(ISNUMBER(Edges[Tweet Date (UTC)])), Edges[Tweet Date (UTC)] >= Misc!$O$3), OR(NOT(ISNUMBER(Edges[Tweet Date (UTC)])), Edges[Tweet Date (UTC)] <= Misc!$P$3),TRUE), TRUE, FALSE) -> TRUE | O99: Mentions | P99: 43045.414 | Q99: RT @CoDWW2Intel: Here's all of the 10 Prestige + Prestige Master Icons in CoD WWII! #CoDWW2 #CoDWWII Credit: Reddit (LackingAGoodName) htt… | T99: codww2 codwwii | U99: 43045.414 | V99: https://twitter.com/#!/bqliz_/status/927474709020622849 | Y99: 927474709020622849
A100: tamosaurusrex | B100: tamosaurusrex | K100: No | L100: 100 | M100: =IF(AND(OR(NOT(ISNUMBER(Edges[Relationship Date (UTC)])), Edges[Relationship Date (UTC)] >= Misc!$O$2), OR(NOT(ISNUMBER(Edges[Relationship Date (UTC)])), Edges[Relationship Date (UTC)] <= Misc!$P$2),OR(NOT(ISNUMBER(Edges[Tweet Date (UTC)])), Edges[Tweet Date (UTC)] >= Misc!$O$3), OR(NOT(ISNUMBER(Edges[Tweet Date (UTC)])), Edges[Tweet Date (UTC)] <= Misc!$P$3),TRUE), TRUE, FALSE) -> TRUE | O100: Tweet | P100: 43045.414 | Q100: I'm really enjoying #CODWWII what I'm not enjoying is the fking CAMPERS 😡😡 it's 2017, not 2007! Stop being lil chickens. | T100: codwwii | U100: 43045.414 | V100: https://twitter.com/#!/tamosaurusrex/status/927474741715357697 | Y100: 927474741715357697
...

Sheet Vertices
B1: Visual Properties | H1: Labels | L1: Layout | R1: Graph Metrics | AA1: Do Not Edit | AC1: Other Columns
A2: Vertex | B2: Color | C2: Shape | D2: Size | E2: Opacity | F2: Image File | G2: Visibility | H2: Label | I2: Label Fill Color | J2: Label Position | K2: Tooltip | L2: Layout Order | M2: X | N2: Y | O2: Locked? | P2: Polar R | Q2: Polar Angle | R2: Degree | S2: In-Degree | T2: Out-Degree | U2: Betweenness Centrality | V2: Closeness Centrality | W2: Eigenvector Centrality | X2: PageRank | Y2: Clustering Coefficient | Z2: Reciprocated Vertex Pair Ratio | AA2: ID | AB2: Dynamic Filter | AC2: Add Your Own Columns Here | AD2: Followed | AE2: Followers | AF2: Tweets | AG2: Favorites | AH2: Time Zone UTC Offset (Seconds) | AI2: Description | AJ2: Location | AK2: Web | AL2: Time Zone | AM2: Joined Twitter Date (UTC) | AN2: Custom Menu Item Text | AO2: Custom Menu Item Action | AP2: Tweeted Search Term? | AQ2: Top URLs in Tweet by Count | AR2: Top URLs in Tweet by Salience | AS2: Top Domains in Tweet by Count | AT2: Top Domains in Tweet by Salience | AU2: Top Hashtags in Tweet by Count | AV2: Top Hashtags in Tweet by Salience | AW2: Top Words in Tweet by Count | AX2: Top Words in Tweet by Salience | AY2: Top Word Pairs in Tweet by Count | AZ2: Top Word Pairs in Tweet by Salience
A3: cdiscount | B3: Red | C3: 11 | D3: 30 | E3: 100 | F3: http://pbs.twimg.com/profile_images/917402131652661249/DkoSj-wS_normal.jpg | K3: cdiscount | M3: 2580.7253 | N3: 3187.4128 | S3: 152 | T3: 0 | U3: 30105.7 | V3: 0.004545 | W3: 0.030709 | X3: 63.833625 | Y3: 0.00026141513 | Z3: 0 | AA3: 3 | AB3: =IF(AND(OR(NOT(ISNUMBER(Vertices[Size])), Vertices[Size] >= Misc!$O$4), OR(NOT(ISNUMBER(Vertices[Size])), Vertices[Size] <= Misc!$P$4),OR(NOT(ISNUMBER(Vertices[X])), Vertices[X] >= Misc!$O$5), OR(NOT(ISNUMBER(Vertices[X])), Vertices[X] <= Misc!$P$5),OR(NOT(ISNUMBER(Vertices[Y])), Vertices[Y] >= Misc!$O$6), OR(NOT(ISNUMBER(Vertices[Y])), Vertices[Y] <= Misc!$P$6),OR(NOT(ISNUMBER(Vertices[In-Degree])), Vertices[In-Degree] >= Misc!$O$7), OR(NOT(ISNUMBER(Vertices[In-Degree])), Vertices[In-Degree] <= Misc!$P$7),OR(NOT(ISNUMBER(Vertices[Out-Degree])), Vertices[Out-Degree] >= Misc!$O$8), OR(NOT(ISNUMBER(Vertices[Out-Degree])), Vertices[Out-Degree] <= Misc!$P$8),OR(NOT(ISNUMBER(Vertices[Betweenness Centrality])), Vertices[Betweenness Centrality] >= Misc!$O$9), OR(NOT(ISNUMBER(Vertices[Betweenness Centrality])), Vertices[Betweenness Centrality] <= Misc!$P$9),OR(NOT(ISNUMBER(Vertices[Closeness Centrality])), Vertices[Closeness Centrality] >= Misc!$O$10), OR(NOT(ISNUMBER(Vertices[Closeness Centrality])), Vertices[Closeness Centrality] <= Misc!$P$10),OR(NOT(ISNUMBER(Vertices[Eigenvector Centrality])), Vertices[Eigenvector Centrality] >= Misc!$O$11), OR(NOT(ISNUMBER(Vertices[Eigenvector Centrality])), Vertices[Eigenvector Centrality] <= Misc!$P$11),OR(NOT(ISNUMBER(Vertices[PageRank])), Vertices[PageRank] >= Misc!$O$12), OR(NOT(ISNUMBER(Vertices[PageRank])), Vertices[PageRank] <= Misc!$P$12),OR(NOT(ISNUMBER(Vertices[Clustering Coefficient])), Vertices[Clustering Coefficient] >= Misc!$O$13), OR(NOT(ISNUMBER(Vertices[Clustering Coefficient])), Vertices[Clustering Coefficient] <= Misc!$P$13),OR(NOT(ISNUMBER(Vertices[Reciprocated Vertex Pair Ratio])), Vertices[Reciprocated Vertex Pair Ratio] >= Misc!$O$14), OR(NOT(ISNUMBER(Vertices[Reciprocated Vertex Pair Ratio])), Vertices[Reciprocated Vertex Pair Ratio] <= Misc!$P$14),OR(NOT(ISNUMBER(Vertices[Followed])), Vertices[Followed] >= Misc!$O$15), OR(NOT(ISNUMBER(Vertices[Followed])), Vertices[Followed] <= Misc!$P$15),OR(NOT(ISNUMBER(Vertices[Followers])), Vertices[Followers] >= Misc!$O$16), OR(NOT(ISNUMBER(Vertices[Followers])), Vertices[Followers] <= Misc!$P$16),OR(NOT(ISNUMBER(Vertices[Tweets])), Vertices[Tweets] >= Misc!$O$17), OR(NOT(ISNUMBER(Vertices[Tweets])), Vertices[Tweets] <= Misc!$P$17),OR(NOT(ISNUMBER(Vertices[Favorites])), Vertices[Favorites] >= Misc!$O$18), OR(NOT(ISNUMBER(Vertices[Favorites])), Vertices[Favorites] <= Misc!$P$18),OR(NOT(ISNUMBER(Vertices[Time Zone UTC Offset (Seconds)])), Vertices[Time Zone UTC Offset (Seconds)] >= Misc!$O$19), OR(NOT(ISNUMBER(Vertices[Time Zone UTC Offset (Seconds)])), Vertices[Time Zone UTC Offset (Seconds)] <= Misc!$P$19),OR(NOT(ISNUMBER(Vertices[Joined Twitter Date (UTC)])), Vertices[Joined Twitter Date (UTC)] >= Misc!$O$20), OR(NOT(ISNUMBER(Vertices[Joined Twitter Date (UTC)])), Vertices[Joined Twitter Date (UTC)] <= Misc!$P$20),TRUE), TRUE, FALSE) -> FALSE | AD3: 3251 | AE3: 241562 | AF3: 71260 | AG3: 2072 | AH3: 3600 | AI3: Cdiscount, N'économisez pas votre plaisir ! #BonPlan & #Concours 👍 Besoin d'un conseil ? Nous sommes en DM de 08h à 19h | AJ3: France | AK3: https://t.co/IUhLib3sxX | AL3: Paris | AM3: 40030.592 | AN3: Open Twitter Page for This Person | AO3: https://twitter.com/cdiscount | AP3: No
A4: thegrefgyt | B4: Red | C4: 11 | D4: 30 | E4: 100 | F4: http://pbs.twimg.com/profile_images/902159333131264000/xZKRU8s3_normal.jpg | K4: thegrefgyt | M4: 1968.2689 | N4: 7743.728 | S4: 128 | T4: 0 | U4: 17018 | V4: 0.007463 | W4: 1e-06 | X4: 59.234589 | Y4: 0 | Z4: 0 | AA4: 4 | AB4: =IF(AND(OR(NOT(ISNUMBER(Vertices[Size])), Vertices[Size] >= Misc!$O$4), OR(NOT(ISNUMBER(Vertices[Size])), Vertices[Size] <= Misc!$P$4),OR(NOT(ISNUMBER(Vertices[X])), Vertices[X] >= Misc!$O$5), OR(NOT(ISNUMBER(Vertices[X])), Vertices[X] <= Misc!$P$5),OR(NOT(ISNUMBER(Vertices[Y])), Vertices[Y] >= Misc!$O$6), OR(NOT(ISNUMBER(Vertices[Y])), Vertices[Y] <= Misc!$P$6),OR(NOT(ISNUMBER(Vertices[In-Degree])), Vertices[In-Degree] >= Misc!$O$7), OR(NOT(ISNUMBER(Vertices[In-Degree])), Vertices[In-Degree] <= Misc!$P$7),OR(NOT(ISNUMBER(Vertices[Out-Degree])), Vertices[Out-Degree] >= Misc!$O$8), OR(NOT(ISNUMBER(Vertices[Out-Degree])), Vertices[Out-Degree] <= Misc!$P$8),OR(NOT(ISNUMBER(Vertices[Betweenness Centrality])), Vertices[Betweenness Centrality] >= Misc!$O$9), OR(NOT(ISNUMBER(Vertices[Betweenness Centrality])), Vertices[Betweenness Centrality] <= Misc!$P$9),OR(NOT(ISNUMBER(Vertices[Closeness Centrality])), Vertices[Closeness Centrality] >= Misc!$O$10), OR(NOT(ISNUMBER(Vertices[Closeness Centrality])), Vertices[Closeness Centrality] <= Misc!$P$10),OR(NOT(ISNUMBER(Vertices[Eigenvector Centrality])), Vertices[Eigenvector Centrality] >= Misc!$O$11), OR(NOT(ISNUMBER(Vertices[Eigenvector Centrality])), Vertices[Eigenvector Centrality] <= Misc!$P$11),OR(NOT(ISNUMBER(Vertices[PageRank])), Vertices[PageRank] >= Misc!$O$12), OR(NOT(ISNUMBER(Vertices[PageRank])), Vertices[PageRank] <= Misc!$P$12),OR(NOT(ISNUMBER(Vertices[Clustering Coefficient])), Vertices[Clustering Coefficient] >= Misc!$O$13), OR(NOT(ISNUMBER(Vertices[Clustering Coefficient])), Vertices[Clustering Coefficient] <= Misc!$P$13),OR(NOT(ISNUMBER(Vertices[Reciprocated Vertex Pair Ratio])), Vertices[Reciprocated Vertex Pair Ratio] >= Misc!$O$14), OR(NOT(ISNUMBER(Vertices[Reciprocated Vertex Pair Ratio])), Vertices[Reciprocated Vertex Pair Ratio] <= Misc!$P$14),OR(NOT(ISNUMBER(Vertices[Followed])), Vertices[Followed] >= Misc!$O$15), OR(NOT(ISNUMBER(Vertices[Followed])), Vertices[Followed] <= Misc!$P$15),OR(NOT(ISNUMBER(Vertices[Followers])), Vertices[Followers] >= Misc!$O$16), OR(NOT(ISNUMBER(Vertices[Followers])), Vertices[Followers] <= Misc!$P$16),OR(NOT(ISNUMBER(Vertices[Tweets])), Vertices[Tweets] >= Misc!$O$17), OR(NOT(ISNUMBER(Vertices[Tweets])), Vertices[Tweets] <= Misc!$P$17),OR(NOT(ISNUMBER(Vertices[Favorites])), Vertices[Favorites] >= Misc!$O$18), OR(NOT(ISNUMBER(Vertices[Favorites])), Vertices[Favorites] <= Misc!$P$18),OR(NOT(ISNUMBER(Vertices[Time Zone UTC Offset (Seconds)])), Vertices[Time Zone UTC Offset (Seconds)] >= Misc!$O$19), OR(NOT(ISNUMBER(Vertices[Time Zone UTC Offset (Seconds)])), Vertices[Time Zone UTC Offset (Seconds)] <= Misc!$P$19),OR(NOT(ISNUMBER(Vertices[Joined Twitter Date (UTC)])), Vertices[Joined Twitter Date (UTC)] >= Misc!$O$20), OR(NOT(ISNUMBER(Vertices[Joined Twitter Date (UTC)])), Vertices[Joined Twitter Date (UTC)] <= Misc!$P$20),TRUE), TRUE, FALSE) -> FALSE | AD4: 924 | AE4: 1332543 | AF4: 29088 | AG4: 33186 | AH4: 3600 | AI4: Do it! DO IT NOW! @TeamHeretics Owner. Business mail! contactothegrefg@gmail.com - https://t.co/cpNuKF7Woe | AJ4: Youtube Sky | AK4: http://t.co/Lvq0wNfyvT | AL4: Madrid | AM4: 41276.991 | AN4: Open Twitter Page for This Person | AO4: https://twitter.com/thegrefgyt | AP4: No
A5: codww2intel | B5: Red | C5: 11 | D5: 30 | E5: 100 | F5: http://pbs.twimg.com/profile_images/855475307213619200/8kh_qSBk_normal.jpg | K5: codww2intel | M5: 7457.2651 | N5: 2648.4304 | S5: 118 | T5: 0 | U5: 216972.42 | V5: 0.00034 | W5: 0 | X5: 51.635127 | Y5: 0 | Z5: 0 | AA5: 5 | AB5: =IF(AND(OR(NOT(ISNUMBER(Vertices[Size])), Vertices[Size] >= Misc!$O$4), OR(NOT(ISNUMBER(Vertices[Size])), Vertices[Size] <= Misc!$P$4),OR(NOT(ISNUMBER(Vertices[X])), Vertices[X] >= Misc!$O$5), OR(NOT(ISNUMBER(Vertices[X])), Vertices[X] <= Misc!$P$5),OR(NOT(ISNUMBER(Vertices[Y])), Vertices[Y] >= Misc!$O$6), OR(NOT(ISNUMBER(Vertices[Y])), Vertices[Y] <= Misc!$P$6),OR(NOT(ISNUMBER(Vertices[In-Degree])), Vertices[In-Degree] >= Misc!$O$7), OR(NOT(ISNUMBER(Vertices[In-Degree])), Vertices[In-Degree] <= Misc!$P$7),OR(NOT(ISNUMBER(Vertices[Out-Degree])), Vertices[Out-Degree] >= Misc!$O$8), OR(NOT(ISNUMBER(Vertices[Out-Degree])), Vertices[Out-Degree] <= Misc!$P$8),OR(NOT(ISNUMBER(Vertices[Betweenness Centrality])), Vertices[Betweenness Centrality] >= Misc!$O$9), OR(NOT(ISNUMBER(Vertices[Betweenness Centrality])), Vertices[Betweenness Centrality] <= Misc!$P$9),OR(NOT(ISNUMBER(Vertices[Closeness Centrality])), Vertices[Closeness Centrality] >= Misc!$O$10), OR(NOT(ISNUMBER(Vertices[Closeness Centrality])), Vertices[Closeness Centrality] <= Misc!$P$10),OR(NOT(ISNUMBER(Vertices[Eigenvector Centrality])), Vertices[Eigenvector Centrality] >= Misc!$O$11), OR(NOT(ISNUMBER(Vertices[Eigenvector Centrality])), Vertices[Eigenvector Centrality] <= Misc!$P$11),OR(NOT(ISNUMBER(Vertices[PageRank])), Vertices[PageRank] >= Misc!$O$12), OR(NOT(ISNUMBER(Vertices[PageRank])), Vertices[PageRank] <= Misc!$P$12),OR(NOT(ISNUMBER(Vertices[Clustering Coefficient])), Vertices[Clustering Coefficient] >= Misc!$O$13), OR(NOT(ISNUMBER(Vertices[Clustering Coefficient])), Vertices[Clustering Coefficient] <= Misc!$P$13),OR(NOT(ISNUMBER(Vertices[Reciprocated Vertex Pair Ratio])), Vertices[Reciprocated Vertex Pair Ratio] >= Misc!$O$14), OR(NOT(ISNUMBER(Vertices[Reciprocated Vertex Pair Ratio])), Vertices[Reciprocated Vertex Pair Ratio] <= Misc!$P$14),OR(NOT(ISNUMBER(Vertices[Followed])), Vertices[Followed] >= Misc!$O$15), OR(NOT(ISNUMBER(Vertices[Followed])), Vertices[Followed] <= Misc!$P$15),OR(NOT(ISNUMBER(Vertices[Followers])), Vertices[Followers] >= Misc!$O$16), OR(NOT(ISNUMBER(Vertices[Followers])), Vertices[Followers] <= Misc!$P$16),OR(NOT(ISNUMBER(Vertices[Tweets])), Vertices[Tweets] >= Misc!$O$17), OR(NOT(ISNUMBER(Vertices[Tweets])), Vertices[Tweets] <= Misc!$P$17),OR(NOT(ISNUMBER(Vertices[Favorites])), Vertices[Favorites] >= Misc!$O$18), OR(NOT(ISNUMBER(Vertices[Favorites])), Vertices[Favorites] <= Misc!$P$18),OR(NOT(ISNUMBER(Vertices[Time Zone UTC Offset (Seconds)])), Vertices[Time Zone UTC Offset (Seconds)] >= Misc!$O$19), OR(NOT(ISNUMBER(Vertices[Time Zone UTC Offset (Seconds)])), Vertices[Time Zone UTC Offset (Seconds)] <= Misc!$P$19),OR(NOT(ISNUMBER(Vertices[Joined Twitter Date (UTC)])), Vertices[Joined Twitter Date (UTC)] >= Misc!$O$20), OR(NOT(ISNUMBER(Vertices[Joined Twitter Date (UTC)])), Vertices[Joined Twitter Date (UTC)] <= Misc!$P$20),TRUE), TRUE, FALSE) -> FALSE | AD5: 360 | AE5: 157477 | AF5: 4684 | AG5: 26245 | AH5: 0 | AI5: Call of Duty WWII PC, Xbox One & PS4 Servers Down Status #CoDWWII #CoDWW2 Zombies #WWIIZombies #CallofDutyWWII #CallofDutyWW2 #CWL2018 - Run by @GamingIntelCom | AJ5: Los Angeles & London | AK5: https://t.co/nelJ9oWXfX | AL5: London | AM5: 41276.757 | AN5: Open Twitter Page for This Person | AO5: https://twitter.com/codww2intel | AP5: No
A6: eaa_tw | B6: Red | C6: 11 | D6: 30 | E6: 100 | F6: http://pbs.twimg.com/profile_images/770905568223506434/-Jcb2OZH_normal.jpg | K6: eaa_tw | M6: 3317.3066 | N6: 8128.1572 | S6: 93 | T6: 0 | U6: 8924 | V6: 0.010204 | W6: 0 | X6: 43.159427 | Y6: 0 | Z6: 0 | AA6: 6 | AB6: =IF(AND(OR(NOT(ISNUMBER(Vertices[Size])), Vertices[Size] >= Misc!$O$4), OR(NOT(ISNUMBER(Vertices[Size])), Vertices[Size] <= Misc!$P$4),OR(NOT(ISNUMBER(Vertices[X])), Vertices[X] >= Misc!$O$5), OR(NOT(ISNUMBER(Vertices[X])), Vertices[X] <= Misc!$P$5),OR(NOT(ISNUMBER(Vertices[Y])), Vertices[Y] >= Misc!$O$6), OR(NOT(ISNUMBER(Vertices[Y])), Vertices[Y] <= Misc!$P$6),OR(NOT(ISNUMBER(Vertices[In-Degree])), Vertices[In-Degree] >= Misc!$O$7), OR(NOT(ISNUMBER(Vertices[In-Degree])), Vertices[In-Degree] <= Misc!$P$7),OR(NOT(ISNUMBER(Vertices[Out-Degree])), Vertices[Out-Degree] >= Misc!$O$8), OR(NOT(ISNUMBER(Vertices[Out-Degree])), Vertices[Out-Degree] <= Misc!$P$8),OR(NOT(ISNUMBER(Vertices[Betweenness Centrality])), Vertices[Betweenness Centrality] >= Misc!$O$9), OR(NOT(ISNUMBER(Vertices[Betweenness Centrality])), Vertices[Betweenness Centrality] <= Misc!$P$9),OR(NOT(ISNUMBER(Vertices[Closeness Centrality])), Vertices[Closeness Centrality] >= Misc!$O$10), OR(NOT(ISNUMBER(Vertices[Closeness Centrality])), Vertices[Closeness Centrality] <= Misc!$P$10),OR(NOT(ISNUMBER(Vertices[Eigenvector Centrality])), Vertices[Eigenvector Centrality] >= Misc!$O$11), OR(NOT(ISNUMBER(Vertices[Eigenvector Centrality])), Vertices[Eigenvector Centrality] <= Misc!$P$11),OR(NOT(ISNUMBER(Vertices[PageRank])), Vertices[PageRank] >= Misc!$O$12), OR(NOT(ISNUMBER(Vertices[PageRank])), Vertices[PageRank] <= Misc!$P$12),OR(NOT(ISNUMBER(Vertices[Clustering Coefficient])), Vertices[Clustering Coefficient] >= Misc!$O$13), OR(NOT(ISNUMBER(Vertices[Clustering Coefficient])), Vertices[Clustering Coefficient] <= Misc!$P$13),OR(NOT(ISNUMBER(Vertices[Reciprocated Vertex Pair Ratio])), Vertices[Reciprocated Vertex Pair Ratio] >= Misc!$O$14), OR(NOT(ISNUMBER(Vertices[Reciprocated Vertex Pair Ratio])), Vertices[Reciprocated Vertex Pair Ratio] <= Misc!$P$14),OR(NOT(ISNUMBER(Vertices[Followed])), Vertices[Followed] >= Misc!$O$15), OR(NOT(ISNUMBER(Vertices[Followed])), Vertices[Followed] <= Misc!$P$15),OR(NOT(ISNUMBER(Vertices[Followers])), Vertices[Followers] >= Misc!$O$16), OR(NOT(ISNUMBER(Vertices[Followers])), Vertices[Followers] <= Misc!$P$16),OR(NOT(ISNUMBER(Vertices[Tweets])), Vertices[Tweets] >= Misc!$O$17), OR(NOT(ISNUMBER(Vertices[Tweets])), Vertices[Tweets] <= Misc!$P$17),OR(NOT(ISNUMBER(Vertices[Favorites])), Vertices[Favorites] >= Misc!$O$18), OR(NOT(ISNUMBER(Vertices[Favorites])), Vertices[Favorites] <= Misc!$P$18),OR(NOT(ISNUMBER(Vertices[Time Zone UTC Offset (Seconds)])), Vertices[Time Zone UTC Offset (Seconds)] >= Misc!$O$19), OR(NOT(ISNUMBER(Vertices[Time Zone UTC Offset (Seconds)])), Vertices[Time Zone UTC Offset (Seconds)] <= Misc!$P$19),OR(NOT(ISNUMBER(Vertices[Joined Twitter Date (UTC)])), Vertices[Joined Twitter Date (UTC)] >= Misc!$O$20), OR(NOT(ISNUMBER(Vertices[Joined Twitter Date (UTC)])), Vertices[Joined Twitter Date (UTC)] <= Misc!$P$20),TRUE), TRUE, FALSE) -> FALSE | AD6: 643 | AE6: 106912 | AF6: 16905 | AG6: 3775 | AH6: 32400 | AI6: FPS/TPSゲームサイト「EAA!!」の公式アカウントです。関係ない海外ニュースなどもノリで扱うよ。YouTube📺 https://t.co/yrnDgPUxNx / 中身@EAA_Nakami | AJ6: 最前線 | AK6: https://t.co/uDOuQQpBYL | AL6: Tokyo | AM6: 40866.974 | AN6: Open Twitter Page for This Person | AO6: https://twitter.com/eaa_tw | AP6: No
A7: hollowpoiint | B7: Red | C7: 11 | D7: 30 | E7: 100 | F7: http://pbs.twimg.com/profile_images/902532081116487680/JbMm17E__normal.jpg | K7: hollowpoiint | M7: 8655.2334 | N7: 4501.5869 | S7: 76 | T7: 0 | U7: 108400.55 | V7: 0.000361 | W7: 0 | X7: 33.677513 | Y7: 0 | Z7: 0 | AA7: 7 | AB7: =IF(AND(OR(NOT(ISNUMBER(Vertices[Size])), Vertices[Size] >= Misc!$O$4), OR(NOT(ISNUMBER(Vertices[Size])), Vertices[Size] <= Misc!$P$4),OR(NOT(ISNUMBER(Vertices[X])), Vertices[X] >= Misc!$O$5), OR(NOT(ISNUMBER(Vertices[X])), Vertices[X] <= Misc!$P$5),OR(NOT(ISNUMBER(Vertices[Y])), Vertices[Y] >= Misc!$O$6), OR(NOT(ISNUMBER(Vertices[Y])), Vertices[Y] <= Misc!$P$6),OR(NOT(ISNUMBER(Vertices[In-Degree])), Vertices[In-Degree] >= Misc!$O$7), OR(NOT(ISNUMBER(Vertices[In-Degree])), Vertices[In-Degree] <= Misc!$P$7),OR(NOT(ISNUMBER(Vertices[Out-Degree])), Vertices[Out-Degree] >= Misc!$O$8), OR(NOT(ISNUMBER(Vertices[Out-Degree])), Vertices[Out-Degree] <= Misc!$P$8),OR(NOT(ISNUMBER(Vertices[Betweenness Centrality])), Vertices[Betweenness Centrality] >= Misc!$O$9), OR(NOT(ISNUMBER(Vertices[Betweenness Centrality])), Vertices[Betweenness Centrality] <= Misc!$P$9),OR(NOT(ISNUMBER(Vertices[Closeness Centrality])), Vertices[Closeness Centrality] >= Misc!$O$10), OR(NOT(ISNUMBER(Vertices[Closeness Centrality])), Vertices[Closeness Centrality] <= Misc!$P$10),OR(NOT(ISNUMBER(Vertices[Eigenvector Centrality])), Vertices[Eigenvector Centrality] >= Misc!$O$11), OR(NOT(ISNUMBER(Vertices[Eigenvector Centrality])), Vertices[Eigenvector Centrality] <= Misc!$P$11),OR(NOT(ISNUMBER(Vertices[PageRank])), Vertices[PageRank] >= Misc!$O$12), OR(NOT(ISNUMBER(Vertices[PageRank])), Vertices[PageRank] <= Misc!$P$12),OR(NOT(ISNUMBER(Vertices[Clustering Coefficient])), Vertices[Clustering Coefficient] >= Misc!$O$13), OR(NOT(ISNUMBER(Vertices[Clustering Coefficient])), Vertices[Clustering Coefficient] <= Misc!$P$13),OR(NOT(ISNUMBER(Vertices[Reciprocated Vertex Pair Ratio])), Vertices[Reciprocated Vertex Pair Ratio] >= Misc!$O$14), OR(NOT(ISNUMBER(Vertices[Reciprocated Vertex Pair Ratio])), Vertices[Reciprocated Vertex Pair Ratio] <= Misc!$P$14),OR(NOT(ISNUMBER(Vertices[Followed])), Vertices[Followed] >= Misc!$O$15), OR(NOT(ISNUMBER(Vertices[Followed])), Vertices[Followed] <= Misc!$P$15),OR(NOT(ISNUMBER(Vertices[Followers])), Vertices[Followers] >= Misc!$O$16), OR(NOT(ISNUMBER(Vertices[Followers])), Vertices[Followers] <= Misc!$P$16),OR(NOT(ISNUMBER(Vertices[Tweets])), Vertices[Tweets] >= Misc!$O$17), OR(NOT(ISNUMBER(Vertices[Tweets])), Vertices[Tweets] <= Misc!$P$17),OR(NOT(ISNUMBER(Vertices[Favorites])), Vertices[Favorites] >= Misc!$O$18), OR(NOT(ISNUMBER(Vertices[Favorites])), Vertices[Favorites] <= Misc!$P$18),OR(NOT(ISNUMBER(Vertices[Time Zone UTC Offset (Seconds)])), Vertices[Time Zone UTC Offset (Seconds)] >= Misc!$O$19), OR(NOT(ISNUMBER(Vertices[Time Zone UTC Offset (Seconds)])), Vertices[Time Zone UTC Offset (Seconds)] <= Misc!$P$19),OR(NOT(ISNUMBER(Vertices[Joined Twitter Date (UTC)])), Vertices[Joined Twitter Date (UTC)] >= Misc!$O$20), OR(NOT(ISNUMBER(Vertices[Joined Twitter Date (UTC)])), Vertices[Joined Twitter Date (UTC)] <= Misc!$P$20),TRUE), TRUE, FALSE) -> FALSE | AD7: 488 | AE7: 134021 | AF7: 53254 | AG7: 46143 | AH7: -18000 | AI7: 1M+ Subscribers. Use Code HOLLOW For 10% OFF @Kontrolfreek @GFuelEnergy @scufgaming @astrogaming Business Inquiries: HollowPoiintBusiness@gmail.com | AK7: https://t.co/KnSAMYROfN | AL7: Eastern Time (US & Canada) | AM7: 41763.776 | AN7: Open Twitter Page for This Person | AO7: https://twitter.com/hollowpoiint | AP7: No
A8: callofduty | B8: Red | C8: 11 | D8: 30 | E8: 100 | F8: http://pbs.twimg.com/profile_images/911334549316972544/cHfFeiK6_normal.jpg | K8: callofduty | M8: 5244.1753 | N8: 8253.5957 | S8: 55 | T8: 0 | U8: 216519.92 | V8: 0.000377 | W8: 0 | X8: 15.307109 | Y8: 0.001010101 | Z8: 0 | AA8: 8 | AB8: =IF(AND(OR(NOT(ISNUMBER(Vertices[Size])), Vertices[Size] >= Misc!$O$4), OR(NOT(ISNUMBER(Vertices[Size])), Vertices[Size] <= Misc!$P$4),OR(NOT(ISNUMBER(Vertices[X])), Vertices[X] >= Misc!$O$5), OR(NOT(ISNUMBER(Vertices[X])), Vertices[X] <= Misc!$P$5),OR(NOT(ISNUMBER(Vertices[Y])), Vertices[Y] >= Misc!$O$6), OR(NOT(ISNUMBER(Vertices[Y])), Vertices[Y] <= Misc!$P$6),OR(NOT(ISNUMBER(Vertices[In-Degree])), Vertices[In-Degree] >= Misc!$O$7), OR(NOT(ISNUMBER(Vertices[In-Degree])), Vertices[In-Degree] <= Misc!$P$7),OR(NOT(ISNUMBER(Vertices[Out-Degree])), Vertices[Out-Degree] >= Misc!$O$8), OR(NOT(ISNUMBER(Vertices[Out-Degree])), Vertices[Out-Degree] <= Misc!$P$8),OR(NOT(ISNUMBER(Vertices[Betweenness Centrality])), Vertices[Betweenness Centrality] >= Misc!$O$9), OR(NOT(ISNUMBER(Vertices[Betweenness Centrality])), Vertices[Betweenness Centrality] <= Misc!$P$9),OR(NOT(ISNUMBER(Vertices[Closeness Centrality])), Vertices[Closeness Centrality] >= Misc!$O$10), OR(NOT(ISNUMBER(Vertices[Closeness Centrality])), Vertices[Closeness Centrality] <= Misc!$P$10),OR(NOT(ISNUMBER(Vertices[Eigenvector Centrality])), Vertices[Eigenvector Centrality] >= Misc!$O$11), OR(NOT(ISNUMBER(Vertices[Eigenvector Centrality])), Vertices[Eigenvector Centrality] <= Misc!$P$11),OR(NOT(ISNUMBER(Vertices[PageRank])), Vertices[PageRank] >= Misc!$O$12), OR(NOT(ISNUMBER(Vertices[PageRank])), Vertices[PageRank] <= Misc!$P$12),OR(NOT(ISNUMBER(Vertices[Clustering Coefficient])), Vertices[Clustering Coefficient] >= Misc!$O$13), OR(NOT(ISNUMBER(Vertices[Clustering Coefficient])), Vertices[Clustering Coefficient] <= Misc!$P$13),OR(NOT(ISNUMBER(Vertices[Reciprocated Vertex Pair Ratio])), Vertices[Reciprocated Vertex Pair Ratio] >= Misc!$O$14), OR(NOT(ISNUMBER(Vertices[Reciprocated Vertex Pair Ratio])), Vertices[Reciprocated Vertex Pair Ratio] <= Misc!$P$14),OR(NOT(ISNUMBER(Vertices[Followed])), Vertices[Followed] >= Misc!$O$15), OR(NOT(ISNUMBER(Vertices[Followed])), Vertices[Followed] <= Misc!$P$15),OR(NOT(ISNUMBER(Vertices[Followers])), Vertices[Followers] >= Misc!$O$16), OR(NOT(ISNUMBER(Vertices[Followers])), Vertices[Followers] <= Misc!$P$16),OR(NOT(ISNUMBER(Vertices[Tweets])), Vertices[Tweets] >= Misc!$O$17), OR(NOT(ISNUMBER(Vertices[Tweets])), Vertices[Tweets] <= Misc!$P$17),OR(NOT(ISNUMBER(Vertices[Favorites])), Vertices[Favorites] >= Misc!$O$18), OR(NOT(ISNUMBER(Vertices[Favorites])), Vertices[Favorites] <= Misc!$P$18),OR(NOT(ISNUMBER(Vertices[Time Zone UTC Offset (Seconds)])), Vertices[Time Zone UTC Offset (Seconds)] >= Misc!$O$19), OR(NOT(ISNUMBER(Vertices[Time Zone UTC Offset (Seconds)])), Vertices[Time Zone UTC Offset (Seconds)] <= Misc!$P$19),OR(NOT(ISNUMBER(Vertices[Joined Twitter Date (UTC)])), Vertices[Joined Twitter Date (UTC)] >= Misc!$O$20), OR(NOT(ISNUMBER(Vertices[Joined Twitter Date (UTC)])), Vertices[Joined Twitter Date (UTC)] <= Misc!$P$20),TRUE), TRUE, FALSE) -> FALSE | AD8: 11 | AE8: 3365814 | AF8: 16069 | AG8: 12188 | AH8: -28800 | AI8: Official Call of Duty® Twitter page. ESRB Rating: MATURE with Blood and Gore, Drug Reference, Intense Violence, Strong Language, and Suggestive Themes. | AK8: http://t.co/q8Cc0GQjNG | AL8: Pacific Time (US & Canada) | AM8: 40662.778 | AN8: Open Twitter Page for This Person | AO8: https://twitter.com/callofduty | AP8: No
A9: apex_clan1 | B9: Red | C9: 11 | D9: 30 | E9: 100 | F9: http://pbs.twimg.com/profile_images/912405397272764416/8FgyfvGo_normal.jpg | K9: apex_clan1 | M9: 9449.8496 | N9: 761.21246 | S9: 53 | T9: 0 | U9: 73908 | V9: 0.000243 | W9: 0 | X9: 24.267508 | Y9: 0 | Z9: 0 | AA9: 9 | AB9: =IF(AND(OR(NOT(ISNUMBER(Vertices[Size])), Vertices[Size] >= Misc!$O$4), OR(NOT(ISNUMBER(Vertices[Size])), Vertices[Size] <= Misc!$P$4),OR(NOT(ISNUMBER(Vertices[X])), Vertices[X] >= Misc!$O$5), OR(NOT(ISNUMBER(Vertices[X])), Vertices[X] <= Misc!$P$5),OR(NOT(ISNUMBER(Vertices[Y])), Vertices[Y] >= Misc!$O$6), OR(NOT(ISNUMBER(Vertices[Y])), Vertices[Y] <= Misc!$P$6),OR(NOT(ISNUMBER(Vertices[In-Degree])), Vertices[In-Degree] >= Misc!$O$7), OR(NOT(ISNUMBER(Vertices[In-Degree])), Vertices[In-Degree] <= Misc!$P$7),OR(NOT(ISNUMBER(Vertices[Out-Degree])), Vertices[Out-Degree] >= Misc!$O$8), OR(NOT(ISNUMBER(Vertices[Out-Degree])), Vertices[Out-Degree] <= Misc!$P$8),OR(NOT(ISNUMBER(Vertices[Betweenness Centrality])), Vertices[Betweenness Centrality] >= Misc!$O$9), OR(NOT(ISNUMBER(Vertices[Betweenness Centrality])), Vertices[Betweenness Centrality] <= Misc!$P$9),OR(NOT(ISNUMBER(Vertices[Closeness Centrality])), Vertices[Closeness Centrality] >= Misc!$O$10), OR(NOT(ISNUMBER(Vertices[Closeness Centrality])), Vertices[Closeness Centrality] <= Misc!$P$10),OR(NOT(ISNUMBER(Vertices[Eigenvector Centrality])), Vertices[Eigenvector Centrality] >= Misc!$O$11), OR(NOT(ISNUMBER(Vertices[Eigenvector Centrality])), Vertices[Eigenvector Centrality] <= Misc!$P$11),OR(NOT(ISNUMBER(Vertices[PageRank])), Vertices[PageRank] >= Misc!$O$12), OR(NOT(ISNUMBER(Vertices[PageRank])), Vertices[PageRank] <= Misc!$P$12),OR(NOT(ISNUMBER(Vertices[Clustering Coefficient])), Vertices[Clustering Coefficient] >= Misc!$O$13), OR(NOT(ISNUMBER(Vertices[Clustering Coefficient])), Vertices[Clustering Coefficient] <= Misc!$P$13),OR(NOT(ISNUMBER(Vertices[Reciprocated Vertex Pair Ratio])), Vertices[Reciprocated Vertex Pair Ratio] >= Misc!$O$14), OR(NOT(ISNUMBER(Vertices[Reciprocated Vertex Pair Ratio])), Vertices[Reciprocated Vertex Pair Ratio] <= Misc!$P$14),OR(NOT(ISNUMBER(Vertices[Followed])), Vertices[Followed] >= Misc!$O$15), OR(NOT(ISNUMBER(Vertices[Followed])), Vertices[Followed] <= Misc!$P$15),OR(NOT(ISNUMBER(Vertices[Followers])), Vertices[Followers] >= Misc!$O$16), OR(NOT(ISNUMBER(Vertices[Followers])), Vertices[Followers] <= Misc!$P$16),OR(NOT(ISNUMBER(Vertices[Tweets])), Vertices[Tweets] >= Misc!$O$17), OR(NOT(ISNUMBER(Vertices[Tweets])), Vertices[Tweets] <= Misc!$P$17),OR(NOT(ISNUMBER(Vertices[Favorites])), Vertices[Favorites] >= Misc!$O$18), OR(NOT(ISNUMBER(Vertices[Favorites])), Vertices[Favorites] <= Misc!$P$18),OR(NOT(ISNUMBER(Vertices[Time Zone UTC Offset (Seconds)])), Vertices[Time Zone UTC Offset (Seconds)] >= Misc!$O$19), OR(NOT(ISNUMBER(Vertices[Time Zone UTC Offset (Seconds)])), Vertices[Time Zone UTC Offset (Seconds)] <= Misc!$P$19),OR(NOT(ISNUMBER(Vertices[Joined Twitter Date (UTC)])), Vertices[Joined Twitter Date (UTC)] >= Misc!$O$20), OR(NOT(ISNUMBER(Vertices[Joined Twitter Date (UTC)])), Vertices[Joined Twitter Date (UTC)] <= Misc!$P$20),TRUE), TRUE, FALSE) -> FALSE | AD9: 56 | AE9: 31219 | AF9: 1486 | AG9: 529 | AH9: 3600 | AI9: Twitter officiel de la ApeX Clan. | AJ9: aymancontactpro@gmail.com | AK9: https://t.co/yFp8YBCfoc | AL9: Paris | AM9: 42142.979 | AN9: Open Twitter Page for This Person | AO9: https://twitter.com/apex_clan1 | AP9: No
A10: rushgamingjp | B10: Red | D10: 1.6103895 | E10: 11.431057 | F10: http://pbs.twimg.com/profile_images/925816996960149505/T3fwirbQ_normal.jpg | K10: rushgamingjp | M10: 2494.5879 | N10: 4838.3862 | S10: 51 | T10: 0 | U10: 3450 | V10: 0.012987 | W10: 0 | X10: 23.774875 | Y10: 0 | Z10: 0 | AA10: 10 | AB10: =IF(AND(OR(NOT(ISNUMBER(Vertices[Size])), Vertices[Size] >= Misc!$O$4), OR(NOT(ISNUMBER(Vertices[Size])), Vertices[Size] <= Misc!$P$4),OR(NOT(ISNUMBER(Vertices[X])), Vertices[X] >= Misc!$O$5), OR(NOT(ISNUMBER(Vertices[X])), Vertices[X] <= Misc!$P$5),OR(NOT(ISNUMBER(Vertices[Y])), Vertices[Y] >= Misc!$O$6), OR(NOT(ISNUMBER(Vertices[Y])), Vertices[Y] <= Misc!$P$6),OR(NOT(ISNUMBER(Vertices[In-Degree])), Vertices[In-Degree] >= Misc!$O$7), OR(NOT(ISNUMBER(Vertices[In-Degree])), Vertices[In-Degree] <= Misc!$P$7),OR(NOT(ISNUMBER(Vertices[Out-Degree])), Vertices[Out-Degree] >= Misc!$O$8), OR(NOT(ISNUMBER(Vertices[Out-Degree])), Vertices[Out-Degree] <= Misc!$P$8),OR(NOT(ISNUMBER(Vertices[Betweenness Centrality])), Vertices[Betweenness Centrality] >= Misc!$O$9), OR(NOT(ISNUMBER(Vertices[Betweenness Centrality])), Vertices[Betweenness Centrality] <= Misc!$P$9),OR(NOT(ISNUMBER(Vertices[Closeness Centrality])), Vertices[Closeness Centrality] >= Misc!$O$10), OR(NOT(ISNUMBER(Vertices[Closeness Centrality])), Vertices[Closeness Centrality] <= Misc!$P$10),OR(NOT(ISNUMBER(Vertices[Eigenvector Centrality])), Vertices[Eigenvector Centrality] >= Misc!$O$11), OR(NOT(ISNUMBER(Vertices[Eigenvector Centrality])), Vertices[Eigenvector Centrality] <= Misc!$P$11),OR(NOT(ISNUMBER(Vertices[PageRank])), Vertices[PageRank] >= Misc!$O$12), OR(NOT(ISNUMBER(Vertices[PageRank])), Vertices[PageRank] <= Misc!$P$12),OR(NOT(ISNUMBER(Vertices[Clustering Coefficient])), Vertices[Clustering Coefficient] >= Misc!$O$13), OR(NOT(ISNUMBER(Vertices[Clustering Coefficient])), Vertices[Clustering Coefficient] <= Misc!$P$13),OR(NOT(ISNUMBER(Vertices[Reciprocated Vertex Pair Ratio])), Vertices[Reciprocated Vertex Pair Ratio] >= Misc!$O$14), OR(NOT(ISNUMBER(Vertices[Reciprocated Vertex Pair Ratio])), Vertices[Reciprocated Vertex Pair Ratio] <= Misc!$P$14),OR(NOT(ISNUMBER(Vertices[Followed])), Vertices[Followed] >= Misc!$O$15), OR(NOT(ISNUMBER(Vertices[Followed])), Vertices[Followed] <= Misc!$P$15),OR(NOT(ISNUMBER(Vertices[Followers])), Vertices[Followers] >= Misc!$O$16), OR(NOT(ISNUMBER(Vertices[Followers])), Vertices[Followers] <= Misc!$P$16),OR(NOT(ISNUMBER(Vertices[Tweets])), Vertices[Tweets] >= Misc!$O$17), OR(NOT(ISNUMBER(Vertices[Tweets])), Vertices[Tweets] <= Misc!$P$17),OR(NOT(ISNUMBER(Vertices[Favorites])), Vertices[Favorites] >= Misc!$O$18), OR(NOT(ISNUMBER(Vertices[Favorites])), Vertices[Favorites] <= Misc!$P$18),OR(NOT(ISNUMBER(Vertices[Time Zone UTC Offset (Seconds)])), Vertices[Time Zone UTC Offset (Seconds)] >= Misc!$O$19), OR(NOT(ISNUMBER(Vertices[Time Zone UTC Offset (Seconds)])), Vertices[Time Zone UTC Offset (Seconds)] <= Misc!$P$19),OR(NOT(ISNUMBER(Vertices[Joined Twitter Date (UTC)])), Vertices[Joined Twitter Date (UTC)] >= Misc!$O$20), OR(NOT(ISNUMBER(Vertices[Joined Twitter Date (UTC)])), Vertices[Joined Twitter Date (UTC)] <= Misc!$P$20),TRUE), TRUE, FALSE) -> TRUE | AD10: 15 | AE10: 2997 | AF10: 52 | AG10: 125 | AH10: -28800 | AI10: Official Account of Professional Call of Duty Team powered by @wekidsinfo 2017 Japan Champions. For Business Inquiries: rushgaming@wekids-inc.com | AK10: https://t.co/M6jDRJqYEH | AL10: Pacific Time (US & Canada) | AM10: 43040.287 | AN10: Open Twitter Page for This Person | AO10: https://twitter.com/rushgamingjp | AP10: No
A11: dexertointel | B11: Red | D11: 1.6393405 | E11: 11.040317 | F11: http://pbs.twimg.com/profile_images/899928346997514240/p2sILHuL_normal.jpg | K11: dexertointel Who's tried to boost at least once? #CODWWII https://t.co/57NmShZA8g | M11: 6426.0054 | N11: 3674.3074 | S11: 46 | T11: 1 | U11: 2508 | V11: 0.016393 | W11: 0 | X11: 20.874196 | Y11: 0 | Z11: 0 | AA11: 11 | AB11: =IF(AND(OR(NOT(ISNUMBER(Vertices[Size])), Vertices[Size] >= Misc!$O$4), OR(NOT(ISNUMBER(Vertices[Size])), Vertices[Size] <= Misc!$P$4),OR(NOT(ISNUMBER(Vertices[X])), Vertices[X] >= Misc!$O$5), OR(NOT(ISNUMBER(Vertices[X])), Vertices[X] <= Misc!$P$5),OR(NOT(ISNUMBER(Vertices[Y])), Vertices[Y] >= Misc!$O$6), OR(NOT(ISNUMBER(Vertices[Y])), Vertices[Y] <= Misc!$P$6),OR(NOT(ISNUMBER(Vertices[In-Degree])), Vertices[In-Degree] >= Misc!$O$7), OR(NOT(ISNUMBER(Vertices[In-Degree])), Vertices[In-Degree] <= Misc!$P$7),OR(NOT(ISNUMBER(Vertices[Out-Degree])), Vertices[Out-Degree] >= Misc!$O$8), OR(NOT(ISNUMBER(Vertices[Out-Degree])), Vertices[Out-Degree] <= Misc!$P$8),OR(NOT(ISNUMBER(Vertices[Betweenness Centrality])), Vertices[Betweenness Centrality] >= Misc!$O$9), OR(NOT(ISNUMBER(Vertices[Betweenness Centrality])), Vertices[Betweenness Centrality] <= Misc!$P$9),OR(NOT(ISNUMBER(Vertices[Closeness Centrality])), Vertices[Closeness Centrality] >= Misc!$O$10), OR(NOT(ISNUMBER(Vertices[Closeness Centrality])), Vertices[Closeness Centrality] <= Misc!$P$10),OR(NOT(ISNUMBER(Vertices[Eigenvector Centrality])), Vertices[Eigenvector Centrality] >= Misc!$O$11), OR(NOT(ISNUMBER(Vertices[Eigenvector Centrality])), Vertices[Eigenvector Centrality] <= Misc!$P$11),OR(NOT(ISNUMBER(Vertices[PageRank])), Vertices[PageRank] >= Misc!$O$12), OR(NOT(ISNUMBER(Vertices[PageRank])), Vertices[PageRank] <= Misc!$P$12),OR(NOT(ISNUMBER(Vertices[Clustering Coefficient])), Vertices[Clustering Coefficient] >= Misc!$O$13), OR(NOT(ISNUMBER(Vertices[Clustering Coefficient])), Vertices[Clustering Coefficient] <= Misc!$P$13),OR(NOT(ISNUMBER(Vertices[Reciprocated Vertex Pair Ratio])), Vertices[Reciprocated Vertex Pair Ratio] >= Misc!$O$14), OR(NOT(ISNUMBER(Vertices[Reciprocated Vertex Pair Ratio])), Vertices[Reciprocated Vertex Pair Ratio] <= Misc!$P$14),OR(NOT(ISNUMBER(Vertices[Followed])), Vertices[Followed] >= Misc!$O$15), OR(NOT(ISNUMBER(Vertices[Followed])), Vertices[Followed] <= Misc!$P$15),OR(NOT(ISNUMBER(Vertices[Followers])), Vertices[Followers] >= Misc!$O$16), OR(NOT(ISNUMBER(Vertices[Followers])), Vertices[Followers] <= Misc!$P$16),OR(NOT(ISNUMBER(Vertices[Tweets])), Vertices[Tweets] >= Misc!$O$17), OR(NOT(ISNUMBER(Vertices[Tweets])), Vertices[Tweets] <= Misc!$P$17),OR(NOT(ISNUMBER(Vertices[Favorites])), Vertices[Favorites] >= Misc!$O$18), OR(NOT(ISNUMBER(Vertices[Favorites])), Vertices[Favorites] <= Misc!$P$18),OR(NOT(ISNUMBER(Vertices[Time Zone UTC Offset (Seconds)])), Vertices[Time Zone UTC Offset (Seconds)] >= Misc!$O$19), OR(NOT(ISNUMBER(Vertices[Time Zone UTC Offset (Seconds)])), Vertices[Time Zone UTC Offset (Seconds)] <= Misc!$P$19),OR(NOT(ISNUMBER(Vertices[Joined Twitter Date (UTC)])), Vertices[Joined Twitter Date (UTC)] >= Misc!$O$20), OR(NOT(ISNUMBER(Vertices[Joined Twitter Date (UTC)])), Vertices[Joined Twitter Date (UTC)] <= Misc!$P$20),TRUE), TRUE, FALSE) -> TRUE | AD11: 1084 | AE11: 100118 | AF11: 32348 | AG11: 3224 | AH11: 0 | AI11: Exclusive CoD Esports News & Entertainment. Also @Dexerto. Try our Beta App iOS: https://t.co/0ozjr9rT9K - Android: https://t.co/rH4zQJMwBP | AJ11: Worldwide | AK11: https://t.co/TdmlpkHRhv | AL11: London | AM11: 40546.067 | AN11: Open Twitter Page for This Person | AO11: https://twitter.com/dexertointel | AP11: Yes | AU11: codwwii | AV11: codwwii | AW11: tried boost once codwwii | AX11: tried boost once codwwii | AY11: tried,boost boost,once once,codwwii | AZ11: tried,boost boost,once once,codwwii
A12: shgames | B12: Red | D12: 1.5032385 | E12: 64.850557 | F12: http://pbs.twimg.com/profile_images/913153929910685696/bL42-M9v_normal.jpg | K12: shgames | M12: 4179.877 | N12: 2160.8386 | S12: 35 | T12: 0 | U12: 132233.98 | V12: 0.000381 | W12: 0 | X12: 10.28755 | Y12: 0.0042016807 | Z12: 0 | AA12: 12 | AB12: =IF(AND(OR(NOT(ISNUMBER(Vertices[Size])), Vertices[Size] >= Misc!$O$4), OR(NOT(ISNUMBER(Vertices[Size])), Vertices[Size] <= Misc!$P$4),OR(NOT(ISNUMBER(Vertices[X])), Vertices[X] >= Misc!$O$5), OR(NOT(ISNUMBER(Vertices[X])), Vertices[X] <= Misc!$P$5),OR(NOT(ISNUMBER(Vertices[Y])), Vertices[Y] >= Misc!$O$6), OR(NOT(ISNUMBER(Vertices[Y])), Vertices[Y] <= Misc!$P$6),OR(NOT(ISNUMBER(Vertices[In-Degree])), Vertices[In-Degree] >= Misc!$O$7), OR(NOT(ISNUMBER(Vertices[In-Degree])), Vertices[In-Degree] <= Misc!$P$7),OR(NOT(ISNUMBER(Vertices[Out-Degree])), Vertices[Out-Degree] >= Misc!$O$8), OR(NOT(ISNUMBER(Vertices[Out-Degree])), Vertices[Out-Degree] <= Misc!$P$8),OR(NOT(ISNUMBER(Vertices[Betweenness Centrality])), Vertices[Betweenness Centrality] >= Misc!$O$9), OR(NOT(ISNUMBER(Vertices[Betweenness Centrality])), Vertices[Betweenness Centrality] <= Misc!$P$9),OR(NOT(ISNUMBER(Vertices[Closeness Centrality])), Vertices[Closeness Centrality] >= Misc!$O$10), OR(NOT(ISNUMBER(Vertices[Closeness Centrality])), Vertices[Closeness Centrality] <= Misc!$P$10),OR(NOT(ISNUMBER(Vertices[Eigenvector Centrality])), Vertices[Eigenvector Centrality] >= Misc!$O$11), OR(NOT(ISNUMBER(Vertices[Eigenvector Centrality])), Vertices[Eigenvector Centrality] <= Misc!$P$11),OR(NOT(ISNUMBER(Vertices[PageRank])), Vertices[PageRank] >= Misc!$O$12), OR(NOT(ISNUMBER(Vertices[PageRank])), Vertices[PageRank] <= Misc!$P$12),OR(NOT(ISNUMBER(Vertices[Clustering Coefficient])), Vertices[Clustering Coefficient] >= Misc!$O$13), OR(NOT(ISNUMBER(Vertices[Clustering Coefficient])), Vertices[Clustering Coefficient] <= Misc!$P$13),OR(NOT(ISNUMBER(Vertices[Reciprocated Vertex Pair Ratio])), Vertices[Reciprocated Vertex Pair Ratio] >= Misc!$O$14), OR(NOT(ISNUMBER(Vertices[Reciprocated Vertex Pair Ratio])), Vertices[Reciprocated Vertex Pair Ratio] <= Misc!$P$14),OR(NOT(ISNUMBER(Vertices[Followed])), Vertices[Followed] >= Misc!$O$15), OR(NOT(ISNUMBER(Vertices[Followed])), Vertices[Followed] <= Misc!$P$15),OR(NOT(ISNUMBER(Vertices[Followers])), Vertices[Followers] >= Misc!$O$16), OR(NOT(ISNUMBER(Vertices[Followers])), Vertices[Followers] <= Misc!$P$16),OR(NOT(ISNUMBER(Vertices[Tweets])), Vertices[Tweets] >= Misc!$O$17), OR(NOT(ISNUMBER(Vertices[Tweets])), Vertices[Tweets] <= Misc!$P$17),OR(NOT(ISNUMBER(Vertices[Favorites])), Vertices[Favorites] >= Misc!$O$18), OR(NOT(ISNUMBER(Vertices[Favorites])), Vertices[Favorites] <= Misc!$P$18),OR(NOT(ISNUMBER(Vertices[Time Zone UTC Offset (Seconds)])), Vertices[Time Zone UTC Offset (Seconds)] >= Misc!$O$19), OR(NOT(ISNUMBER(Vertices[Time Zone UTC Offset (Seconds)])), Vertices[Time Zone UTC Offset (Seconds)] <= Misc!$P$19),OR(NOT(ISNUMBER(Vertices[Joined Twitter Date (UTC)])), Vertices[Joined Twitter Date (UTC)] >= Misc!$O$20), OR(NOT(ISNUMBER(Vertices[Joined Twitter Date (UTC)])), Vertices[Joined Twitter Date (UTC)] <= Misc!$P$20),TRUE), TRUE, FALSE) -> TRUE | AD12: 386 | AE12: 1168907 | AF12: 7868 | AG12: 5076 | AH12: -28800 | AI12: Game Makers. Team behind this year's #CODWWII, #AdvancedWarfare & #MW3. We love #HammerHeads. Not the sharks, but our fans. | AJ12: Bay Area, CA | AK12: https://t.co/zpji1A60jI | AL12: Pacific Time (US & Canada) | AM12: 40245.877 | AN12: Open Twitter Page for This Person | AO12: https://twitter.com/shgames | AP12: No
A13: k_carius | B13: Red | D13: 1.7575755 | E13: 10.438028 | F13: http://pbs.twimg.com/profile_images/923156615821385728/gj8HvYDj_normal.jpg | K13: k_carius | M13: 5365.813 | N13: 3025.5312 | S13: 33 | T13: 0 | U13: 1056 | V13: 0.030303 | W13: 0 | X13: 15.702698 | Y13: 0 | Z13: 0 | AA13: 13 | AB13: =IF(AND(OR(NOT(ISNUMBER(Vertices[Size])), Vertices[Size] >= Misc!$O$4), OR(NOT(ISNUMBER(Vertices[Size])), Vertices[Size] <= Misc!$P$4),OR(NOT(ISNUMBER(Vertices[X])), Vertices[X] >= Misc!$O$5), OR(NOT(ISNUMBER(Vertices[X])), Vertices[X] <= Misc!$P$5),OR(NOT(ISNUMBER(Vertices[Y])), Vertices[Y] >= Misc!$O$6), OR(NOT(ISNUMBER(Vertices[Y])), Vertices[Y] <= Misc!$P$6),OR(NOT(ISNUMBER(Vertices[In-Degree])), Vertices[In-Degree] >= Misc!$O$7), OR(NOT(ISNUMBER(Vertices[In-Degree])), Vertices[In-Degree] <= Misc!$P$7),OR(NOT(ISNUMBER(Vertices[Out-Degree])), Vertices[Out-Degree] >= Misc!$O$8), OR(NOT(ISNUMBER(Vertices[Out-Degree])), Vertices[Out-Degree] <= Misc!$P$8),OR(NOT(ISNUMBER(Vertices[Betweenness Centrality])), Vertices[Betweenness Centrality] >= Misc!$O$9), OR(NOT(ISNUMBER(Vertices[Betweenness Centrality])), Vertices[Betweenness Centrality] <= Misc!$P$9),OR(NOT(ISNUMBER(Vertices[Closeness Centrality])), Vertices[Closeness Centrality] >= Misc!$O$10), OR(NOT(ISNUMBER(Vertices[Closeness Centrality])), Vertices[Closeness Centrality] <= Misc!$P$10),OR(NOT(ISNUMBER(Vertices[Eigenvector Centrality])), Vertices[Eigenvector Centrality] >= Misc!$O$11), OR(NOT(ISNUMBER(Vertices[Eigenvector Centrality])), Vertices[Eigenvector Centrality] <= Misc!$P$11),OR(NOT(ISNUMBER(Vertices[PageRank])), Vertices[PageRank] >= Misc!$O$12), OR(NOT(ISNUMBER(Vertices[PageRank])), Vertices[PageRank] <= Misc!$P$12),OR(NOT(ISNUMBER(Vertices[Clustering Coefficient])), Vertices[Clustering Coefficient] >= Misc!$O$13), OR(NOT(ISNUMBER(Vertices[Clustering Coefficient])), Vertices[Clustering Coefficient] <= Misc!$P$13),OR(NOT(ISNUMBER(Vertices[Reciprocated Vertex Pair Ratio])), Vertices[Reciprocated Vertex Pair Ratio] >= Misc!$O$14), OR(NOT(ISNUMBER(Vertices[Reciprocated Vertex Pair Ratio])), Vertices[Reciprocated Vertex Pair Ratio] <= Misc!$P$14),OR(NOT(ISNUMBER(Vertices[Followed])), Vertices[Followed] >= Misc!$O$15), OR(NOT(ISNUMBER(Vertices[Followed])), Vertices[Followed] <= Misc!$P$15),OR(NOT(ISNUMBER(Vertices[Followers])), Vertices[Followers] >= Misc!$O$16), OR(NOT(ISNUMBER(Vertices[Followers])), Vertices[Followers] <= Misc!$P$16),OR(NOT(ISNUMBER(Vertices[Tweets])), Vertices[Tweets] >= Misc!$O$17), OR(NOT(ISNUMBER(Vertices[Tweets])), Vertices[Tweets] <= Misc!$P$17),OR(NOT(ISNUMBER(Vertices[Favorites])), Vertices[Favorites] >= Misc!$O$18), OR(NOT(ISNUMBER(Vertices[Favorites])), Vertices[Favorites] <= Misc!$P$18),OR(NOT(ISNUMBER(Vertices[Time Zone UTC Offset (Seconds)])), Vertices[Time Zone UTC Offset (Seconds)] >= Misc!$O$19), OR(NOT(ISNUMBER(Vertices[Time Zone UTC Offset (Seconds)])), Vertices[Time Zone UTC Offset (Seconds)] <= Misc!$P$19),OR(NOT(ISNUMBER(Vertices[Joined Twitter Date (UTC)])), Vertices[Joined Twitter Date (UTC)] >= Misc!$O$20), OR(NOT(ISNUMBER(Vertices[Joined Twitter Date (UTC)])), Vertices[Joined Twitter Date (UTC)] <= Misc!$P$20),TRUE), TRUE, FALSE) -> TRUE | AD13: 317 | AE13: 162 | AF13: 3779 | AG13: 1967 | AI13: 爆弾三勇士系コスサミで五年連続堀越二朗やってるバトルシッパーNWUType1大好きーの害悪33フレンズ。 最近破壊筒で誤爆して二階級特進した。 サバゲー、WT、ドイツ国防軍戦車兵、関東軍、アメリカ陸軍第二レンジャー隊やってる バトルシップとダーティハリーは俺の古事記 プラモも作ってるけど最近生産ラインは停滞気味 | AJ13: 盧溝橋 | AM13: 42325.216 | AN13: Open Twitter Page for This Person | AO13: https://twitter.com/k_carius | AP13: No
A14: siefe | B14: Red | D14: 1.5022015 | E14: 25.388742 | F14: http://pbs.twimg.com/profile_images/866072999266570240/KRqegIom_normal.jpg | K14: siefe | M14: 7458.3867 | N14: 8810.9951 | S14: 29 | T14: 0 | U14: 37099.25 | V14: 0.000259 | W14: 0 | X14: 12.634843 | Y14: 0 | Z14: 0 | AA14: 14 | AB14: =IF(AND(OR(NOT(ISNUMBER(Vertices[Size])), Vertices[Size] >= Misc!$O$4), OR(NOT(ISNUMBER(Vertices[Size])), Vertices[Size] <= Misc!$P$4),OR(NOT(ISNUMBER(Vertices[X])), Vertices[X] >= Misc!$O$5), OR(NOT(ISNUMBER(Vertices[X])), Vertices[X] <= Misc!$P$5),OR(NOT(ISNUMBER(Vertices[Y])), Vertices[Y] >= Misc!$O$6), OR(NOT(ISNUMBER(Vertices[Y])), Vertices[Y] <= Misc!$P$6),OR(NOT(ISNUMBER(Vertices[In-Degree])), Vertices[In-Degree] >= Misc!$O$7), OR(NOT(ISNUMBER(Vertices[In-Degree])), Vertices[In-Degree] <= Misc!$P$7),OR(NOT(ISNUMBER(Vertices[Out-Degree])), Vertices[Out-Degree] >= Misc!$O$8), OR(NOT(ISNUMBER(Vertices[Out-Degree])), Vertices[Out-Degree] <= Misc!$P$8),OR(NOT(ISNUMBER(Vertices[Betweenness Centrality])), Vertices[Betweenness Centrality] >= Misc!$O$9), OR(NOT(ISNUMBER(Vertices[Betweenness Centrality])), Vertices[Betweenness Centrality] <= Misc!$P$9),OR(NOT(ISNUMBER(Vertices[Closeness Centrality])), Vertices[Closeness Centrality] >= Misc!$O$10), OR(NOT(ISNUMBER(Vertices[Closeness Centrality])), Vertices[Closeness Centrality] <= Misc!$P$10),OR(NOT(ISNUMBER(Vertices[Eigenvector Centrality])), Vertices[Eigenvector Centrality] >= Misc!$O$11), OR(NOT(ISNUMBER(Vertices[Eigenvector Centrality])), Vertices[Eigenvector Centrality] <= Misc!$P$11),OR(NOT(ISNUMBER(Vertices[PageRank])), Vertices[PageRank] >= Misc!$O$12), OR(NOT(ISNUMBER(Vertices[PageRank])), Vertices[PageRank] <= Misc!$P$12),OR(NOT(ISNUMBER(Vertices[Clustering Coefficient])), Vertices[Clustering Coefficient] >= Misc!$O$13), OR(NOT(ISNUMBER(Vertices[Clustering Coefficient])), Vertices[Clustering Coefficient] <= Misc!$P$13),OR(NOT(ISNUMBER(Vertices[Reciprocated Vertex Pair Ratio])), Vertices[Reciprocated Vertex Pair Ratio] >= Misc!$O$14), OR(NOT(ISNUMBER(Vertices[Reciprocated Vertex Pair Ratio])), Vertices[Reciprocated Vertex Pair Ratio] <= Misc!$P$14),OR(NOT(ISNUMBER(Vertices[Followed])), Vertices[Followed] >= Misc!$O$15), OR(NOT(ISNUMBER(Vertices[Followed])), Vertices[Followed] <= Misc!$P$15),OR(NOT(ISNUMBER(Vertices[Followers])), Vertices[Followers] >= Misc!$O$16), OR(NOT(ISNUMBER(Vertices[Followers])), Vertices[Followers] <= Misc!$P$16),OR(NOT(ISNUMBER(Vertices[Tweets])), Vertices[Tweets] >= Misc!$O$17), OR(NOT(ISNUMBER(Vertices[Tweets])), Vertices[Tweets] <= Misc!$P$17),OR(NOT(ISNUMBER(Vertices[Favorites])), Vertices[Favorites] >= Misc!$O$18), OR(NOT(ISNUMBER(Vertices[Favorites])), Vertices[Favorites] <= Misc!$P$18),OR(NOT(ISNUMBER(Vertices[Time Zone UTC Offset (Seconds)])), Vertices[Time Zone UTC Offset (Seconds)] >= Misc!$O$19), OR(NOT(ISNUMBER(Vertices[Time Zone UTC Offset (Seconds)])), Vertices[Time Zone UTC Offset (Seconds)] <= Misc!$P$19),OR(NOT(ISNUMBER(Vertices[Joined Twitter Date (UTC)])), Vertices[Joined Twitter Date (UTC)] >= Misc!$O$20), OR(NOT(ISNUMBER(Vertices[Joined Twitter Date (UTC)])), Vertices[Joined Twitter Date (UTC)] <= Misc!$P$20),TRUE), TRUE, FALSE) -> TRUE | AD14: 968 | AE14: 114931 | AF14: 20176 | AG14: 54842 | AH14: -28800 | AI14: I play video games on @Microsoft @WatchMixer for a living. 🙃Sponsored by @Corsair & @XSplit | Biz: Business@Siefe.gg | Pics: https://t.co/ycbUybdYqs | AJ14: St Petersburg, FL | AK14: https://t.co/rtdTKI4r6H | AL14: Pacific Time (US & Canada) | AM14: 39989.056 | AN14: Open Twitter Page for This Person | AO14: https://twitter.com/siefe | AP14: No
A15: postabargain | B15: Red | D15: 1.50221 | E15: 17.403199 | F15: http://pbs.twimg.com/profile_images/879443035616051202/tkCtN43l_normal.jpg | K15: postabargain Xbox One S 500GB Console + Assassins Creed Origins + Call of Duty WWII (XB1) - £199.99 #ACOrigins #CODWWII: https://t.co/DWLsiLbi7N | M15: 2795.3435 | N15: 9396.5635 | S15: 27 | T15: 1 | U15: 17847.667 | V15: 0.00026 | W15: 0 | X15: 6.510811 | Y15: 0.0030769231 | Z15: 0 | AA15: 15 | AB15: =IF(AND(OR(NOT(ISNUMBER(Vertices[Size])), Vertices[Size] >= Misc!$O$4), OR(NOT(ISNUMBER(Vertices[Size])), Vertices[Size] <= Misc!$P$4),OR(NOT(ISNUMBER(Vertices[X])), Vertices[X] >= Misc!$O$5), OR(NOT(ISNUMBER(Vertices[X])), Vertices[X] <= Misc!$P$5),OR(NOT(ISNUMBER(Vertices[Y])), Vertices[Y] >= Misc!$O$6), OR(NOT(ISNUMBER(Vertices[Y])), Vertices[Y] <= Misc!$P$6),OR(NOT(ISNUMBER(Vertices[In-Degree])), Vertices[In-Degree] >= Misc!$O$7), OR(NOT(ISNUMBER(Vertices[In-Degree])), Vertices[In-Degree] <= Misc!$P$7),OR(NOT(ISNUMBER(Vertices[Out-Degree])), Vertices[Out-Degree] >= Misc!$O$8), OR(NOT(ISNUMBER(Vertices[Out-Degree])), Vertices[Out-Degree] <= Misc!$P$8),OR(NOT(ISNUMBER(Vertices[Betweenness Centrality])), Vertices[Betweenness Centrality] >= Misc!$O$9), OR(NOT(ISNUMBER(Vertices[Betweenness Centrality])), Vertices[Betweenness Centrality] <= Misc!$P$9),OR(NOT(ISNUMBER(Vertices[Closeness Centrality])), Vertices[Closeness Centrality] >= Misc!$O$10), OR(NOT(ISNUMBER(Vertices[Closeness Centrality])), Vertices[Closeness Centrality] <= Misc!$P$10),OR(NOT(ISNUMBER(Vertices[Eigenvector Centrality])), Vertices[Eigenvector Centrality] >= Misc!$O$11), OR(NOT(ISNUMBER(Vertices[Eigenvector Centrality])), Vertices[Eigenvector Centrality] <= Misc!$P$11),OR(NOT(ISNUMBER(Vertices[PageRank])), Vertices[PageRank] >= Misc!$O$12), OR(NOT(ISNUMBER(Vertices[PageRank])), Vertices[PageRank] <= Misc!$P$12),OR(NOT(ISNUMBER(Vertices[Clustering Coefficient])), Vertices[Clustering Coefficient] >= Misc!$O$13), OR(NOT(ISNUMBER(Vertices[Clustering Coefficient])), Vertices[Clustering Coefficient] <= Misc!$P$13),OR(NOT(ISNUMBER(Vertices[Reciprocated Vertex Pair Ratio])), Vertices[Reciprocated Vertex Pair Ratio] >= Misc!$O$14), OR(NOT(ISNUMBER(Vertices[Reciprocated Vertex Pair Ratio])), Vertices[Reciprocated Vertex Pair Ratio] <= Misc!$P$14),OR(NOT(ISNUMBER(Vertices[Followed])), Vertices[Followed] >= Misc!$O$15), OR(NOT(ISNUMBER(Vertices[Followed])), Vertices[Followed] <= Misc!$P$15),OR(NOT(ISNUMBER(Vertices[Followers])), Vertices[Followers] >= Misc!$O$16), OR(NOT(ISNUMBER(Vertices[Followers])), Vertices[Followers] <= Misc!$P$16),OR(NOT(ISNUMBER(Vertices[Tweets])), Vertices[Tweets] >= Misc!$O$17), OR(NOT(ISNUMBER(Vertices[Tweets])), Vertices[Tweets] <= Misc!$P$17),OR(NOT(ISNUMBER(Vertices[Favorites])), Vertices[Favorites] >= Misc!$O$18), OR(NOT(ISNUMBER(Vertices[Favorites])), Vertices[Favorites] <= Misc!$P$18),OR(NOT(ISNUMBER(Vertices[Time Zone UTC Offset (Seconds)])), Vertices[Time Zone UTC Offset (Seconds)] >= Misc!$O$19), OR(NOT(ISNUMBER(Vertices[Time Zone UTC Offset (Seconds)])), Vertices[Time Zone UTC Offset (Seconds)] <= Misc!$P$19),OR(NOT(ISNUMBER(Vertices[Joined Twitter Date (UTC)])), Vertices[Joined Twitter Date (UTC)] >= Misc!$O$20), OR(NOT(ISNUMBER(Vertices[Joined Twitter Date (UTC)])), Vertices[Joined Twitter Date (UTC)] <= Misc!$P$20),TRUE), TRUE, FALSE) -> TRUE | AD15: 5594 | AE15: 25914 | AF15: 121819 | AG15: 12820 | AH15: 0 | AI15: Postabargain has it's finger on the pulse when it comes to the best gaming/movie/electrical bargains (and more)! Follow us, join in and you WILL save money :) | AJ15: Glasgow, Scotland, UK | AK15: http://t.co/uaVmWYL8fz | AL15: Edinburgh | AM15: 39866.605 | AN15: Open Twitter Page for This Person | AO15: https://twitter.com/postabargain | AP15: Yes | AQ15: http://www.postabargain.co.uk/categories/xbox-one/microsoft-xbox-one-s-500gb-console-xb1/073295 http://www.postabargain.co.uk/categories/ps4/call-of-duty-wwii-ps4/073289 http://www.postabargain.co.uk/categories/ps4/call-of-duty-wwii-pro-edition-includes-season-pass-ps4/073288 | AR15: http://www.postabargain.co.uk/categories/xbox-one/microsoft-xbox-one-s-500gb-console-xb1/073295 http://www.postabargain.co.uk/categories/ps4/call-of-duty-wwii-ps4/073289 http://www.postabargain.co.uk/categories/ps4/call-of-duty-wwii-pro-edition-includes-season-pass-ps4/073288 | AS15: co.uk | AT15: co.uk | AU15: codwwii acorigins | AV15: acorigins codwwii | AW15: call duty wwii 99 codwwii ps4 xbox one s 500gb | AX15: xbox one s 500gb console assassins creed origins xb1 199 | AY15: call,duty duty,wwii xbox,one one,s s,500gb 500gb,console console,assassins assassins,creed creed,origins origins,call | AZ15: xbox,one one,s s,500gb 500gb,console console,assassins assassins,creed creed,origins origins,call wwii,xb1 xb1,199
A16: michaelcondrey | B16: Red | D16: 1.5027965 | E16: 29.813334 | F16: http://pbs.twimg.com/profile_images/925035888312307712/90heWQyn_normal.jpg | K16: michaelcondrey | M16: 4227.7153 | N16: 2282.1787 | S16: 26 | T16: 0 | U16: 47766.079 | V16: 0.000329 | W16: 0 | X16: 7.585132 | Y16: 0 | Z16: 0 | AA16: 16 | AB16: =IF(AND(OR(NOT(ISNUMBER(Vertices[Size])), Vertices[Size] >= Misc!$O$4), OR(NOT(ISNUMBER(Vertices[Size])), Vertices[Size] <= Misc!$P$4),OR(NOT(ISNUMBER(Vertices[X])), Vertices[X] >= Misc!$O$5), OR(NOT(ISNUMBER(Vertices[X])), Vertices[X] <= Misc!$P$5),OR(NOT(ISNUMBER(Vertices[Y])), Vertices[Y] >= Misc!$O$6), OR(NOT(ISNUMBER(Vertices[Y])), Vertices[Y] <= Misc!$P$6),OR(NOT(ISNUMBER(Vertices[In-Degree])), Vertices[In-Degree] >= Misc!$O$7), OR(NOT(ISNUMBER(Vertices[In-Degree])), Vertices[In-Degree] <= Misc!$P$7),OR(NOT(ISNUMBER(Vertices[Out-Degree])), Vertices[Out-Degree] >= Misc!$O$8), OR(NOT(ISNUMBER(Vertices[Out-Degree])), Vertices[Out-Degree] <= Misc!$P$8),OR(NOT(ISNUMBER(Vertices[Betweenness Centrality])), Vertices[Betweenness Centrality] >= Misc!$O$9), OR(NOT(ISNUMBER(Vertices[Betweenness Centrality])), Vertices[Betweenness Centrality] <= Misc!$P$9),OR(NOT(ISNUMBER(Vertices[Closeness Centrality])), Vertices[Closeness Centrality] >= Misc!$O$10), OR(NOT(ISNUMBER(Vertices[Closeness Centrality])), Vertices[Closeness Centrality] <= Misc!$P$10),OR(NOT(ISNUMBER(Vertices[Eigenvector Centrality])), Vertices[Eigenvector Centrality] >= Misc!$O$11), OR(NOT(ISNUMBER(Vertices[Eigenvector Centrality])), Vertices[Eigenvector Centrality] <= Misc!$P$11),OR(NOT(ISNUMBER(Vertices[PageRank])), Vertices[PageRank] >= Misc!$O$12), OR(NOT(ISNUMBER(Vertices[PageRank])), Vertices[PageRank] <= Misc!$P$12),OR(NOT(ISNUMBER(Vertices[Clustering Coefficient])), Vertices[Clustering Coefficient] >= Misc!$O$13), OR(NOT(ISNUMBER(Vertices[Clustering Coefficient])), Vertices[Clustering Coefficient] <= Misc!$P$13),OR(NOT(ISNUMBER(Vertices[Reciprocated Vertex Pair Ratio])), Vertices[Reciprocated Vertex Pair Ratio] >= Misc!$O$14), OR(NOT(ISNUMBER(Vertices[Reciprocated Vertex Pair Ratio])), Vertices[Reciprocated Vertex Pair Ratio] <= Misc!$P$14),OR(NOT(ISNUMBER(Vertices[Followed])), Vertices[Followed] >= Misc!$O$15), OR(NOT(ISNUMBER(Vertices[Followed])), Vertices[Followed] <= Misc!$P$15),OR(NOT(ISNUMBER(Vertices[Followers])), Vertices[Followers] >= Misc!$O$16), OR(NOT(ISNUMBER(Vertices[Followers])), Vertices[Followers] <= Misc!$P$16),OR(NOT(ISNUMBER(Vertices[Tweets])), Vertices[Tweets] >= Misc!$O$17), OR(NOT(ISNUMBER(Vertices[Tweets])), Vertices[Tweets] <= Misc!$P$17),OR(NOT(ISNUMBER(Vertices[Favorites])), Vertices[Favorites] >= Misc!$O$18), OR(NOT(ISNUMBER(Vertices[Favorites])), Vertices[Favorites] <= Misc!$P$18),OR(NOT(ISNUMBER(Vertices[Time Zone UTC Offset (Seconds)])), Vertices[Time Zone UTC Offset (Seconds)] >= Misc!$O$19), OR(NOT(ISNUMBER(Vertices[Time Zone UTC Offset (Seconds)])), Vertices[Time Zone UTC Offset (Seconds)] <= Misc!$P$19),OR(NOT(ISNUMBER(Vertices[Joined Twitter Date (UTC)])), Vertices[Joined Twitter Date (UTC)] >= Misc!$O$20), OR(NOT(ISNUMBER(Vertices[Joined Twitter Date (UTC)])), Vertices[Joined Twitter Date (UTC)] <= Misc!$P$20),TRUE), TRUE, FALSE) -> TRUE | AD16: 294 | AE16: 496253 | AF16: 7581 | AG16: 22 | AH16: -28800 | AI16: Game Maker. Call of Duty: WWII. The original #HammerHead. I once sang with the conductor of the Boston Philharmonic. Views are my own. | AJ16: San Francisco | AK16: https://t.co/yZwdJehjz1 | AL16: Pacific Time (US & Canada) | AM16: 39668.284 | AN16: Open Twitter Page for This Person | AO16: https://twitter.com/michaelcondrey | AP16: No
A17: buhllistic | B17: Red | D17: 1.826927 | E17: 10.26962 | F17: http://pbs.twimg.com/profile_images/922112952760766469/cgCRN8Z4_normal.jpg | K17: buhllistic | M17: 4247.8472 | N17: 5586.6011 | S17: 26 | T17: 0 | U17: 650 | V17: 0.038462 | W17: 0 | X17: 12.486483 | Y17: 0 | Z17: 0 | AA17: 17 | AB17: =IF(AND(OR(NOT(ISNUMBER(Vertices[Size])), Vertices[Size] >= Misc!$O$4), OR(NOT(ISNUMBER(Vertices[Size])), Vertices[Size] <= Misc!$P$4),OR(NOT(ISNUMBER(Vertices[X])), Vertices[X] >= Misc!$O$5), OR(NOT(ISNUMBER(Vertices[X])), Vertices[X] <= Misc!$P$5),OR(NOT(ISNUMBER(Vertices[Y])), Vertices[Y] >= Misc!$O$6), OR(NOT(ISNUMBER(Vertices[Y])), Vertices[Y] <= Misc!$P$6),OR(NOT(ISNUMBER(Vertices[In-Degree])), Vertices[In-Degree] >= Misc!$O$7), OR(NOT(ISNUMBER(Vertices[In-Degree])), Vertices[In-Degree] <= Misc!$P$7),OR(NOT(ISNUMBER(Vertices[Out-Degree])), Vertices[Out-Degree] >= Misc!$O$8), OR(NOT(ISNUMBER(Vertices[Out-Degree])), Vertices[Out-Degree] <= Misc!$P$8),OR(NOT(ISNUMBER(Vertices[Betweenness Centrality])), Vertices[Betweenness Centrality] >= Misc!$O$9), OR(NOT(ISNUMBER(Vertices[Betweenness Centrality])), Vertices[Betweenness Centrality] <= Misc!$P$9),OR(NOT(ISNUMBER(Vertices[Closeness Centrality])), Vertices[Closeness Centrality] >= Misc!$O$10), OR(NOT(ISNUMBER(Vertices[Closeness Centrality])), Vertices[Closeness Centrality] <= Misc!$P$10),OR(NOT(ISNUMBER(Vertices[Eigenvector Centrality])), Vertices[Eigenvector Centrality] >= Misc!$O$11), OR(NOT(ISNUMBER(Vertices[Eigenvector Centrality])), Vertices[Eigenvector Centrality] <= Misc!$P$11),OR(NOT(ISNUMBER(Vertices[PageRank])), Vertices[PageRank] >= Misc!$O$12), OR(NOT(ISNUMBER(Vertices[PageRank])), Vertices[PageRank] <= Misc!$P$12),OR(NOT(ISNUMBER(Vertices[Clustering Coefficient])), Vertices[Clustering Coefficient] >= Misc!$O$13), OR(NOT(ISNUMBER(Vertices[Clustering Coefficient])), Vertices[Clustering Coefficient] <= Misc!$P$13),OR(NOT(ISNUMBER(Vertices[Reciprocated Vertex Pair Ratio])), Vertices[Reciprocated Vertex Pair Ratio] >= Misc!$O$14), OR(NOT(ISNUMBER(Vertices[Reciprocated Vertex Pair Ratio])), Vertices[Reciprocated Vertex Pair Ratio] <= Misc!$P$14),OR(NOT(ISNUMBER(Vertices[Followed])), Vertices[Followed] >= Misc!$O$15), OR(NOT(ISNUMBER(Vertices[Followed])), Vertices[Followed] <= Misc!$P$15),OR(NOT(ISNUMBER(Vertices[Followers])), Vertices[Followers] >= Misc!$O$16), OR(NOT(ISNUMBER(Vertices[Followers])), Vertices[Followers] <= Misc!$P$16),OR(NOT(ISNUMBER(Vertices[Tweets])), Vertices[Tweets] >= Misc!$O$17), OR(NOT(ISNUMBER(Vertices[Tweets])), Vertices[Tweets] <= Misc!$P$17),OR(NOT(ISNUMBER(Vertices[Favorites])), Vertices[Favorites] >= Misc!$O$18), OR(NOT(ISNUMBER(Vertices[Favorites])), Vertices[Favorites] <= Misc!$P$18),OR(NOT(ISNUMBER(Vertices[Time Zone UTC Offset (Seconds)])), Vertices[Time Zone UTC Offset (Seconds)] >= Misc!$O$19), OR(NOT(ISNUMBER(Vertices[Time Zone UTC Offset (Seconds)])), Vertices[Time Zone UTC Offset (Seconds)] <= Misc!$P$19),OR(NOT(ISNUMBER(Vertices[Joined Twitter Date (UTC)])), Vertices[Joined Twitter Date (UTC)] >= Misc!$O$20), OR(NOT(ISNUMBER(Vertices[Joined Twitter Date (UTC)])), Vertices[Joined Twitter Date (UTC)] <= Misc!$P$20),TRUE), TRUE, FALSE) -> TRUE | AD17: 1991 | AE17: 17331 | AF17: 12809 | AG17: 67863 | AH17: -28800 | AI17: i provide #CoDWWII content on the youtube for over 12,000 people when i feel like it | @eRa_Eternity @WeilluminateAll | All Social Medias: @Buhllistic | AJ17: Queens, NY | AK17: https://t.co/xxs52BMDsK | AL17: Pacific Time (US & Canada) | AM17: 42436.108 | AN17: Open Twitter Page for This Person | AO17: https://twitter.com/buhllistic | AP17: No
A18: game_collection | B18: Red | D18: 1.5022015 | E18: 16.82331 | F18: http://pbs.twimg.com/profile_images/800867936131018753/PPv7lqWi_normal.jpg | K18: game_collection | M18: 2795.7046 | N18: 9427.7676 | S18: 25 | T18: 0 | U18: 16449.667 | V18: 0.000259 | W18: 0 | X18: 6.004117 | Y18: 0.0033333333 | Z18: 0 | AA18: 18 | AB18: =IF(AND(OR(NOT(ISNUMBER(Vertices[Size])), Vertices[Size] >= Misc!$O$4), OR(NOT(ISNUMBER(Vertices[Size])), Vertices[Size] <= Misc!$P$4),OR(NOT(ISNUMBER(Vertices[X])), Vertices[X] >= Misc!$O$5), OR(NOT(ISNUMBER(Vertices[X])), Vertices[X] <= Misc!$P$5),OR(NOT(ISNUMBER(Vertices[Y])), Vertices[Y] >= Misc!$O$6), OR(NOT(ISNUMBER(Vertices[Y])), Vertices[Y] <= Misc!$P$6),OR(NOT(ISNUMBER(Vertices[In-Degree])), Vertices[In-Degree] >= Misc!$O$7), OR(NOT(ISNUMBER(Vertices[In-Degree])), Vertices[In-Degree] <= Misc!$P$7),OR(NOT(ISNUMBER(Vertices[Out-Degree])), Vertices[Out-Degree] >= Misc!$O$8), OR(NOT(ISNUMBER(Vertices[Out-Degree])), Vertices[Out-Degree] <= Misc!$P$8),OR(NOT(ISNUMBER(Vertices[Betweenness Centrality])), Vertices[Betweenness Centrality] >= Misc!$O$9), OR(NOT(ISNUMBER(Vertices[Betweenness Centrality])), Vertices[Betweenness Centrality] <= Misc!$P$9),OR(NOT(ISNUMBER(Vertices[Closeness Centrality])), Vertices[Closeness Centrality] >= Misc!$O$10), OR(NOT(ISNUMBER(Vertices[Closeness Centrality])), Vertices[Closeness Centrality] <= Misc!$P$10),OR(NOT(ISNUMBER(Vertices[Eigenvector Centrality])), Vertices[Eigenvector Centrality] >= Misc!$O$11), OR(NOT(ISNUMBER(Vertices[Eigenvector Centrality])), Vertices[Eigenvector Centrality] <= Misc!$P$11),OR(NOT(ISNUMBER(Vertices[PageRank])), Vertices[PageRank] >= Misc!$O$12), OR(NOT(ISNUMBER(Vertices[PageRank])), Vertices[PageRank] <= Misc!$P$12),OR(NOT(ISNUMBER(Vertices[Clustering Coefficient])), Vertices[Clustering Coefficient] >= Misc!$O$13), OR(NOT(ISNUMBER(Vertices[Clustering Coefficient])), Vertices[Clustering Coefficient] <= Misc!$P$13),OR(NOT(ISNUMBER(Vertices[Reciprocated Vertex Pair Ratio])), Vertices[Reciprocated Vertex Pair Ratio] >= Misc!$O$14), OR(NOT(ISNUMBER(Vertices[Reciprocated Vertex Pair Ratio])), Vertices[Reciprocated Vertex Pair Ratio] <= Misc!$P$14),OR(NOT(ISNUMBER(Vertices[Followed])), Vertices[Followed] >= Misc!$O$15), OR(NOT(ISNUMBER(Vertices[Followed])), Vertices[Followed] <= Misc!$P$15),OR(NOT(ISNUMBER(Vertices[Followers])), Vertices[Followers] >= Misc!$O$16), OR(NOT(ISNUMBER(Vertices[Followers])), Vertices[Followers] <= Misc!$P$16),OR(NOT(ISNUMBER(Vertices[Tweets])), Vertices[Tweets] >= Misc!$O$17), OR(NOT(ISNUMBER(Vertices[Tweets])), Vertices[Tweets] <= Misc!$P$17),OR(NOT(ISNUMBER(Vertices[Favorites])), Vertices[Favorites] >= Misc!$O$18), OR(NOT(ISNUMBER(Vertices[Favorites])), Vertices[Favorites] <= Misc!$P$18),OR(NOT(ISNUMBER(Vertices[Time Zone UTC Offset (Seconds)])), Vertices[Time Zone UTC Offset (Seconds)] >= Misc!$O$19), OR(NOT(ISNUMBER(Vertices[Time Zone UTC Offset (Seconds)])), Vertices[Time Zone UTC Offset (Seconds)] <= Misc!$P$19),OR(NOT(ISNUMBER(Vertices[Joined Twitter Date (UTC)])), Vertices[Joined Twitter Date (UTC)] >= Misc!$O$20), OR(NOT(ISNUMBER(Vertices[Joined Twitter Date (UTC)])), Vertices[Joined Twitter Date (UTC)] <= Misc!$P$20),TRUE), TRUE, FALSE) -> TRUE | AD18: 13448 | AE18: 30181 | AF18: 7843 | AG18: 681 | AH18: 0 | AI18: We sell PS4, Xbox One, Switch, PS3, Xbox 360 games. Free UK delivery on everything (International delivery available). Follow us for great offers & poor puns. | AJ18: UK | AK18: http://t.co/02uvmcrBsU | AL18: London | AM18: 40093.887 | AN18: Open Twitter Page for This Person | AO18: https://twitter.com/game_collection | AP18: No
A19: atviassist | B19: Red | D19: 1.502822 | E19: 37.293808 | F19: http://pbs.twimg.com/profile_images/649637858509086721/d7Sfos5K_normal.png | K19: atviassist | M19: 4089.8625 | N19: 2198.1367 | S19: 23 | T19: 0 | U19: 65800.039 | V19: 0.000332 | W19: 0 | X19: 8.196908 | Y19: 0 | Z19: 0 | AA19: 19 | AB19: =IF(AND(OR(NOT(ISNUMBER(Vertices[Size])), Vertices[Size] >= Misc!$O$4), OR(NOT(ISNUMBER(Vertices[Size])), Vertices[Size] <= Misc!$P$4),OR(NOT(ISNUMBER(Vertices[X])), Vertices[X] >= Misc!$O$5), OR(NOT(ISNUMBER(Vertices[X])), Vertices[X] <= Misc!$P$5),OR(NOT(ISNUMBER(Vertices[Y])), Vertices[Y] >= Misc!$O$6), OR(NOT(ISNUMBER(Vertices[Y])), Vertices[Y] <= Misc!$P$6),OR(NOT(ISNUMBER(Vertices[In-Degree])), Vertices[In-Degree] >= Misc!$O$7), OR(NOT(ISNUMBER(Vertices[In-Degree])), Vertices[In-Degree] <= Misc!$P$7),OR(NOT(ISNUMBER(Vertices[Out-Degree])), Vertices[Out-Degree] >= Misc!$O$8), OR(NOT(ISNUMBER(Vertices[Out-Degree])), Vertices[Out-Degree] <= Misc!$P$8),OR(NOT(ISNUMBER(Vertices[Betweenness Centrality])), Vertices[Betweenness Centrality] >= Misc!$O$9), OR(NOT(ISNUMBER(Vertices[Betweenness Centrality])), Vertices[Betweenness Centrality] <= Misc!$P$9),OR(NOT(ISNUMBER(Vertices[Closeness Centrality])), Vertices[Closeness Centrality] >= Misc!$O$10), OR(NOT(ISNUMBER(Vertices[Closeness Centrality])), Vertices[Closeness Centrality] <= Misc!$P$10),OR(NOT(ISNUMBER(Vertices[Eigenvector Centrality])), Vertices[Eigenvector Centrality] >= Misc!$O$11), OR(NOT(ISNUMBER(Vertices[Eigenvector Centrality])), Vertices[Eigenvector Centrality] <= Misc!$P$11),OR(NOT(ISNUMBER(Vertices[PageRank])), Vertices[PageRank] >= Misc!$O$12), OR(NOT(ISNUMBER(Vertices[PageRank])), Vertices[PageRank] <= Misc!$P$12),OR(NOT(ISNUMBER(Vertices[Clustering Coefficient])), Vertices[Clustering Coefficient] >= Misc!$O$13), OR(NOT(ISNUMBER(Vertices[Clustering Coefficient])), Vertices[Clustering Coefficient] <= Misc!$P$13),OR(NOT(ISNUMBER(Vertices[Reciprocated Vertex Pair Ratio])), Vertices[Reciprocated Vertex Pair Ratio] >= Misc!$O$14), OR(NOT(ISNUMBER(Vertices[Reciprocated Vertex Pair Ratio])), Vertices[Reciprocated Vertex Pair Ratio] <= Misc!$P$14),OR(NOT(ISNUMBER(Vertices[Followed])), Vertices[Followed] >= Misc!$O$15), OR(NOT(ISNUMBER(Vertices[Followed])), Vertices[Followed] <= Misc!$P$15),OR(NOT(ISNUMBER(Vertices[Followers])), Vertices[Followers] >= Misc!$O$16), OR(NOT(ISNUMBER(Vertices[Followers])), Vertices[Followers] <= Misc!$P$16),OR(NOT(ISNUMBER(Vertices[Tweets])), Vertices[Tweets] >= Misc!$O$17), OR(NOT(ISNUMBER(Vertices[Tweets])), Vertices[Tweets] <= Misc!$P$17),OR(NOT(ISNUMBER(Vertices[Favorites])), Vertices[Favorites] >= Misc!$O$18), OR(NOT(ISNUMBER(Vertices[Favorites])), Vertices[Favorites] <= Misc!$P$18),OR(NOT(ISNUMBER(Vertices[Time Zone UTC Offset (Seconds)])), Vertices[Time Zone UTC Offset (Seconds)] >= Misc!$O$19), OR(NOT(ISNUMBER(Vertices[Time Zone UTC Offset (Seconds)])), Vertices[Time Zone UTC Offset (Seconds)] <= Misc!$P$19),OR(NOT(ISNUMBER(Vertices[Joined Twitter Date (UTC)])), Vertices[Joined Twitter Date (UTC)] >= Misc!$O$20), OR(NOT(ISNUMBER(Vertices[Joined Twitter Date (UTC)])), Vertices[Joined Twitter Date (UTC)] <= Misc!$P$20),TRUE), TRUE, FALSE) -> TRUE | AD19: 13673 | AE19: 748195 | AF19: 1343390 | AG19: 2088 | AH19: -28800 | AI19: Activision Player Support | AJ19: Santa Monica, CA | AK19: http://t.co/vz96CETWDV | AL19: Pacific Time (US & Canada) | AM19: 40112.085 | AN19: Open Twitter Page for This Person | AO19: https://twitter.com/atviassist | AP19: No
A20: sharp_tk | B20: Red | D20: 1.6808545 | E20: 10.059233 | F20: http://pbs.twimg.com/profile_images/910801659961503745/hyL4TQHq_normal.jpg | K20: sharp_tk | M20: 2717.0764 | N20: 6404.6235 | S20: 22 | T20: 0 | U20: 142.8 | V20: 0.021277 | W20: 0 | X20: 2.644515 | Y20: 0 | Z20: 0 | AA20: 20 | AB20: =IF(AND(OR(NOT(ISNUMBER(Vertices[Size])), Vertices[Size] >= Misc!$O$4), OR(NOT(ISNUMBER(Vertices[Size])), Vertices[Size] <= Misc!$P$4),OR(NOT(ISNUMBER(Vertices[X])), Vertices[X] >= Misc!$O$5), OR(NOT(ISNUMBER(Vertices[X])), Vertices[X] <= Misc!$P$5),OR(NOT(ISNUMBER(Vertices[Y])), Vertices[Y] >= Misc!$O$6), OR(NOT(ISNUMBER(Vertices[Y])), Vertices[Y] <= Misc!$P$6),OR(NOT(ISNUMBER(Vertices[In-Degree])), Vertices[In-Degree] >= Misc!$O$7), OR(NOT(ISNUMBER(Vertices[In-Degree])), Vertices[In-Degree] <= Misc!$P$7),OR(NOT(ISNUMBER(Vertices[Out-Degree])), Vertices[Out-Degree] >= Misc!$O$8), OR(NOT(ISNUMBER(Vertices[Out-Degree])), Vertices[Out-Degree] <= Misc!$P$8),OR(NOT(ISNUMBER(Vertices[Betweenness Centrality])), Vertices[Betweenness Centrality] >= Misc!$O$9), OR(NOT(ISNUMBER(Vertices[Betweenness Centrality])), Vertices[Betweenness Centrality] <= Misc!$P$9),OR(NOT(ISNUMBER(Vertices[Closeness Centrality])), Vertices[Closeness Centrality] >= Misc!$O$10), OR(NOT(ISNUMBER(Vertices[Closeness Centrality])), Vertices[Closeness Centrality] <= Misc!$P$10),OR(NOT(ISNUMBER(Vertices[Eigenvector Centrality])), Vertices[Eigenvector Centrality] >= Misc!$O$11), OR(NOT(ISNUMBER(Vertices[Eigenvector Centrality])), Vertices[Eigenvector Centrality] <= Misc!$P$11),OR(NOT(ISNUMBER(Vertices[PageRank])), Vertices[PageRank] >= Misc!$O$12), OR(NOT(ISNUMBER(Vertices[PageRank])), Vertices[PageRank] <= Misc!$P$12),OR(NOT(ISNUMBER(Vertices[Clustering Coefficient])), Vertices[Clustering Coefficient] >= Misc!$O$13), OR(NOT(ISNUMBER(Vertices[Clustering Coefficient])), Vertices[Clustering Coefficient] <= Misc!$P$13),OR(NOT(ISNUMBER(Vertices[Reciprocated Vertex Pair Ratio])), Vertices[Reciprocated Vertex Pair Ratio] >= Misc!$O$14), OR(NOT(ISNUMBER(Vertices[Reciprocated Vertex Pair Ratio])), Vertices[Reciprocated Vertex Pair Ratio] <= Misc!$P$14),OR(NOT(ISNUMBER(Vertices[Followed])), Vertices[Followed] >= Misc!$O$15), OR(NOT(ISNUMBER(Vertices[Followed])), Vertices[Followed] <= Misc!$P$15),OR(NOT(ISNUMBER(Vertices[Followers])), Vertices[Followers] >= Misc!$O$16), OR(NOT(ISNUMBER(Vertices[Followers])), Vertices[Followers] <= Misc!$P$16),OR(NOT(ISNUMBER(Vertices[Tweets])), Vertices[Tweets] >= Misc!$O$17), OR(NOT(ISNUMBER(Vertices[Tweets])), Vertices[Tweets] <= Misc!$P$17),OR(NOT(ISNUMBER(Vertices[Favorites])), Vertices[Favorites] >= Misc!$O$18), OR(NOT(ISNUMBER(Vertices[Favorites])), Vertices[Favorites] <= Misc!$P$18),OR(NOT(ISNUMBER(Vertices[Time Zone UTC Offset (Seconds)])), Vertices[Time Zone UTC Offset (Seconds)] >= Misc!$O$19), OR(NOT(ISNUMBER(Vertices[Time Zone UTC Offset (Seconds)])), Vertices[Time Zone UTC Offset (Seconds)] <= Misc!$P$19),OR(NOT(ISNUMBER(Vertices[Joined Twitter Date (UTC)])), Vertices[Joined Twitter Date (UTC)] >= Misc!$O$20), OR(NOT(ISNUMBER(Vertices[Joined Twitter Date (UTC)])), Vertices[Joined Twitter Date (UTC)] <= Misc!$P$20),TRUE), TRUE, FALSE) -> TRUE | AD20: 1526 | AE20: 277252 | AF20: 43618 | AG20: 18894 | AH20: -14400 | AI20: Youtuber/Streamer for Team Kaliber. Business Inquiries: Sharp@TeamKaliber.com | AJ20: Kentucky/ATL | AK20: https://t.co/SW7ZftMqiN | AL20: Atlantic Time (Canada) | AM20: 41219.061 | AN20: Open Twitter Page for This Person | AO20: https://twitter.com/sharp_tk | AP20: No
A21: neslo | B21: Red | D21: 1.6808545 | E21: 10.059233 | F21: http://pbs.twimg.com/profile_images/884499649465372672/ifriLItW_normal.jpg | K21: neslo | M21: 2688.0447 | N21: 6354.4595 | S21: 22 | T21: 0 | U21: 142.8 | V21: 0.021277 | W21: 0 | X21: 2.644515 | Y21: 0 | Z21: 0 | AA21: 21 | AB21: =IF(AND(OR(NOT(ISNUMBER(Vertices[Size])), Vertices[Size] >= Misc!$O$4), OR(NOT(ISNUMBER(Vertices[Size])), Vertices[Size] <= Misc!$P$4),OR(NOT(ISNUMBER(Vertices[X])), Vertices[X] >= Misc!$O$5), OR(NOT(ISNUMBER(Vertices[X])), Vertices[X] <= Misc!$P$5),OR(NOT(ISNUMBER(Vertices[Y])), Vertices[Y] >= Misc!$O$6), OR(NOT(ISNUMBER(Vertices[Y])), Vertices[Y] <= Misc!$P$6),OR(NOT(ISNUMBER(Vertices[In-Degree])), Vertices[In-Degree] >= Misc!$O$7), OR(NOT(ISNUMBER(Vertices[In-Degree])), Vertices[In-Degree] <= Misc!$P$7),OR(NOT(ISNUMBER(Vertices[Out-Degree])), Vertices[Out-Degree] >= Misc!$O$8), OR(NOT(ISNUMBER(Vertices[Out-Degree])), Vertices[Out-Degree] <= Misc!$P$8),OR(NOT(ISNUMBER(Vertices[Betweenness Centrality])), Vertices[Betweenness Centrality] >= Misc!$O$9), OR(NOT(ISNUMBER(Vertices[Betweenness Centrality])), Vertices[Betweenness Centrality] <= Misc!$P$9),OR(NOT(ISNUMBER(Vertices[Closeness Centrality])), Vertices[Closeness Centrality] >= Misc!$O$10), OR(NOT(ISNUMBER(Vertices[Closeness Centrality])), Vertices[Closeness Centrality] <= Misc!$P$10),OR(NOT(ISNUMBER(Vertices[Eigenvector Centrality])), Vertices[Eigenvector Centrality] >= Misc!$O$11), OR(NOT(ISNUMBER(Vertices[Eigenvector Centrality])), Vertices[Eigenvector Centrality] <= Misc!$P$11),OR(NOT(ISNUMBER(Vertices[PageRank])), Vertices[PageRank] >= Misc!$O$12), OR(NOT(ISNUMBER(Vertices[PageRank])), Vertices[PageRank] <= Misc!$P$12),OR(NOT(ISNUMBER(Vertices[Clustering Coefficient])), Vertices[Clustering Coefficient] >= Misc!$O$13), OR(NOT(ISNUMBER(Vertices[Clustering Coefficient])), Vertices[Clustering Coefficient] <= Misc!$P$13),OR(NOT(ISNUMBER(Vertices[Reciprocated Vertex Pair Ratio])), Vertices[Reciprocated Vertex Pair Ratio] >= Misc!$O$14), OR(NOT(ISNUMBER(Vertices[Reciprocated Vertex Pair Ratio])), Vertices[Reciprocated Vertex Pair Ratio] <= Misc!$P$14),OR(NOT(ISNUMBER(Vertices[Followed])), Vertices[Followed] >= Misc!$O$15), OR(NOT(ISNUMBER(Vertices[Followed])), Vertices[Followed] <= Misc!$P$15),OR(NOT(ISNUMBER(Vertices[Followers])), Vertices[Followers] >= Misc!$O$16), OR(NOT(ISNUMBER(Vertices[Followers])), Vertices[Followers] <= Misc!$P$16),OR(NOT(ISNUMBER(Vertices[Tweets])), Vertices[Tweets] >= Misc!$O$17), OR(NOT(ISNUMBER(Vertices[Tweets])), Vertices[Tweets] <= Misc!$P$17),OR(NOT(ISNUMBER(Vertices[Favorites])), Vertices[Favorites] >= Misc!$O$18), OR(NOT(ISNUMBER(Vertices[Favorites])), Vertices[Favorites] <= Misc!$P$18),OR(NOT(ISNUMBER(Vertices[Time Zone UTC Offset (Seconds)])), Vertices[Time Zone UTC Offset (Seconds)] >= Misc!$O$19), OR(NOT(ISNUMBER(Vertices[Time Zone UTC Offset (Seconds)])), Vertices[Time Zone UTC Offset (Seconds)] <= Misc!$P$19),OR(NOT(ISNUMBER(Vertices[Joined Twitter Date (UTC)])), Vertices[Joined Twitter Date (UTC)] >= Misc!$O$20), OR(NOT(ISNUMBER(Vertices[Joined Twitter Date (UTC)])), Vertices[Joined Twitter Date (UTC)] <= Misc!$P$20),TRUE), TRUE, FALSE) -> TRUE | AD21: 999 | AE21: 152975 | AF21: 8318 | AG21: 15358 | AH21: -18000 | AI21: Professional Call of Duty Player for @StayPureGG X-Games Medalist | Business Inquiries : neslo@echofox.gg | AK21: https://t.co/tY5CIQ6G14 | AL21: Eastern Time (US & Canada) | AM21: 40512.875 | AN21: Open Twitter Page for This Person | AO21: https://twitter.com/neslo | AP21: No
A22: toshmcgruder | B22: Red | D22: 1.6808545 | E22: 10.059233 | F22: http://pbs.twimg.com/profile_images/643933490233262081/XHlIMzUY_normal.jpg | K22: toshmcgruder | M22: 2685.5737 | N22: 6425.7544 | S22: 22 | T22: 0 | U22: 142.8 | V22: 0.021277 | W22: 0 | X22: 2.644515 | Y22: 0 | Z22: 0 | AA22: 22 | AB22: =IF(AND(OR(NOT(ISNUMBER(Vertices[Size])), Vertices[Size] >= Misc!$O$4), OR(NOT(ISNUMBER(Vertices[Size])), Vertices[Size] <= Misc!$P$4),OR(NOT(ISNUMBER(Vertices[X])), Vertices[X] >= Misc!$O$5), OR(NOT(ISNUMBER(Vertices[X])), Vertices[X] <= Misc!$P$5),OR(NOT(ISNUMBER(Vertices[Y])), Vertices[Y] >= Misc!$O$6), OR(NOT(ISNUMBER(Vertices[Y])), Vertices[Y] <= Misc!$P$6),OR(NOT(ISNUMBER(Vertices[In-Degree])), Vertices[In-Degree] >= Misc!$O$7), OR(NOT(ISNUMBER(Vertices[In-Degree])), Vertices[In-Degree] <= Misc!$P$7),OR(NOT(ISNUMBER(Vertices[Out-Degree])), Vertices[Out-Degree] >= Misc!$O$8), OR(NOT(ISNUMBER(Vertices[Out-Degree])), Vertices[Out-Degree] <= Misc!$P$8),OR(NOT(ISNUMBER(Vertices[Betweenness Centrality])), Vertices[Betweenness Centrality] >= Misc!$O$9), OR(NOT(ISNUMBER(Vertices[Betweenness Centrality])), Vertices[Betweenness Centrality] <= Misc!$P$9),OR(NOT(ISNUMBER(Vertices[Closeness Centrality])), Vertices[Closeness Centrality] >= Misc!$O$10), OR(NOT(ISNUMBER(Vertices[Closeness Centrality])), Vertices[Closeness Centrality] <= Misc!$P$10),OR(NOT(ISNUMBER(Vertices[Eigenvector Centrality])), Vertices[Eigenvector Centrality] >= Misc!$O$11), OR(NOT(ISNUMBER(Vertices[Eigenvector Centrality])), Vertices[Eigenvector Centrality] <= Misc!$P$11),OR(NOT(ISNUMBER(Vertices[PageRank])), Vertices[PageRank] >= Misc!$O$12), OR(NOT(ISNUMBER(Vertices[PageRank])), Vertices[PageRank] <= Misc!$P$12),OR(NOT(ISNUMBER(Vertices[Clustering Coefficient])), Vertices[Clustering Coefficient] >= Misc!$O$13), OR(NOT(ISNUMBER(Vertices[Clustering Coefficient])), Vertices[Clustering Coefficient] <= Misc!$P$13),OR(NOT(ISNUMBER(Vertices[Reciprocated Vertex Pair Ratio])), Vertices[Reciprocated Vertex Pair Ratio] >= Misc!$O$14), OR(NOT(ISNUMBER(Vertices[Reciprocated Vertex Pair Ratio])), Vertices[Reciprocated Vertex Pair Ratio] <= Misc!$P$14),OR(NOT(ISNUMBER(Vertices[Followed])), Vertices[Followed] >= Misc!$O$15), OR(NOT(ISNUMBER(Vertices[Followed])), Vertices[Followed] <= Misc!$P$15),OR(NOT(ISNUMBER(Vertices[Followers])), Vertices[Followers] >= Misc!$O$16), OR(NOT(ISNUMBER(Vertices[Followers])), Vertices[Followers] <= Misc!$P$16),OR(NOT(ISNUMBER(Vertices[Tweets])), Vertices[Tweets] >= Misc!$O$17), OR(NOT(ISNUMBER(Vertices[Tweets])), Vertices[Tweets] <= Misc!$P$17),OR(NOT(ISNUMBER(Vertices[Favorites])), Vertices[Favorites] >= Misc!$O$18), OR(NOT(ISNUMBER(Vertices[Favorites])), Vertices[Favorites] <= Misc!$P$18),OR(NOT(ISNUMBER(Vertices[Time Zone UTC Offset (Seconds)])), Vertices[Time Zone UTC Offset (Seconds)] >= Misc!$O$19), OR(NOT(ISNUMBER(Vertices[Time Zone UTC Offset (Seconds)])), Vertices[Time Zone UTC Offset (Seconds)] <= Misc!$P$19),OR(NOT(ISNUMBER(Vertices[Joined Twitter Date (UTC)])), Vertices[Joined Twitter Date (UTC)] >= Misc!$O$20), OR(NOT(ISNUMBER(Vertices[Joined Twitter Date (UTC)])), Vertices[Joined Twitter Date (UTC)] <= Misc!$P$20),TRUE), TRUE, FALSE) -> TRUE | AD22: 623 | AE22: 72499 | AF22: 9012 | AG22: 42 | AH22: -28800 | AI22: Stainville - Player for @StayPureGG - Full Stack Engineer - Business Inquiries: istainville@gmail.com | AJ22: California | AK22: https://t.co/PeBX4VXtsE | AL22: Pacific Time (US & Canada) | AM22: 39866.262 | AN22: Open Twitter Page for This Person | AO22: https://twitter.com/toshmcgruder | AP22: No
A23: whea7s | B23: Red | D23: 1.6808545 | E23: 10.059233 | F23: http://pbs.twimg.com/profile_images/886705021966069760/SIVyctuQ_normal.jpg | K23: whea7s | M23: 2670.9912 | N23: 6390.3423 | S23: 22 | T23: 0 | U23: 142.8 | V23: 0.021277 | W23: 0 | X23: 2.644515 | Y23: 0 | Z23: 0 | AA23: 23 | AB23: =IF(AND(OR(NOT(ISNUMBER(Vertices[Size])), Vertices[Size] >= Misc!$O$4), OR(NOT(ISNUMBER(Vertices[Size])), Vertices[Size] <= Misc!$P$4),OR(NOT(ISNUMBER(Vertices[X])), Vertices[X] >= Misc!$O$5), OR(NOT(ISNUMBER(Vertices[X])), Vertices[X] <= Misc!$P$5),OR(NOT(ISNUMBER(Vertices[Y])), Vertices[Y] >= Misc!$O$6), OR(NOT(ISNUMBER(Vertices[Y])), Vertices[Y] <= Misc!$P$6),OR(NOT(ISNUMBER(Vertices[In-Degree])), Vertices[In-Degree] >= Misc!$O$7), OR(NOT(ISNUMBER(Vertices[In-Degree])), Vertices[In-Degree] <= Misc!$P$7),OR(NOT(ISNUMBER(Vertices[Out-Degree])), Vertices[Out-Degree] >= Misc!$O$8), OR(NOT(ISNUMBER(Vertices[Out-Degree])), Vertices[Out-Degree] <= Misc!$P$8),OR(NOT(ISNUMBER(Vertices[Betweenness Centrality])), Vertices[Betweenness Centrality] >= Misc!$O$9), OR(NOT(ISNUMBER(Vertices[Betweenness Centrality])), Vertices[Betweenness Centrality] <= Misc!$P$9),OR(NOT(ISNUMBER(Vertices[Closeness Centrality])), Vertices[Closeness Centrality] >= Misc!$O$10), OR(NOT(ISNUMBER(Vertices[Closeness Centrality])), Vertices[Closeness Centrality] <= Misc!$P$10),OR(NOT(ISNUMBER(Vertices[Eigenvector Centrality])), Vertices[Eigenvector Centrality] >= Misc!$O$11), OR(NOT(ISNUMBER(Vertices[Eigenvector Centrality])), Vertices[Eigenvector Centrality] <= Misc!$P$11),OR(NOT(ISNUMBER(Vertices[PageRank])), Vertices[PageRank] >= Misc!$O$12), OR(NOT(ISNUMBER(Vertices[PageRank])), Vertices[PageRank] <= Misc!$P$12),OR(NOT(ISNUMBER(Vertices[Clustering Coefficient])), Vertices[Clustering Coefficient] >= Misc!$O$13), OR(NOT(ISNUMBER(Vertices[Clustering Coefficient])), Vertices[Clustering Coefficient] <= Misc!$P$13),OR(NOT(ISNUMBER(Vertices[Reciprocated Vertex Pair Ratio])), Vertices[Reciprocated Vertex Pair Ratio] >= Misc!$O$14), OR(NOT(ISNUMBER(Vertices[Reciprocated Vertex Pair Ratio])), Vertices[Reciprocated Vertex Pair Ratio] <= Misc!$P$14),OR(NOT(ISNUMBER(Vertices[Followed])), Vertices[Followed] >= Misc!$O$15), OR(NOT(ISNUMBER(Vertices[Followed])), Vertices[Followed] <= Misc!$P$15),OR(NOT(ISNUMBER(Vertices[Followers])), Vertices[Followers] >= Misc!$O$16), OR(NOT(ISNUMBER(Vertices[Followers])), Vertices[Followers] <= Misc!$P$16),OR(NOT(ISNUMBER(Vertices[Tweets])), Vertices[Tweets] >= Misc!$O$17), OR(NOT(ISNUMBER(Vertices[Tweets])), Vertices[Tweets] <= Misc!$P$17),OR(NOT(ISNUMBER(Vertices[Favorites])), Vertices[Favorites] >= Misc!$O$18), OR(NOT(ISNUMBER(Vertices[Favorites])), Vertices[Favorites] <= Misc!$P$18),OR(NOT(ISNUMBER(Vertices[Time Zone UTC Offset (Seconds)])), Vertices[Time Zone UTC Offset (Seconds)] >= Misc!$O$19), OR(NOT(ISNUMBER(Vertices[Time Zone UTC Offset (Seconds)])), Vertices[Time Zone UTC Offset (Seconds)] <= Misc!$P$19),OR(NOT(ISNUMBER(Vertices[Joined Twitter Date (UTC)])), Vertices[Joined Twitter Date (UTC)] >= Misc!$O$20), OR(NOT(ISNUMBER(Vertices[Joined Twitter Date (UTC)])), Vertices[Joined Twitter Date (UTC)] <= Misc!$P$20),TRUE), TRUE, FALSE) -> TRUE | AD23: 555 | AE23: 62496 | AF23: 4108 | AG23: 3014 | AH23: -21600 | AI23: Professional Call Of Duty Player | AJ23: New Orleans, LA | AK23: https://t.co/cS2m87So6w | AL23: Central Time (US & Canada) | AM23: 39865.86 | AN23: Open Twitter Page for This Person | AO23: https://twitter.com/whea7s | AP23: No
A24: staypuregg | B24: Red | D24: 1.6808545 | E24: 10.059233 | F24: http://pbs.twimg.com/profile_images/926194502032769026/ABKqddT7_normal.jpg | K24: staypuregg | M24: 2718.2805 | N24: 6360.9746 | S24: 22 | T24: 0 | U24: 142.8 | V24: 0.021277 | W24: 0 | X24: 2.644515 | Y24: 0 | Z24: 0 | AA24: 24 | AB24: =IF(AND(OR(NOT(ISNUMBER(Vertices[Size])), Vertices[Size] >= Misc!$O$4), OR(NOT(ISNUMBER(Vertices[Size])), Vertices[Size] <= Misc!$P$4),OR(NOT(ISNUMBER(Vertices[X])), Vertices[X] >= Misc!$O$5), OR(NOT(ISNUMBER(Vertices[X])), Vertices[X] <= Misc!$P$5),OR(NOT(ISNUMBER(Vertices[Y])), Vertices[Y] >= Misc!$O$6), OR(NOT(ISNUMBER(Vertices[Y])), Vertices[Y] <= Misc!$P$6),OR(NOT(ISNUMBER(Vertices[In-Degree])), Vertices[In-Degree] >= Misc!$O$7), OR(NOT(ISNUMBER(Vertices[In-Degree])), Vertices[In-Degree] <= Misc!$P$7),OR(NOT(ISNUMBER(Vertices[Out-Degree])), Vertices[Out-Degree] >= Misc!$O$8), OR(NOT(ISNUMBER(Vertices[Out-Degree])), Vertices[Out-Degree] <= Misc!$P$8),OR(NOT(ISNUMBER(Vertices[Betweenness Centrality])), Vertices[Betweenness Centrality] >= Misc!$O$9), OR(NOT(ISNUMBER(Vertices[Betweenness Centrality])), Vertices[Betweenness Centrality] <= Misc!$P$9),OR(NOT(ISNUMBER(Vertices[Closeness Centrality])), Vertices[Closeness Centrality] >= Misc!$O$10), OR(NOT(ISNUMBER(Vertices[Closeness Centrality])), Vertices[Closeness Centrality] <= Misc!$P$10),OR(NOT(ISNUMBER(Vertices[Eigenvector Centrality])), Vertices[Eigenvector Centrality] >= Misc!$O$11), OR(NOT(ISNUMBER(Vertices[Eigenvector Centrality])), Vertices[Eigenvector Centrality] <= Misc!$P$11),OR(NOT(ISNUMBER(Vertices[PageRank])), Vertices[PageRank] >= Misc!$O$12), OR(NOT(ISNUMBER(Vertices[PageRank])), Vertices[PageRank] <= Misc!$P$12),OR(NOT(ISNUMBER(Vertices[Clustering Coefficient])), Vertices[Clustering Coefficient] >= Misc!$O$13), OR(NOT(ISNUMBER(Vertices[Clustering Coefficient])), Vertices[Clustering Coefficient] <= Misc!$P$13),OR(NOT(ISNUMBER(Vertices[Reciprocated Vertex Pair Ratio])), Vertices[Reciprocated Vertex Pair Ratio] >= Misc!$O$14), OR(NOT(ISNUMBER(Vertices[Reciprocated Vertex Pair Ratio])), Vertices[Reciprocated Vertex Pair Ratio] <= Misc!$P$14),OR(NOT(ISNUMBER(Vertices[Followed])), Vertices[Followed] >= Misc!$O$15), OR(NOT(ISNUMBER(Vertices[Followed])), Vertices[Followed] <= Misc!$P$15),OR(NOT(ISNUMBER(Vertices[Followers])), Vertices[Followers] >= Misc!$O$16), OR(NOT(ISNUMBER(Vertices[Followers])), Vertices[Followers] <= Misc!$P$16),OR(NOT(ISNUMBER(Vertices[Tweets])), Vertices[Tweets] >= Misc!$O$17), OR(NOT(ISNUMBER(Vertices[Tweets])), Vertices[Tweets] <= Misc!$P$17),OR(NOT(ISNUMBER(Vertices[Favorites])), Vertices[Favorites] >= Misc!$O$18), OR(NOT(ISNUMBER(Vertices[Favorites])), Vertices[Favorites] <= Misc!$P$18),OR(NOT(ISNUMBER(Vertices[Time Zone UTC Offset (Seconds)])), Vertices[Time Zone UTC Offset (Seconds)] >= Misc!$O$19), OR(NOT(ISNUMBER(Vertices[Time Zone UTC Offset (Seconds)])), Vertices[Time Zone UTC Offset (Seconds)] <= Misc!$P$19),OR(NOT(ISNUMBER(Vertices[Joined Twitter Date (UTC)])), Vertices[Joined Twitter Date (UTC)] >= Misc!$O$20), OR(NOT(ISNUMBER(Vertices[Joined Twitter Date (UTC)])), Vertices[Joined Twitter Date (UTC)] <= Misc!$P$20),TRUE), TRUE, FALSE) -> TRUE | AD24: 47 | AE24: 8582 | AF24: 13 | AG24: 46 | AH24: -28800 | AI24: Official Twitter of PURE Gaming. EST. 2017. 📧contact@staypure.gg #StayPURE | AJ24: Los Angeles, CA | AL24: Pacific Time (US & Canada) | AM24: 43035.135 | AN24: Open Twitter Page for This Person | AO24: https://twitter.com/staypuregg | AP24: No
A25: rn4roku | B25: Red | D25: 1.5023205 | E25: 20.876037 | F25: http://pbs.twimg.com/profile_images/926635384733294592/JR8DlJFB_normal.jpg | K25: rn4roku 「オイィィィィイイイ↑ッス！！ どうもォ～中将でぇ～す」 「え～と、今日は流行りのタグを見つけたんで、試してみたいと思います」 「それじゃ、本編、ｽﾀｰｯｽﾀｰｯｽﾀｰｯｽﾀｰｯ…（対馬編集）」… https://t.co/kedtXduCFm | M25: 5684.1782 | N25: 2110.9458 | S25: 21 | T25: 1 | U25: 26220 | V25: 0.000273 | W25: 0 | X25: 9.349856 | Y25: 0 | Z25: 0 | AA25: 25 | AB25: =IF(AND(OR(NOT(ISNUMBER(Vertices[Size])), Vertices[Size] >= Misc!$O$4), OR(NOT(ISNUMBER(Vertices[Size])), Vertices[Size] <= Misc!$P$4),OR(NOT(ISNUMBER(Vertices[X])), Vertices[X] >= Misc!$O$5), OR(NOT(ISNUMBER(Vertices[X])), Vertices[X] <= Misc!$P$5),OR(NOT(ISNUMBER(Vertices[Y])), Vertices[Y] >= Misc!$O$6), OR(NOT(ISNUMBER(Vertices[Y])), Vertices[Y] <= Misc!$P$6),OR(NOT(ISNUMBER(Vertices[In-Degree])), Vertices[In-Degree] >= Misc!$O$7), OR(NOT(ISNUMBER(Vertices[In-Degree])), Vertices[In-Degree] <= Misc!$P$7),OR(NOT(ISNUMBER(Vertices[Out-Degree])), Vertices[Out-Degree] >= Misc!$O$8), OR(NOT(ISNUMBER(Vertices[Out-Degree])), Vertices[Out-Degree] <= Misc!$P$8),OR(NOT(ISNUMBER(Vertices[Betweenness Centrality])), Vertices[Betweenness Centrality] >= Misc!$O$9), OR(NOT(ISNUMBER(Vertices[Betweenness Centrality])), Vertices[Betweenness Centrality] <= Misc!$P$9),OR(NOT(ISNUMBER(Vertices[Closeness Centrality])), Vertices[Closeness Centrality] >= Misc!$O$10), OR(NOT(ISNUMBER(Vertices[Closeness Centrality])), Vertices[Closeness Centrality] <= Misc!$P$10),OR(NOT(ISNUMBER(Vertices[Eigenvector Centrality])), Vertices[Eigenvector Centrality] >= Misc!$O$11), OR(NOT(ISNUMBER(Vertices[Eigenvector Centrality])), Vertices[Eigenvector Centrality] <= Misc!$P$11),OR(NOT(ISNUMBER(Vertices[PageRank])), Vertices[PageRank] >= Misc!$O$12), OR(NOT(ISNUMBER(Vertices[PageRank])), Vertices[PageRank] <= Misc!$P$12),OR(NOT(ISNUMBER(Vertices[Clustering Coefficient])), Vertices[Clustering Coefficient] >= Misc!$O$13), OR(NOT(ISNUMBER(Vertices[Clustering Coefficient])), Vertices[Clustering Coefficient] <= Misc!$P$13),OR(NOT(ISNUMBER(Vertices[Reciprocated Vertex Pair Ratio])), Vertices[Reciprocated Vertex Pair Ratio] >= Misc!$O$14), OR(NOT(ISNUMBER(Vertices[Reciprocated Vertex Pair Ratio])), Vertices[Reciprocated Vertex Pair Ratio] <= Misc!$P$14),OR(NOT(ISNUMBER(Vertices[Followed])), Vertices[Followed] >= Misc!$O$15), OR(NOT(ISNUMBER(Vertices[Followed])), Vertices[Followed] <= Misc!$P$15),OR(NOT(ISNUMBER(Vertices[Followers])), Vertices[Followers] >= Misc!$O$16), OR(NOT(ISNUMBER(Vertices[Followers])), Vertices[Followers] <= Misc!$P$16),OR(NOT(ISNUMBER(Vertices[Tweets])), Vertices[Tweets] >= Misc!$O$17), OR(NOT(ISNUMBER(Vertices[Tweets])), Vertices[Tweets] <= Misc!$P$17),OR(NOT(ISNUMBER(Vertices[Favorites])), Vertices[Favorites] >= Misc!$O$18), OR(NOT(ISNUMBER(Vertices[Favorites])), Vertices[Favorites] <= Misc!$P$18),OR(NOT(ISNUMBER(Vertices[Time Zone UTC Offset (Seconds)])), Vertices[Time Zone UTC Offset (Seconds)] >= Misc!$O$19), OR(NOT(ISNUMBER(Vertices[Time Zone UTC Offset (Seconds)])), Vertices[Time Zone UTC Offset (Seconds)] <= Misc!$P$19),OR(NOT(ISNUMBER(Vertices[Joined Twitter Date (UTC)])), Vertices[Joined Twitter Date (UTC)] >= Misc!$O$20), OR(NOT(ISNUMBER(Vertices[Joined Twitter Date (UTC)])), Vertices[Joined Twitter Date (UTC)] <= Misc!$P$20),TRUE), TRUE, FALSE) -> TRUE | AD25: 8190 | AE25: 7936 | AF25: 355 | AG25: 405 | AH25: 32400 | AI25: 座右の銘は「食事・睡眠・排泄・CoD」／PS4で CoDやBFなどのFPSを中心にゲームをプレイしてます。／スマホではデレステをプレイ中。課金は0か3万、どっちかです。／最近はsyamuさんの動画を見て毎ﾆﾁｨ！パワーを貰ってまｽｩｩｩｩｩ…／PSID：JOHNNY_GRU か、もしくはソウじゃないか、どっちかです。 | AJ25: 最寄りの駅から徒歩1分 | AL25: Tokyo | AM25: 42762.78 | AN25: Open Twitter Page for This Person | AO25: https://twitter.com/rn4roku | AP25: Yes | AQ25: https://twitter.com/i/web/status/927482469577670656 | AR25: https://twitter.com/i/web/status/927482469577670656 | AS25: twitter.com | AT25: twitter.com | AW25: オイィィィィイイイ ッス どうもォ 中将でぇ す え と 今日は流行りのタグを見つけたんで 試してみたいと思います それじゃ | AX25: オイィィィィイイイ ッス どうもォ 中将でぇ す え と 今日は流行りのタグを見つけたんで 試してみたいと思います それじゃ | AY25: オイィィィィイイイ,ッス ッス,どうもォ どうもォ,中将でぇ 中将でぇ,す す,え え,と と,今日は流行りのタグを見つけたんで 今日は流行りのタグを見つけたんで,試してみたいと思います 試してみたいと思います,それじゃ それじゃ,本編 | AZ25: オイィィィィイイイ,ッス ッス,どうもォ どうもォ,中将でぇ 中将でぇ,す す,え え,と と,今日は流行りのタグを見つけたんで 今日は流行りのタグを見つけたんで,試してみたいと思います 試してみたいと思います,それじゃ それじゃ,本編
A26: hyperrts | B26: Red | D26: 1.5018615 | E26: 13.037506 | F26: http://pbs.twimg.com/profile_images/926061830300090368/54X7HbT2_normal.jpg | K26: hyperrts RT @Bxkid7: Good morning live for the #grind on #CODWWII so pumped up today https://t.co/JwkaqdfnTm @J4LOrg @HyperRTs @Day_RTs https://… | M26: 651.31757 | N26: 5253.6816 | S26: 20 | T26: 13 | U26: 7322.8348 | V26: 0.000219 | W26: 0 | X26: 3.462141 | Y26: 0.13076923 | Z26: 0.26923077 | AA26: 26 | AB26: =IF(AND(OR(NOT(ISNUMBER(Vertices[Size])), Vertices[Size] >= Misc!$O$4), OR(NOT(ISNUMBER(Vertices[Size])), Vertices[Size] <= Misc!$P$4),OR(NOT(ISNUMBER(Vertices[X])), Vertices[X] >= Misc!$O$5), OR(NOT(ISNUMBER(Vertices[X])), Vertices[X] <= Misc!$P$5),OR(NOT(ISNUMBER(Vertices[Y])), Vertices[Y] >= Misc!$O$6), OR(NOT(ISNUMBER(Vertices[Y])), Vertices[Y] <= Misc!$P$6),OR(NOT(ISNUMBER(Vertices[In-Degree])), Vertices[In-Degree] >= Misc!$O$7), OR(NOT(ISNUMBER(Vertices[In-Degree])), Vertices[In-Degree] <= Misc!$P$7),OR(NOT(ISNUMBER(Vertices[Out-Degree])), Vertices[Out-Degree] >= Misc!$O$8), OR(NOT(ISNUMBER(Vertices[Out-Degree])), Vertices[Out-Degree] <= Misc!$P$8),OR(NOT(ISNUMBER(Vertices[Betweenness Centrality])), Vertices[Betweenness Centrality] >= Misc!$O$9), OR(NOT(ISNUMBER(Vertices[Betweenness Centrality])), Vertices[Betweenness Centrality] <= Misc!$P$9),OR(NOT(ISNUMBER(Vertices[Closeness Centrality])), Vertices[Closeness Centrality] >= Misc!$O$10), OR(NOT(ISNUMBER(Vertices[Closeness Centrality])), Vertices[Closeness Centrality] <= Misc!$P$10),OR(NOT(ISNUMBER(Vertices[Eigenvector Centrality])), Vertices[Eigenvector Centrality] >= Misc!$O$11), OR(NOT(ISNUMBER(Vertices[Eigenvector Centrality])), Vertices[Eigenvector Centrality] <= Misc!$P$11),OR(NOT(ISNUMBER(Vertices[PageRank])), Vertices[PageRank] >= Misc!$O$12), OR(NOT(ISNUMBER(Vertices[PageRank])), Vertices[PageRank] <= Misc!$P$12),OR(NOT(ISNUMBER(Vertices[Clustering Coefficient])), Vertices[Clustering Coefficient] >= Misc!$O$13), OR(NOT(ISNUMBER(Vertices[Clustering Coefficient])), Vertices[Clustering Coefficient] <= Misc!$P$13),OR(NOT(ISNUMBER(Vertices[Reciprocated Vertex Pair Ratio])), Vertices[Reciprocated Vertex Pair Ratio] >= Misc!$O$14), OR(NOT(ISNUMBER(Vertices[Reciprocated Vertex Pair Ratio])), Vertices[Reciprocated Vertex Pair Ratio] <= Misc!$P$14),OR(NOT(ISNUMBER(Vertices[Followed])), Vertices[Followed] >= Misc!$O$15), OR(NOT(ISNUMBER(Vertices[Followed])), Vertices[Followed] <= Misc!$P$15),OR(NOT(ISNUMBER(Vertices[Followers])), Vertices[Followers] >= Misc!$O$16), OR(NOT(ISNUMBER(Vertices[Followers])), Vertices[Followers] <= Misc!$P$16),OR(NOT(ISNUMBER(Vertices[Tweets])), Vertices[Tweets] >= Misc!$O$17), OR(NOT(ISNUMBER(Vertices[Tweets])), Vertices[Tweets] <= Misc!$P$17),OR(NOT(ISNUMBER(Vertices[Favorites])), Vertices[Favorites] >= Misc!$O$18), OR(NOT(ISNUMBER(Vertices[Favorites])), Vertices[Favorites] <= Misc!$P$18),OR(NOT(ISNUMBER(Vertices[Time Zone UTC Offset (Seconds)])), Vertices[Time Zone UTC Offset (Seconds)] >= Misc!$O$19), OR(NOT(ISNUMBER(Vertices[Time Zone UTC Offset (Seconds)])), Vertices[Time Zone UTC Offset (Seconds)] <= Misc!$P$19),OR(NOT(ISNUMBER(Vertices[Joined Twitter Date (UTC)])), Vertices[Joined Twitter Date (UTC)] >= Misc!$O$20), OR(NOT(ISNUMBER(Vertices[Joined Twitter Date (UTC)])), Vertices[Joined Twitter Date (UTC)] <= Misc!$P$20),TRUE), TRUE, FALSE) -> TRUE | AD26: 66 | AE26: 65734 | AF26: 487902 | AG26: 36498 | AH26: 37800 | AI26: Tag + Follow for RTs. Retweeting since 2015. For inquiries and support please dm @supporthyper. DM for promotion & advertisement ⭐🙌 | AK26: https://t.co/CvWy6Ce6uz | AL26: Adelaide | AM26: 42043.049 | AN26: Open Twitter Page for This Person | AO26: https://twitter.com/hyperrts | AP26: Yes | AQ26: http://www.twitch.tv/bxkid7 | AR26: http://www.twitch.tv/bxkid7 | AS26: twitch.tv | AT26: twitch.tv | AU26: codwwii grind codww2 | AV26: grind codww2 codwwii | AW26: hyperrts codwwii bxkid7 good morning live grind pumped up today | AX26: bxkid7 good morning live grind pumped up today j4lorg day_rts | AY26: rt,bxkid7 bxkid7,good good,morning morning,live live,grind grind,codwwii codwwii,pumped pumped,up up,today today,j4lorg | AZ26: rt,bxkid7 bxkid7,good good,morning morning,live live,grind grind,codwwii codwwii,pumped pumped,up up,today today,j4lorg
A27: fnac | B27: Red | D27: 1.516864 | E27: 11.64466 | F27: http://pbs.twimg.com/profile_images/879248375887130624/YEL0fF_z_normal.jpg | K27: fnac | M27: 2483.2625 | N27: 3252.1401 | S27: 19 | T27: 0 | U27: 3964.9545 | V27: 0.001984 | W27: 0.001588 | X27: 7.522586 | Y27: 0 | Z27: 0 | AA27: 27 | AB27: =IF(AND(OR(NOT(ISNUMBER(Vertices[Size])), Vertices[Size] >= Misc!$O$4), OR(NOT(ISNUMBER(Vertices[Size])), Vertices[Size] <= Misc!$P$4),OR(NOT(ISNUMBER(Vertices[X])), Vertices[X] >= Misc!$O$5), OR(NOT(ISNUMBER(Vertices[X])), Vertices[X] <= Misc!$P$5),OR(NOT(ISNUMBER(Vertices[Y])), Vertices[Y] >= Misc!$O$6), OR(NOT(ISNUMBER(Vertices[Y])), Vertices[Y] <= Misc!$P$6),OR(NOT(ISNUMBER(Vertices[In-Degree])), Vertices[In-Degree] >= Misc!$O$7), OR(NOT(ISNUMBER(Vertices[In-Degree])), Vertices[In-Degree] <= Misc!$P$7),OR(NOT(ISNUMBER(Vertices[Out-Degree])), Vertices[Out-Degree] >= Misc!$O$8), OR(NOT(ISNUMBER(Vertices[Out-Degree])), Vertices[Out-Degree] <= Misc!$P$8),OR(NOT(ISNUMBER(Vertices[Betweenness Centrality])), Vertices[Betweenness Centrality] >= Misc!$O$9), OR(NOT(ISNUMBER(Vertices[Betweenness Centrality])), Vertices[Betweenness Centrality] <= Misc!$P$9),OR(NOT(ISNUMBER(Vertices[Closeness Centrality])), Vertices[Closeness Centrality] >= Misc!$O$10), OR(NOT(ISNUMBER(Vertices[Closeness Centrality])), Vertices[Closeness Centrality] <= Misc!$P$10),OR(NOT(ISNUMBER(Vertices[Eigenvector Centrality])), Vertices[Eigenvector Centrality] >= Misc!$O$11), OR(NOT(ISNUMBER(Vertices[Eigenvector Centrality])), Vertices[Eigenvector Centrality] <= Misc!$P$11),OR(NOT(ISNUMBER(Vertices[PageRank])), Vertices[PageRank] >= Misc!$O$12), OR(NOT(ISNUMBER(Vertices[PageRank])), Vertices[PageRank] <= Misc!$P$12),OR(NOT(ISNUMBER(Vertices[Clustering Coefficient])), Vertices[Clustering Coefficient] >= Misc!$O$13), OR(NOT(ISNUMBER(Vertices[Clustering Coefficient])), Vertices[Clustering Coefficient] <= Misc!$P$13),OR(NOT(ISNUMBER(Vertices[Reciprocated Vertex Pair Ratio])), Vertices[Reciprocated Vertex Pair Ratio] >= Misc!$O$14), OR(NOT(ISNUMBER(Vertices[Reciprocated Vertex Pair Ratio])), Vertices[Reciprocated Vertex Pair Ratio] <= Misc!$P$14),OR(NOT(ISNUMBER(Vertices[Followed])), Vertices[Followed] >= Misc!$O$15), OR(NOT(ISNUMBER(Vertices[Followed])), Vertices[Followed] <= Misc!$P$15),OR(NOT(ISNUMBER(Vertices[Followers])), Vertices[Followers] >= Misc!$O$16), OR(NOT(ISNUMBER(Vertices[Followers])), Vertices[Followers] <= Misc!$P$16),OR(NOT(ISNUMBER(Vertices[Tweets])), Vertices[Tweets] >= Misc!$O$17), OR(NOT(ISNUMBER(Vertices[Tweets])), Vertices[Tweets] <= Misc!$P$17),OR(NOT(ISNUMBER(Vertices[Favorites])), Vertices[Favorites] >= Misc!$O$18), OR(NOT(ISNUMBER(Vertices[Favorites])), Vertices[Favorites] <= Misc!$P$18),OR(NOT(ISNUMBER(Vertices[Time Zone UTC Offset (Seconds)])), Vertices[Time Zone UTC Offset (Seconds)] >= Misc!$O$19), OR(NOT(ISNUMBER(Vertices[Time Zone UTC Offset (Seconds)])), Vertices[Time Zone UTC Offset (Seconds)] <= Misc!$P$19),OR(NOT(ISNUMBER(Vertices[Joined Twitter Date (UTC)])), Vertices[Joined Twitter Date (UTC)] >= Misc!$O$20), OR(NOT(ISNUMBER(Vertices[Joined Twitter Date (UTC)])), Vertices[Joined Twitter Date (UTC)] <= Misc!$P$20),TRUE), TRUE, FALSE) -> TRUE | AD27: 1372 | AE27: 201480 | AF27: 30860 | AG27: 4298 | AH27: 3600 | AI27: Compte officiel de la #Fnac : Actu High Tech / Loisirs / Gaming / Musique / Culture / Bons plans // SAV ➡️ @FnacVousAide - https://t.co/XJynKVH22a | AJ27: France | AK27: https://t.co/JrbiyJbx5b | AL27: Paris | AM27: 39336.382 | AN27: Open Twitter Page for This Person | AO27: https://twitter.com/fnac | AP27: No
A28: astrogaming | B28: Red | D28: 1.5027285 | E28: 29.641067 | F28: http://pbs.twimg.com/profile_images/722892441993392128/ZIa5R9Z9_normal.jpg | K28: astrogaming | M28: 5199.2241 | N28: 8212.418 | S28: 18 | T28: 0 | U28: 47350.776 | V28: 0.000321 | W28: 0 | X28: 4.290754 | Y28: 0 | Z28: 0 | AA28: 28 | AB28: =IF(AND(OR(NOT(ISNUMBER(Vertices[Size])), Vertices[Size] >= Misc!$O$4), OR(NOT(ISNUMBER(Vertices[Size])), Vertices[Size] <= Misc!$P$4),OR(NOT(ISNUMBER(Vertices[X])), Vertices[X] >= Misc!$O$5), OR(NOT(ISNUMBER(Vertices[X])), Vertices[X] <= Misc!$P$5),OR(NOT(ISNUMBER(Vertices[Y])), Vertices[Y] >= Misc!$O$6), OR(NOT(ISNUMBER(Vertices[Y])), Vertices[Y] <= Misc!$P$6),OR(NOT(ISNUMBER(Vertices[In-Degree])), Vertices[In-Degree] >= Misc!$O$7), OR(NOT(ISNUMBER(Vertices[In-Degree])), Vertices[In-Degree] <= Misc!$P$7),OR(NOT(ISNUMBER(Vertices[Out-Degree])), Vertices[Out-Degree] >= Misc!$O$8), OR(NOT(ISNUMBER(Vertices[Out-Degree])), Vertices[Out-Degree] <= Misc!$P$8),OR(NOT(ISNUMBER(Vertices[Betweenness Centrality])), Vertices[Betweenness Centrality] >= Misc!$O$9), OR(NOT(ISNUMBER(Vertices[Betweenness Centrality])), Vertices[Betweenness Centrality] <= Misc!$P$9),OR(NOT(ISNUMBER(Vertices[Closeness Centrality])), Vertices[Closeness Centrality] >= Misc!$O$10), OR(NOT(ISNUMBER(Vertices[Closeness Centrality])), Vertices[Closeness Centrality] <= Misc!$P$10),OR(NOT(ISNUMBER(Vertices[Eigenvector Centrality])), Vertices[Eigenvector Centrality] >= Misc!$O$11), OR(NOT(ISNUMBER(Vertices[Eigenvector Centrality])), Vertices[Eigenvector Centrality] <= Misc!$P$11),OR(NOT(ISNUMBER(Vertices[PageRank])), Vertices[PageRank] >= Misc!$O$12), OR(NOT(ISNUMBER(Vertices[PageRank])), Vertices[PageRank] <= Misc!$P$12),OR(NOT(ISNUMBER(Vertices[Clustering Coefficient])), Vertices[Clustering Coefficient] >= Misc!$O$13), OR(NOT(ISNUMBER(Vertices[Clustering Coefficient])), Vertices[Clustering Coefficient] <= Misc!$P$13),OR(NOT(ISNUMBER(Vertices[Reciprocated Vertex Pair Ratio])), Vertices[Reciprocated Vertex Pair Ratio] >= Misc!$O$14), OR(NOT(ISNUMBER(Vertices[Reciprocated Vertex Pair Ratio])), Vertices[Reciprocated Vertex Pair Ratio] <= Misc!$P$14),OR(NOT(ISNUMBER(Vertices[Followed])), Vertices[Followed] >= Misc!$O$15), OR(NOT(ISNUMBER(Vertices[Followed])), Vertices[Followed] <= Misc!$P$15),OR(NOT(ISNUMBER(Vertices[Followers])), Vertices[Followers] >= Misc!$O$16), OR(NOT(ISNUMBER(Vertices[Followers])), Vertices[Followers] <= Misc!$P$16),OR(NOT(ISNUMBER(Vertices[Tweets])), Vertices[Tweets] >= Misc!$O$17), OR(NOT(ISNUMBER(Vertices[Tweets])), Vertices[Tweets] <= Misc!$P$17),OR(NOT(ISNUMBER(Vertices[Favorites])), Vertices[Favorites] >= Misc!$O$18), OR(NOT(ISNUMBER(Vertices[Favorites])), Vertices[Favorites] <= Misc!$P$18),OR(NOT(ISNUMBER(Vertices[Time Zone UTC Offset (Seconds)])), Vertices[Time Zone UTC Offset (Seconds)] >= Misc!$O$19), OR(NOT(ISNUMBER(Vertices[Time Zone UTC Offset (Seconds)])), Vertices[Time Zone UTC Offset (Seconds)] <= Misc!$P$19),OR(NOT(ISNUMBER(Vertices[Joined Twitter Date (UTC)])), Vertices[Joined Twitter Date (UTC)] >= Misc!$O$20), OR(NOT(ISNUMBER(Vertices[Joined Twitter Date (UTC)])), Vertices[Joined Twitter Date (UTC)] <= Misc!$P$20),TRUE), TRUE, FALSE) -> TRUE | AD28: 3316 | AE28: 1046376 | AF28: 37435 | AG28: 55291 | AH28: -28800 | AI28: The ASTRO crew shares our favorite news about gaming products, lifestyle & #esports . #ASTROfamily @AstroSupport @ASTROStreams https://t.co/tAoRKiEBBl | AJ28: San Francisco, CA | AK28: https://t.co/lPhR0vFNZY | AL28: Pacific Time (US & Canada) | AM28: 39821.822 | AN28: Open Twitter Page for This Person | AO28: https://twitter.com/astrogaming | AP28: No
A29: turtlebeach | B29: Red | D29: 1.502193 | E29: 19.178678 | F29: http://pbs.twimg.com/profile_images/896826823975325697/lRW403E4_normal.jpg | K29: turtlebeach | M29: 2763.9426 | N29: 9354.6758 | S29: 17 | T29: 0 | U29: 22128 | V29: 0.000258 | W29: 0 | X29: 7.338694 | Y29: 0 | Z29: 0 | AA29: 29 | AB29: =IF(AND(OR(NOT(ISNUMBER(Vertices[Size])), Vertices[Size] >= Misc!$O$4), OR(NOT(ISNUMBER(Vertices[Size])), Vertices[Size] <= Misc!$P$4),OR(NOT(ISNUMBER(Vertices[X])), Vertices[X] >= Misc!$O$5), OR(NOT(ISNUMBER(Vertices[X])), Vertices[X] <= Misc!$P$5),OR(NOT(ISNUMBER(Vertices[Y])), Vertices[Y] >= Misc!$O$6), OR(NOT(ISNUMBER(Vertices[Y])), Vertices[Y] <= Misc!$P$6),OR(NOT(ISNUMBER(Vertices[In-Degree])), Vertices[In-Degree] >= Misc!$O$7), OR(NOT(ISNUMBER(Vertices[In-Degree])), Vertices[In-Degree] <= Misc!$P$7),OR(NOT(ISNUMBER(Vertices[Out-Degree])), Vertices[Out-Degree] >= Misc!$O$8), OR(NOT(ISNUMBER(Vertices[Out-Degree])), Vertices[Out-Degree] <= Misc!$P$8),OR(NOT(ISNUMBER(Vertices[Betweenness Centrality])), Vertices[Betweenness Centrality] >= Misc!$O$9), OR(NOT(ISNUMBER(Vertices[Betweenness Centrality])), Vertices[Betweenness Centrality] <= Misc!$P$9),OR(NOT(ISNUMBER(Vertices[Closeness Centrality])), Vertices[Closeness Centrality] >= Misc!$O$10), OR(NOT(ISNUMBER(Vertices[Closeness Centrality])), Vertices[Closeness Centrality] <= Misc!$P$10),OR(NOT(ISNUMBER(Vertices[Eigenvector Centrality])), Vertices[Eigenvector Centrality] >= Misc!$O$11), OR(NOT(ISNUMBER(Vertices[Eigenvector Centrality])), Vertices[Eigenvector Centrality] <= Misc!$P$11),OR(NOT(ISNUMBER(Vertices[PageRank])), Vertices[PageRank] >= Misc!$O$12), OR(NOT(ISNUMBER(Vertices[PageRank])), Vertices[PageRank] <= Misc!$P$12),OR(NOT(ISNUMBER(Vertices[Clustering Coefficient])), Vertices[Clustering Coefficient] >= Misc!$O$13), OR(NOT(ISNUMBER(Vertices[Clustering Coefficient])), Vertices[Clustering Coefficient] <= Misc!$P$13),OR(NOT(ISNUMBER(Vertices[Reciprocated Vertex Pair Ratio])), Vertices[Reciprocated Vertex Pair Ratio] >= Misc!$O$14), OR(NOT(ISNUMBER(Vertices[Reciprocated Vertex Pair Ratio])), Vertices[Reciprocated Vertex Pair Ratio] <= Misc!$P$14),OR(NOT(ISNUMBER(Vertices[Followed])), Vertices[Followed] >= Misc!$O$15), OR(NOT(ISNUMBER(Vertices[Followed])), Vertices[Followed] <= Misc!$P$15),OR(NOT(ISNUMBER(Vertices[Followers])), Vertices[Followers] >= Misc!$O$16), OR(NOT(ISNUMBER(Vertices[Followers])), Vertices[Followers] <= Misc!$P$16),OR(NOT(ISNUMBER(Vertices[Tweets])), Vertices[Tweets] >= Misc!$O$17), OR(NOT(ISNUMBER(Vertices[Tweets])), Vertices[Tweets] <= Misc!$P$17),OR(NOT(ISNUMBER(Vertices[Favorites])), Vertices[Favorites] >= Misc!$O$18), OR(NOT(ISNUMBER(Vertices[Favorites])), Vertices[Favorites] <= Misc!$P$18),OR(NOT(ISNUMBER(Vertices[Time Zone UTC Offset (Seconds)])), Vertices[Time Zone UTC Offset (Seconds)] >= Misc!$O$19), OR(NOT(ISNUMBER(Vertices[Time Zone UTC Offset (Seconds)])), Vertices[Time Zone UTC Offset (Seconds)] <= Misc!$P$19),OR(NOT(ISNUMBER(Vertices[Joined Twitter Date (UTC)])), Vertices[Joined Twitter Date (UTC)] >= Misc!$O$20), OR(NOT(ISNUMBER(Vertices[Joined Twitter Date (UTC)])), Vertices[Joined Twitter Date (UTC)] <= Misc!$P$20),TRUE), TRUE, FALSE) -> TRUE | AD29: 617 | AE29: 445627 | AF29: 65527 | AG29: 5208 | AH29: -18000 | AI29: #HearEverything. Defeat Everyone. || Support: @AskTurtleBeach & https://t.co/xhpZRMR8Zl || Add us on Instagram: https://t.co/BWrBB7ac3R | AJ29: San Diego, CA | AK29: https://t.co/sbHuPfzpm3 | AL29: Eastern Time (US & Canada) | AM29: 39950.789 | AN29: Open Twitter Page for This Person | AO29: https://twitter.com/turtlebeach | AP29: No
A30: napoan | B30: Red | D30: 2.03125 | E30: 10.099552 | F30: http://pbs.twimg.com/profile_images/855773232120582144/MY_UNJWL_normal.jpg | K30: napoan | M30: 5853.3047 | N30: 6901.7534 | S30: 16 | T30: 0 | U30: 240 | V30: 0.0625 | W30: 0 | X30: 7.891889 | Y30: 0 | Z30: 0 | AA30: 30 | AB30: =IF(AND(OR(NOT(ISNUMBER(Vertices[Size])), Vertices[Size] >= Misc!$O$4), OR(NOT(ISNUMBER(Vertices[Size])), Vertices[Size] <= Misc!$P$4),OR(NOT(ISNUMBER(Vertices[X])), Vertices[X] >= Misc!$O$5), OR(NOT(ISNUMBER(Vertices[X])), Vertices[X] <= Misc!$P$5),OR(NOT(ISNUMBER(Vertices[Y])), Vertices[Y] >= Misc!$O$6), OR(NOT(ISNUMBER(Vertices[Y])), Vertices[Y] <= Misc!$P$6),OR(NOT(ISNUMBER(Vertices[In-Degree])), Vertices[In-Degree] >= Misc!$O$7), OR(NOT(ISNUMBER(Vertices[In-Degree])), Vertices[In-Degree] <= Misc!$P$7),OR(NOT(ISNUMBER(Vertices[Out-Degree])), Vertices[Out-Degree] >= Misc!$O$8), OR(NOT(ISNUMBER(Vertices[Out-Degree])), Vertices[Out-Degree] <= Misc!$P$8),OR(NOT(ISNUMBER(Vertices[Betweenness Centrality])), Vertices[Betweenness Centrality] >= Misc!$O$9), OR(NOT(ISNUMBER(Vertices[Betweenness Centrality])), Vertices[Betweenness Centrality] <= Misc!$P$9),OR(NOT(ISNUMBER(Vertices[Closeness Centrality])), Vertices[Closeness Centrality] >= Misc!$O$10), OR(NOT(ISNUMBER(Vertices[Closeness Centrality])), Vertices[Closeness Centrality] <= Misc!$P$10),OR(NOT(ISNUMBER(Vertices[Eigenvector Centrality])), Vertices[Eigenvector Centrality] >= Misc!$O$11), OR(NOT(ISNUMBER(Vertices[Eigenvector Centrality])), Vertices[Eigenvector Centrality] <= Misc!$P$11),OR(NOT(ISNUMBER(Vertices[PageRank])), Vertices[PageRank] >= Misc!$O$12), OR(NOT(ISNUMBER(Vertices[PageRank])), Vertices[PageRank] <= Misc!$P$12),OR(NOT(ISNUMBER(Vertices[Clustering Coefficient])), Vertices[Clustering Coefficient] >= Misc!$O$13), OR(NOT(ISNUMBER(Vertices[Clustering Coefficient])), Vertices[Clustering Coefficient] <= Misc!$P$13),OR(NOT(ISNUMBER(Vertices[Reciprocated Vertex Pair Ratio])), Vertices[Reciprocated Vertex Pair Ratio] >= Misc!$O$14), OR(NOT(ISNUMBER(Vertices[Reciprocated Vertex Pair Ratio])), Vertices[Reciprocated Vertex Pair Ratio] <= Misc!$P$14),OR(NOT(ISNUMBER(Vertices[Followed])), Vertices[Followed] >= Misc!$O$15), OR(NOT(ISNUMBER(Vertices[Followed])), Vertices[Followed] <= Misc!$P$15),OR(NOT(ISNUMBER(Vertices[Followers])), Vertices[Followers] >= Misc!$O$16), OR(NOT(ISNUMBER(Vertices[Followers])), Vertices[Followers] <= Misc!$P$16),OR(NOT(ISNUMBER(Vertices[Tweets])), Vertices[Tweets] >= Misc!$O$17), OR(NOT(ISNUMBER(Vertices[Tweets])), Vertices[Tweets] <= Misc!$P$17),OR(NOT(ISNUMBER(Vertices[Favorites])), Vertices[Favorites] >= Misc!$O$18), OR(NOT(ISNUMBER(Vertices[Favorites])), Vertices[Favorites] <= Misc!$P$18),OR(NOT(ISNUMBER(Vertices[Time Zone UTC Offset (Seconds)])), Vertices[Time Zone UTC Offset (Seconds)] >= Misc!$O$19), OR(NOT(ISNUMBER(Vertices[Time Zone UTC Offset (Seconds)])), Vertices[Time Zone UTC Offset (Seconds)] <= Misc!$P$19),OR(NOT(ISNUMBER(Vertices[Joined Twitter Date (UTC)])), Vertices[Joined Twitter Date (UTC)] >= Misc!$O$20), OR(NOT(ISNUMBER(Vertices[Joined Twitter Date (UTC)])), Vertices[Joined Twitter Date (UTC)] <= Misc!$P$20),TRUE), TRUE, FALSE) -> TRUE | AD30: 2165 | AE30: 10421 | AF30: 10033 | AG30: 13211 | AH30: 32400 | AI30: いつの間にか訪問者数日本一になりました。やたら検索妨害してくるやべーやつです。名前を間違えられた回数も多分日本一です。Minecraft(マインクラフト)のアップデート情報とかPV自慢とかつぶやきます・Steam/Origin/PSN:napoan・Discord:napoan#5674 フレンド申請お気軽にどうぞ🤗 | AJ30: 滅多に人が来ない岡山の県南 | AK30: https://t.co/oB9epGXlzc | AL30: Tokyo | AM30: 41355.549 | AN30: Open Twitter Page for This Person | AO30: https://twitter.com/napoan | AP30: No
A31: tesco | B31: Red | D31: 2.0666695 | E31: 10.087108 | F31: http://pbs.twimg.com/profile_images/884777664514576385/CbGSu8MT_normal.jpg | K31: tesco | M31: 5540.3345 | N31: 3796.5352 | S31: 15 | T31: 0 | U31: 210 | V31: 0.066667 | W31: 0 | X31: 7.43243 | Y31: 0 | Z31: 0 | AA31: 31 | AB31: =IF(AND(OR(NOT(ISNUMBER(Vertices[Size])), Vertices[Size] >= Misc!$O$4), OR(NOT(ISNUMBER(Vertices[Size])), Vertices[Size] <= Misc!$P$4),OR(NOT(ISNUMBER(Vertices[X])), Vertices[X] >= Misc!$O$5), OR(NOT(ISNUMBER(Vertices[X])), Vertices[X] <= Misc!$P$5),OR(NOT(ISNUMBER(Vertices[Y])), Vertices[Y] >= Misc!$O$6), OR(NOT(ISNUMBER(Vertices[Y])), Vertices[Y] <= Misc!$P$6),OR(NOT(ISNUMBER(Vertices[In-Degree])), Vertices[In-Degree] >= Misc!$O$7), OR(NOT(ISNUMBER(Vertices[In-Degree])), Vertices[In-Degree] <= Misc!$P$7),OR(NOT(ISNUMBER(Vertices[Out-Degree])), Vertices[Out-Degree] >= Misc!$O$8), OR(NOT(ISNUMBER(Vertices[Out-Degree])), Vertices[Out-Degree] <= Misc!$P$8),OR(NOT(ISNUMBER(Vertices[Betweenness Centrality])), Vertices[Betweenness Centrality] >= Misc!$O$9), OR(NOT(ISNUMBER(Vertices[Betweenness Centrality])), Vertices[Betweenness Centrality] <= Misc!$P$9),OR(NOT(ISNUMBER(Vertices[Closeness Centrality])), Vertices[Closeness Centrality] >= Misc!$O$10), OR(NOT(ISNUMBER(Vertices[Closeness Centrality])), Vertices[Closeness Centrality] <= Misc!$P$10),OR(NOT(ISNUMBER(Vertices[Eigenvector Centrality])), Vertices[Eigenvector Centrality] >= Misc!$O$11), OR(NOT(ISNUMBER(Vertices[Eigenvector Centrality])), Vertices[Eigenvector Centrality] <= Misc!$P$11),OR(NOT(ISNUMBER(Vertices[PageRank])), Vertices[PageRank] >= Misc!$O$12), OR(NOT(ISNUMBER(Vertices[PageRank])), Vertices[PageRank] <= Misc!$P$12),OR(NOT(ISNUMBER(Vertices[Clustering Coefficient])), Vertices[Clustering Coefficient] >= Misc!$O$13), OR(NOT(ISNUMBER(Vertices[Clustering Coefficient])), Vertices[Clustering Coefficient] <= Misc!$P$13),OR(NOT(ISNUMBER(Vertices[Reciprocated Vertex Pair Ratio])), Vertices[Reciprocated Vertex Pair Ratio] >= Misc!$O$14), OR(NOT(ISNUMBER(Vertices[Reciprocated Vertex Pair Ratio])), Vertices[Reciprocated Vertex Pair Ratio] <= Misc!$P$14),OR(NOT(ISNUMBER(Vertices[Followed])), Vertices[Followed] >= Misc!$O$15), OR(NOT(ISNUMBER(Vertices[Followed])), Vertices[Followed] <= Misc!$P$15),OR(NOT(ISNUMBER(Vertices[Followers])), Vertices[Followers] >= Misc!$O$16), OR(NOT(ISNUMBER(Vertices[Followers])), Vertices[Followers] <= Misc!$P$16),OR(NOT(ISNUMBER(Vertices[Tweets])), Vertices[Tweets] >= Misc!$O$17), OR(NOT(ISNUMBER(Vertices[Tweets])), Vertices[Tweets] <= Misc!$P$17),OR(NOT(ISNUMBER(Vertices[Favorites])), Vertices[Favorites] >= Misc!$O$18), OR(NOT(ISNUMBER(Vertices[Favorites])), Vertices[Favorites] <= Misc!$P$18),OR(NOT(ISNUMBER(Vertices[Time Zone UTC Offset (Seconds)])), Vertices[Time Zone UTC Offset (Seconds)] >= Misc!$O$19), OR(NOT(ISNUMBER(Vertices[Time Zone UTC Offset (Seconds)])), Vertices[Time Zone UTC Offset (Seconds)] <= Misc!$P$19),OR(NOT(ISNUMBER(Vertices[Joined Twitter Date (UTC)])), Vertices[Joined Twitter Date (UTC)] >= Misc!$O$20), OR(NOT(ISNUMBER(Vertices[Joined Twitter Date (UTC)])), Vertices[Joined Twitter Date (UTC)] <= Misc!$P$20),TRUE), TRUE, FALSE) -> TRUE | AD31: 169923 | AE31: 515175 | AF31: 1865695 | AG31: 3559 | AH31: 0 | AI31: Every little helps. Follow us for quick and easy recipes, food inspiration and helpful home hacks. Customer care for UK customers is here 24/7 | AK31: https://t.co/ABQcsq7Bz5 | AL31: London | AM31: 40627.658 | AN31: Open Twitter Page for This Person | AO31: https://twitter.com/tesco | AP31: No
A32: team_infused | B32: Red | D32: 1.501921 | E32: 18.042958 | F32: http://pbs.twimg.com/profile_images/2453007492/12vsol6dweu09f047a5a_normal.png | K32: team_infused | M32: 8648.3203 | N32: 6612.1719 | S32: 15 | T32: 0 | U32: 19390 | V32: 0.000226 | W32: 0 | X32: 6.856621 | Y32: 0 | Z32: 0 | AA32: 32 | AB32: =IF(AND(OR(NOT(ISNUMBER(Vertices[Size])), Vertices[Size] >= Misc!$O$4), OR(NOT(ISNUMBER(Vertices[Size])), Vertices[Size] <= Misc!$P$4),OR(NOT(ISNUMBER(Vertices[X])), Vertices[X] >= Misc!$O$5), OR(NOT(ISNUMBER(Vertices[X])), Vertices[X] <= Misc!$P$5),OR(NOT(ISNUMBER(Vertices[Y])), Vertices[Y] >= Misc!$O$6), OR(NOT(ISNUMBER(Vertices[Y])), Vertices[Y] <= Misc!$P$6),OR(NOT(ISNUMBER(Vertices[In-Degree])), Vertices[In-Degree] >= Misc!$O$7), OR(NOT(ISNUMBER(Vertices[In-Degree])), Vertices[In-Degree] <= Misc!$P$7),OR(NOT(ISNUMBER(Vertices[Out-Degree])), Vertices[Out-Degree] >= Misc!$O$8), OR(NOT(ISNUMBER(Vertices[Out-Degree])), Vertices[Out-Degree] <= Misc!$P$8),OR(NOT(ISNUMBER(Vertices[Betweenness Centrality])), Vertices[Betweenness Centrality] >= Misc!$O$9), OR(NOT(ISNUMBER(Vertices[Betweenness Centrality])), Vertices[Betweenness Centrality] <= Misc!$P$9),OR(NOT(ISNUMBER(Vertices[Closeness Centrality])), Vertices[Closeness Centrality] >= Misc!$O$10), OR(NOT(ISNUMBER(Vertices[Closeness Centrality])), Vertices[Closeness Centrality] <= Misc!$P$10),OR(NOT(ISNUMBER(Vertices[Eigenvector Centrality])), Vertices[Eigenvector Centrality] >= Misc!$O$11), OR(NOT(ISNUMBER(Vertices[Eigenvector Centrality])), Vertices[Eigenvector Centrality] <= Misc!$P$11),OR(NOT(ISNUMBER(Vertices[PageRank])), Vertices[PageRank] >= Misc!$O$12), OR(NOT(ISNUMBER(Vertices[PageRank])), Vertices[PageRank] <= Misc!$P$12),OR(NOT(ISNUMBER(Vertices[Clustering Coefficient])), Vertices[Clustering Coefficient] >= Misc!$O$13), OR(NOT(ISNUMBER(Vertices[Clustering Coefficient])), Vertices[Clustering Coefficient] <= Misc!$P$13),OR(NOT(ISNUMBER(Vertices[Reciprocated Vertex Pair Ratio])), Vertices[Reciprocated Vertex Pair Ratio] >= Misc!$O$14), OR(NOT(ISNUMBER(Vertices[Reciprocated Vertex Pair Ratio])), Vertices[Reciprocated Vertex Pair Ratio] <= Misc!$P$14),OR(NOT(ISNUMBER(Vertices[Followed])), Vertices[Followed] >= Misc!$O$15), OR(NOT(ISNUMBER(Vertices[Followed])), Vertices[Followed] <= Misc!$P$15),OR(NOT(ISNUMBER(Vertices[Followers])), Vertices[Followers] >= Misc!$O$16), OR(NOT(ISNUMBER(Vertices[Followers])), Vertices[Followers] <= Misc!$P$16),OR(NOT(ISNUMBER(Vertices[Tweets])), Vertices[Tweets] >= Misc!$O$17), OR(NOT(ISNUMBER(Vertices[Tweets])), Vertices[Tweets] <= Misc!$P$17),OR(NOT(ISNUMBER(Vertices[Favorites])), Vertices[Favorites] >= Misc!$O$18), OR(NOT(ISNUMBER(Vertices[Favorites])), Vertices[Favorites] <= Misc!$P$18),OR(NOT(ISNUMBER(Vertices[Time Zone UTC Offset (Seconds)])), Vertices[Time Zone UTC Offset (Seconds)] >= Misc!$O$19), OR(NOT(ISNUMBER(Vertices[Time Zone UTC Offset (Seconds)])), Vertices[Time Zone UTC Offset (Seconds)] <= Misc!$P$19),OR(NOT(ISNUMBER(Vertices[Joined Twitter Date (UTC)])), Vertices[Joined Twitter Date (UTC)] >= Misc!$O$20), OR(NOT(ISNUMBER(Vertices[Joined Twitter Date (UTC)])), Vertices[Joined Twitter Date (UTC)] <= Misc!$P$20),TRUE), TRUE, FALSE) -> TRUE | AD32: 182 | AE32: 40094 | AF32: 13535 | AG32: 6273 | AH32: 0 | AI32: Professional Esports Brand Sponsored by: @ASTROGaming @AOC_Gaming @ScufGaming @KontrolFreek @Rockstar_Energy @elgatogaming @BLKSportUK @noblechairs #RedArmy | AJ32: United Kingdom | AK32: https://t.co/jMHAMnbzVP | AL32: London | AM32: 40077.009 | AN32: Open Twitter Page for This Person | AO32: https://twitter.com/team_infused | AP32: No
A33: eunitedgg | B33: Red | D33: 1.502227 | E33: 10.536197 | F33: http://pbs.twimg.com/profile_images/912832232548470784/MY5jl4Em_normal.jpg | K33: eunitedgg | M33: 5212.5317 | N33: 8096.8706 | S33: 15 | T33: 0 | U33: 1292.6667 | V33: 0.000262 | W33: 0 | X33: 3.448021 | Y33: 0 | Z33: 0 | AA33: 33 | AB33: =IF(AND(OR(NOT(ISNUMBER(Vertices[Size])), Vertices[Size] >= Misc!$O$4), OR(NOT(ISNUMBER(Vertices[Size])), Vertices[Size] <= Misc!$P$4),OR(NOT(ISNUMBER(Vertices[X])), Vertices[X] >= Misc!$O$5), OR(NOT(ISNUMBER(Vertices[X])), Vertices[X] <= Misc!$P$5),OR(NOT(ISNUMBER(Vertices[Y])), Vertices[Y] >= Misc!$O$6), OR(NOT(ISNUMBER(Vertices[Y])), Vertices[Y] <= Misc!$P$6),OR(NOT(ISNUMBER(Vertices[In-Degree])), Vertices[In-Degree] >= Misc!$O$7), OR(NOT(ISNUMBER(Vertices[In-Degree])), Vertices[In-Degree] <= Misc!$P$7),OR(NOT(ISNUMBER(Vertices[Out-Degree])), Vertices[Out-Degree] >= Misc!$O$8), OR(NOT(ISNUMBER(Vertices[Out-Degree])), Vertices[Out-Degree] <= Misc!$P$8),OR(NOT(ISNUMBER(Vertices[Betweenness Centrality])), Vertices[Betweenness Centrality] >= Misc!$O$9), OR(NOT(ISNUMBER(Vertices[Betweenness Centrality])), Vertices[Betweenness Centrality] <= Misc!$P$9),OR(NOT(ISNUMBER(Vertices[Closeness Centrality])), Vertices[Closeness Centrality] >= Misc!$O$10), OR(NOT(ISNUMBER(Vertices[Closeness Centrality])), Vertices[Closeness Centrality] <= Misc!$P$10),OR(NOT(ISNUMBER(Vertices[Eigenvector Centrality])), Vertices[Eigenvector Centrality] >= Misc!$O$11), OR(NOT(ISNUMBER(Vertices[Eigenvector Centrality])), Vertices[Eigenvector Centrality] <= Misc!$P$11),OR(NOT(ISNUMBER(Vertices[PageRank])), Vertices[PageRank] >= Misc!$O$12), OR(NOT(ISNUMBER(Vertices[PageRank])), Vertices[PageRank] <= Misc!$P$12),OR(NOT(ISNUMBER(Vertices[Clustering Coefficient])), Vertices[Clustering Coefficient] >= Misc!$O$13), OR(NOT(ISNUMBER(Vertices[Clustering Coefficient])), Vertices[Clustering Coefficient] <= Misc!$P$13),OR(NOT(ISNUMBER(Vertices[Reciprocated Vertex Pair Ratio])), Vertices[Reciprocated Vertex Pair Ratio] >= Misc!$O$14), OR(NOT(ISNUMBER(Vertices[Reciprocated Vertex Pair Ratio])), Vertices[Reciprocated Vertex Pair Ratio] <= Misc!$P$14),OR(NOT(ISNUMBER(Vertices[Followed])), Vertices[Followed] >= Misc!$O$15), OR(NOT(ISNUMBER(Vertices[Followed])), Vertices[Followed] <= Misc!$P$15),OR(NOT(ISNUMBER(Vertices[Followers])), Vertices[Followers] >= Misc!$O$16), OR(NOT(ISNUMBER(Vertices[Followers])), Vertices[Followers] <= Misc!$P$16),OR(NOT(ISNUMBER(Vertices[Tweets])), Vertices[Tweets] >= Misc!$O$17), OR(NOT(ISNUMBER(Vertices[Tweets])), Vertices[Tweets] <= Misc!$P$17),OR(NOT(ISNUMBER(Vertices[Favorites])), Vertices[Favorites] >= Misc!$O$18), OR(NOT(ISNUMBER(Vertices[Favorites])), Vertices[Favorites] <= Misc!$P$18),OR(NOT(ISNUMBER(Vertices[Time Zone UTC Offset (Seconds)])), Vertices[Time Zone UTC Offset (Seconds)] >= Misc!$O$19), OR(NOT(ISNUMBER(Vertices[Time Zone UTC Offset (Seconds)])), Vertices[Time Zone UTC Offset (Seconds)] <= Misc!$P$19),OR(NOT(ISNUMBER(Vertices[Joined Twitter Date (UTC)])), Vertices[Joined Twitter Date (UTC)] >= Misc!$O$20), OR(NOT(ISNUMBER(Vertices[Joined Twitter Date (UTC)])), Vertices[Joined Twitter Date (UTC)] <= Misc!$P$20),TRUE), TRUE, FALSE) -> TRUE | AD33: 53 | AE33: 31531 | AF33: 5235 | AG33: 6661 | AH33: -28800 | AI33: Unifying esports fans & players. Teams in League of Legends, Call of Duty, SMITE & Gears of War. Partnered with @ASTROGaming & @SCUFGaming | AJ33: Los Angeles, CA | AK33: https://t.co/4N06oC4WAk | AL33: Pacific Time (US & Canada) | AM33: 42581.968 | AN33: Open Twitter Page for This Person | AO33: https://twitter.com/eunitedgg | AP33: No
A34: legitmeow | B34: Red | D34: 2.0666695 | E34: 10.087108 | F34: http://pbs.twimg.com/profile_images/901958724180312066/7BOyvoar_normal.jpg | K34: legitmeow | M34: 3512.1482 | N34: 7053.0557 | S34: 15 | T34: 0 | U34: 210 | V34: 0.066667 | W34: 0 | X34: 7.43243 | Y34: 0 | Z34: 0 | AA34: 34 | AB34: =IF(AND(OR(NOT(ISNUMBER(Vertices[Size])), Vertices[Size] >= Misc!$O$4), OR(NOT(ISNUMBER(Vertices[Size])), Vertices[Size] <= Misc!$P$4),OR(NOT(ISNUMBER(Vertices[X])), Vertices[X] >= Misc!$O$5), OR(NOT(ISNUMBER(Vertices[X])), Vertices[X] <= Misc!$P$5),OR(NOT(ISNUMBER(Vertices[Y])), Vertices[Y] >= Misc!$O$6), OR(NOT(ISNUMBER(Vertices[Y])), Vertices[Y] <= Misc!$P$6),OR(NOT(ISNUMBER(Vertices[In-Degree])), Vertices[In-Degree] >= Misc!$O$7), OR(NOT(ISNUMBER(Vertices[In-Degree])), Vertices[In-Degree] <= Misc!$P$7),OR(NOT(ISNUMBER(Vertices[Out-Degree])), Vertices[Out-Degree] >= Misc!$O$8), OR(NOT(ISNUMBER(Vertices[Out-Degree])), Vertices[Out-Degree] <= Misc!$P$8),OR(NOT(ISNUMBER(Vertices[Betweenness Centrality])), Vertices[Betweenness Centrality] >= Misc!$O$9), OR(NOT(ISNUMBER(Vertices[Betweenness Centrality])), Vertices[Betweenness Centrality] <= Misc!$P$9),OR(NOT(ISNUMBER(Vertices[Closeness Centrality])), Vertices[Closeness Centrality] >= Misc!$O$10), OR(NOT(ISNUMBER(Vertices[Closeness Centrality])), Vertices[Closeness Centrality] <= Misc!$P$10),OR(NOT(ISNUMBER(Vertices[Eigenvector Centrality])), Vertices[Eigenvector Centrality] >= Misc!$O$11), OR(NOT(ISNUMBER(Vertices[Eigenvector Centrality])), Vertices[Eigenvector Centrality] <= Misc!$P$11),OR(NOT(ISNUMBER(Vertices[PageRank])), Vertices[PageRank] >= Misc!$O$12), OR(NOT(ISNUMBER(Vertices[PageRank])), Vertices[PageRank] <= Misc!$P$12),OR(NOT(ISNUMBER(Vertices[Clustering Coefficient])), Vertices[Clustering Coefficient] >= Misc!$O$13), OR(NOT(ISNUMBER(Vertices[Clustering Coefficient])), Vertices[Clustering Coefficient] <= Misc!$P$13),OR(NOT(ISNUMBER(Vertices[Reciprocated Vertex Pair Ratio])), Vertices[Reciprocated Vertex Pair Ratio] >= Misc!$O$14), OR(NOT(ISNUMBER(Vertices[Reciprocated Vertex Pair Ratio])), Vertices[Reciprocated Vertex Pair Ratio] <= Misc!$P$14),OR(NOT(ISNUMBER(Vertices[Followed])), Vertices[Followed] >= Misc!$O$15), OR(NOT(ISNUMBER(Vertices[Followed])), Vertices[Followed] <= Misc!$P$15),OR(NOT(ISNUMBER(Vertices[Followers])), Vertices[Followers] >= Misc!$O$16), OR(NOT(ISNUMBER(Vertices[Followers])), Vertices[Followers] <= Misc!$P$16),OR(NOT(ISNUMBER(Vertices[Tweets])), Vertices[Tweets] >= Misc!$O$17), OR(NOT(ISNUMBER(Vertices[Tweets])), Vertices[Tweets] <= Misc!$P$17),OR(NOT(ISNUMBER(Vertices[Favorites])), Vertices[Favorites] >= Misc!$O$18), OR(NOT(ISNUMBER(Vertices[Favorites])), Vertices[Favorites] <= Misc!$P$18),OR(NOT(ISNUMBER(Vertices[Time Zone UTC Offset (Seconds)])), Vertices[Time Zone UTC Offset (Seconds)] >= Misc!$O$19), OR(NOT(ISNUMBER(Vertices[Time Zone UTC Offset (Seconds)])), Vertices[Time Zone UTC Offset (Seconds)] <= Misc!$P$19),OR(NOT(ISNUMBER(Vertices[Joined Twitter Date (UTC)])), Vertices[Joined Twitter Date (UTC)] >= Misc!$O$20), OR(NOT(ISNUMBER(Vertices[Joined Twitter Date (UTC)])), Vertices[Joined Twitter Date (UTC)] <= Misc!$P$20),TRUE), TRUE, FALSE) -> TRUE | AD34: 1103 | AE34: 20829 | AF34: 12632 | AG34: 31827 | AH34: -28800 | AI34: Sometimes I play Call of Duty. Director @SoaRGaming. #CODWWII #MWRemastered #CSGO #MWR | AJ34: Canada | AK34: https://t.co/tl6CBTa4iQ | AL34: Pacific Time (US & Canada) | AM34: 40474.882 | AN34: Open Twitter Page for This Person | AO34: https://twitter.com/legitmeow | AP34: No
